Workbook

Sheet Trial Balance
A1: Trial Balance
C4: TB1 | E4: TB2 | G4: Adj | I4: Mgt Accs
A5: Account | B5: Balance | C5: Debit | D5: Credit | E5: Debit | F5: Credit | G5: Debit | H5: Credit | I5: Debit | J5: Credit | K5: October | L5: Movement | M5: Category
I6: =G6+C6+E6 -> 0 | J6: =H6+D6+F6 -> 0 | L6: =I6-J6 -> 0 | M6: Fixed assets
I7: =G7+C7+E7 -> 0 | J7: =H7+D7+F7 -> 0 | L7: =I7-J7 -> 0 | M7: Fixed assets
I8: =G8+C8+E8 -> 0 | J8: =H8+D8+F8 -> 0 | L8: =I8-J8 -> 0 | M8: Fixed assets
I9: =G9+C9+E9 -> 0 | J9: =H9+D9+F9 -> 0 | L9: =I9-J9 -> 0 | M9: Fixed assets
I10: =G10+C10+E10 -> 0 | J10: =H10+D10+F10 -> 0 | L10: =I10-J10 -> 0 | M10: Fixed assets
I11: =G11+C11+E11 -> 0 | J11: =H11+D11+F11 -> 0 | L11: =I11-J11 -> 0 | M11: Fixed assets
I12: =G12+C12+E12 -> 0 | J12: =H12+D12+F12 -> 0 | L12: =I12-J12 -> 0 | M12: Fixed assets
I13: =G13+C13+E13 -> 0 | J13: =H13+D13+F13 -> 0 | L13: =I13-J13 -> 0 | M13: Fixed assets
I14: =G14+C14+E14 -> 0 | J14: =H14+D14+F14 -> 0 | L14: =I14-J14 -> 0 | M14: Fixed assets
I15: =G15+C15+E15 -> 0 | J15: =H15+D15+F15 -> 0 | L15: =I15-J15 -> 0 | M15: Intangible assets
I16: =G16+C16+E16 -> 0 | J16: =H16+D16+F16 -> 0 | L16: =I16-J16 -> 0 | M16: Intangible assets
I17: =G17+C17+E17 -> 0 | J17: =H17+D17+F17 -> 0 | L17: =I17-J17 -> 0 | M17: Stock
... I53: =G53+C53+E53 -> 0 | J53: =H53+D53+F53 -> 0 | L53: =I53-J53 -> 0 | M53: P&L
I54: =G54+C54+E54 -> 0 | J54: =H54+D54+F54 -> 0 | L54: =J54-I54-K54 -> 0 | M54: Sales
I55: =G55+C55+E55 -> 0 | J55: =H55+D55+F55 -> 0 | L55: =J55-I55-K55 -> 0 | M55: Sales
I56: =G56+C56+E56 -> 0 | J56: =H56+D56+F56 -> 0 | L56: =J56-I56-K56 -> 0 | M56: Sales
I57: =G57+C57+E57 -> 0 | J57: =H57+D57+F57 -> 0 | L57: =J57-I57-K57 -> 0 | M57: Sales
I58: =G58+C58+E58 -> 0 | J58: =H58+D58+F58 -> 0 | L58: =J58-I58-K58 -> 0 | M58: Sales
I59: =G59+C59+E59 -> 0 | J59: =H59+D59+F59 -> 0 | L59: =J59-I59-K59 -> 0 | M59: Sales
I60: =G60+C60+E60 -> 0 | J60: =H60+D60+F60 -> 0 | L60: =J60-I60-K60 -> 0 | M60: Sales
I61: =G61+C61+E61 -> 0 | J61: =H61+D61+F61 -> 0 | L61: =J61-I61-K61 -> 0 | M61: Sales
I62: =G62+C62+E62 -> 0 | J62: =H62+D62+F62 -> 0 | L62: =J62-I62-K62 -> 0 | M62: Sales
I63: =G63+C63+E63 -> 0 | J63: =H63+D63+F63 -> 0 | L63: =J63-I63-K63 -> 0 | M63: Sales
I64: =G64+C64+E64 -> 0 | J64: =H64+D64+F64 -> 0 | L64: =J64-I64-K64 -> 0 | M64: Direct
I65: =G65+C65+E65 -> 0 | J65: =H65+D65+F65 -> 0 | L65: =J65-I65-K65 -> 0 | M65: Direct
... I86: =G86+C86+E86 -> 0 | J86: =H86+D86+F86 -> 0 | L86: =J86-I86-K86 -> 0 | M86: G&A
I87: =G87+C87+E87 -> 0 | J87: =H87+D87+F87 -> 0 | L87: =J87-I87-K87 -> 0
I88: =G88+C88+E88 -> 0 | J88: =H88+D88+F88 -> 0 | L88: =J88-I88-K88 -> 0 | M88: Direct
I89: =G89+C89+E89 -> 0 | J89: =H89+D89+F89 -> 0 | L89: =J89-I89-K89 -> 0 | M89: Prod Indirect
I90: =G90+C90+E90 -> 0 | J90: =H90+D90+F90 -> 0 | L90: =J90-I90-K90 -> 0 | M90: R&D
I91: =G91+C91+E91 -> 0 | J91: =H91+D91+F91 -> 0 | L91: =J91-I91-K91 -> 0 | M91: S&M
I92: =G92+C92+E92 -> 0 | J92: =H92+D92+F92 -> 0 | L92: =J92-I92-K92 -> 0 | M92: G&A
I93: =G93+C93+E93 -> 0 | J93: =H93+D93+F93 -> 0 | L93: =J93-I93-K93 -> 0
I94: =G94+C94+E94 -> 0 | J94: =H94+D94+F94 -> 0 | L94: =J94-I94-K94 -> 0 | M94: Direct
I95: =G95+C95+E95 -> 0 | J95: =H95+D95+F95 -> 0 | L95: =J95-I95-K95 -> 0 | M95: Prod Indirect
I96: =G96+C96+E96 -> 0 | J96: =H96+D96+F96 -> 0 | L96: =J96-I96-K96 -> 0 | M96: R&D
I97: =G97+C97+E97 -> 0 | J97: =H97+D97+F97 -> 0 | L97: =J97-I97-K97 -> 0 | M97: S&M
I98: =G98+C98+E98 -> 0 | J98: =H98+D98+F98 -> 0 | L98: =J98-I98-K98 -> 0 | M98: G&A
I99: =G99+C99+E99 -> 0 | J99: =H99+D99+F99 -> 0 | L99: =J99-I99-K99 -> 0
I100: =G100+C100+E100 -> 0 | J100: =H100+D100+F100 -> 0 | L100: =J100-I100-K100 -> 0 | M100: G&A
I101: =G101+C101+E101 -> 0 | J101: =H101+D101+F101 -> 0 | L101: =J101-I101-K101 -> 0 | M101: G&A
I102: =G102+C102+E102 -> 0 | J102: =H102+D102+F102 -> 0 | L102: =J102-I102-K102 -> 0 | M102: G&A
I103: =G103+C103+E103 -> 0 | J103: =H103+D103+F103 -> 0 | L103: =J103-I103-K103 -> 0 | M103: G&A
I104: =G104+C104+E104 -> 0 | J104: =H104+D104+F104 -> 0 | L104: =J104-I104-K104 -> 0 | M104: G&A
I105: =G105+C105+E105 -> 0 | J105: =H105+D105+F105 -> 0 | L105: =J105-I105-K105 -> 0 | M105: G&A
I106: =G106+C106+E106 -> 0 | J106: =H106+D106+F106 -> 0 | L106: =J106-I106-K106 -> 0 | M106: G&A
I107: =G107+C107+E107 -> 0 | J107: =H107+D107+F107 -> 0 | L107: =J107-I107-K107 -> 0 | M107: G&A
I108: =G108+C108+E108 -> 0 | J108: =H108+D108+F108 -> 0 | L108: =J108-I108-K108 -> 0 | M108: G&A
I109: =G109+C109+E109 -> 0 | J109: =H109+D109+F109 -> 0 | L109: =J109-I109-K109 -> 0 | M109: G&A
I110: =G110+C110+E110 -> 0 | J110: =H110+D110+F110 -> 0 | L110: =J110-I110-K110 -> 0 | M110: G&A
I111: =G111+C111+E111 -> 0 | J111: =H111+D111+F111 -> 0 | L111: =J111-I111-K111 -> 0 | M111: G&A
... I151: =G151+C151+E151 -> 0 | J151: =H151+D151+F151 -> 0 | L151: =J151-I151-K151 -> 0 | M151: Rent income
I152: =G152+C152+E152 -> 0 | J152: =H152+D152+F152 -> 0 | L152: =J152-I152-K152 -> 0
I153: =G153+C153+E153 -> 0 | J153: =H153+D153+F153 -> 0 | L153: =J153-I153-K153 -> 0 | M153: Building costs
I154: =G154+C154+E154 -> 0 | J154: =H154+D154+F154 -> 0 | L154: =J154-I154-K154 -> 0 | M154: Building costs
I155: =G155+C155+E155 -> 0 | J155: =H155+D155+F155 -> 0 | L155: =J155-I155-K155 -> 0 | M155: Building costs
I156: =G156+C156+E156 -> 0 | J156: =H156+D156+F156 -> 0 | L156: =J156-I156-K156 -> 0 | M156: Building costs
I157: =G157+C157+E157 -> 0 | J157: =H157+D157+F157 -> 0 | L157: =J157-I157-K157 -> 0 | M157: Building costs
I158: =G158+C158+E158 -> 0 | J158: =H158+D158+F158 -> 0 | L158: =J158-I158-K158 -> 0 | M158: Building costs
I159: =G159+C159+E159 -> 0 | J159: =H159+D159+F159 -> 0 | L159: =J159-I159-K159 -> 0 | M159: Building costs
I160: =G160+C160+E160 -> 0 | J160: =H160+D160+F160 -> 0 | L160: =J160-I160-K160 -> 0 | M160: Building costs
I161: =G161+C161+E161 -> 0 | J161: =H161+D161+F161 -> 0 | L161: =J161-I161-K161 -> 0 | M161: Building costs
I162: =G162+C162+E162 -> 0 | J162: =H162+D162+F162 -> 0 | L162: =J162-I162-K162 -> 0 | M162: Building costs
I163: =G163+C163+E163 -> 0 | J163: =H163+D163+F163 -> 0 | L163: =J163-I163-K163 -> 0 | M163: Building costs
I164: =G164+C164+E164 -> 0 | J164: =H164+D164+F164 -> 0 | L164: =J164-I164-K164 -> 0 | M164: Building costs
... I181: =G181+C181+E181 -> 0 | J181: =H181+D181+F181 -> 0 | L181: =J181-I181-K181 -> 0 | M181: Exceptional
I182: =G182+C182+E182 -> 0 | J182: =H182+D182+F182 -> 0 | L182: =I182-J182 -> 0 | M182: Fixed assets
I183: =G183+C183+E183 -> 0 | J183: =H183+D183+F183 -> 0 | L183: =I183-J183 -> 0 | M183: Fixed assets
I184: =G184+C184+E184 -> 0 | J184: =H184+D184+F184 -> 0 | L184: =I184-J184 -> 0 | M184: Fixed assets
I185: =G185+C185+E185 -> 0 | J185: =H185+D185+F185 -> 0 | L185: =I185-J185 -> 0 | M185: Fixed assets
I186: =G186+C186+E186 -> 0 | J186: =H186+D186+F186 -> 0 | L186: =I186-J186 -> 0 | M186: Fixed assets
I187: =G187+C187+E187 -> 0 | J187: =H187+D187+F187 -> 0 | L187: =I187-J187 -> 0 | M187: Fixed assets
I188: =G188+C188+E188 -> 0 | J188: =H188+D188+F188 -> 0 | L188: =I188-J188 -> 0 | M188: Fixed assets
I189: =G189+C189+E189 -> 0 | J189: =H189+D189+F189 -> 0 | L189: =I189-J189 -> 0 | M189: Fixed assets
I190: =G190+C190+E190 -> 0 | J190: =H190+D190+F190 -> 0 | L190: =I190-J190 -> 0 | M190: Investments
I191: =G191+C191+E191 -> 0 | J191: =H191+D191+F191 -> 0 | L191: =I191-J191 -> 0 | M191: Trade debtors
I192: =G192+C192+E192 -> 0 | J192: =H192+D192+F192 -> 0 | L192: =I192-J192 -> 0 | M192: Other Creditors
I193: =G193+C193+E193 -> 0 | J193: =H193+D193+F193 -> 0 | L193: =I193-J193 -> 0 | M193: Other debtors
... I220: =G220+C220+E220 -> 0 | J220: =H220+D220+F220 -> 0 | L220: =I220-J220 -> 0 | M220: Reserves
C221: =SUM(C6:C145) -> 0 | D221: =SUM(D6:D145) -> 0 | E221: =SUM(E6:E220) -> 0 | F221: =SUM(F6:F220) -> 0 | G221: =SUM(G6:G220) -> 0 | H221: =SUM(H6:H220) -> 0 | I221: =SUM(I6:I220) -> 0 | J221: =SUM(J6:J220) -> 0 | K221: =SUM(K6:K220) -> 0 | L221: =SUM(L54:L181)-SUM(L182:L220)-SUM(L6:L53) -> 0
F222: =E221-F221 -> 0 | H222: =G221-H221 -> 0

Sheet TB 1

Sheet TB 2

Sheet Balance Sheet
H1: USD conversion | I1: 1.32 | M1: GBP
B3: Actual | C3: Budget | D3: Variance | G3: Actual | M3: Actual
A4: £'000 | B4: 45931 | C4: 45931 | D4: 45931 | G4: 45627 | M4: 45627
A6: Intangible Assets | B6: ='Trial Balance'!L15+'Trial Balance'!L16 -> 0 | D6: =-(C6-B6) -> 0 | I6: =G6-B6 -> 0
A7: Tangible Assets | D7: =-(C7-B7) -> 0 | G7: =19594*I1 -> 25864.08 | I7: =G7-B7 -> 25864.08 | M7: =19594 -> 19594
A8: Total Fixed Assets | C8: =SUM(C6:C7) -> 0 | D8: =SUM(D6:D7) -> 0 | G8: =SUM(G6:G7) -> 25864.08 | M8: =SUM(M6:M7) -> 19594
D10: =-(C10-B10) -> 0 | G10: 0 | I10: =G10-B10 -> 0 | M10: 0
A11: Trade Debtors | D11: =-(C11-B11) -> 0 | G11: =490043*I1 -> 646856.76 | I11: =G11-B11 -> 646856.76 | M11: =490043 -> 490043
A12: Other debtors | D12: =-(C12-B12) -> 0 | I12: =G12-B12 -> 0
A13: VAT | D13: =-(C13-B13) -> 0 | I13: =G13-B13 -> 0
A14: Cash | D14: =-(C14-B14) -> 0 | G14: =1633703*I1 -> 2156488 | I14: =G14-B14 -> 2156488 | M14: =1633703 -> 1633703
A15: Total Current Assets | B15: =SUM(B10:B14) -> 0 | C15: =SUM(C10:C14) -> 0 | D15: =SUM(D10:D14) -> 0 | G15: =SUM(G10:G14) -> 2803344.7 | M15: =SUM(M10:M14) -> 2123746
A17: Trade Creditors | D17: =-(C17-B17) -> 0 | G17: =(-334279+99000)*I1 -> -310568.28 | I17: =G17-B17 -> -310568.28 | M17: =(-334279+99000) -> -235279
A18: Deferred Tax | D18: =-(C18-B18) -> 0 | I18: =G18-B18 -> 0
A19: Other creditors | D19: =-(C19-B19) -> 0 | I19: =G19-B19 -> 0
A20: Total Current Liabilities | B20: =SUM(B17:B19) -> 0 | C20: =SUM(C17:C19) -> 0 | D20: =SUM(D17:D19) -> 0 | G20: =SUM(G17:G19) -> -310568.28 | M20: =SUM(M17:M19) -> -235279
A22: Loans | D22: =-(C22-B22) -> 0 | G22: =(-192000-99000)*I1 -> -384120 | I22: =G22-B22 -> -384120 | K22: =318000-(9000*3)+G22 -> -93120 | M22: =(-192000-99000) -> -291000
A24: Net Assets | B24: =B8+B15+B20+B22 -> 0 | C24: =C8+C15-C20-C22 -> 0 | D24: =D8+D15+D20+D22 -> 0 | G24: =G8+G15+G20+G22 -> 2134520.5 | M24: =M8+M15+M20+M22 -> 1617061
A26: Share Cap
A27: Share capital | D27: =-(C27-B27) -> 0 | G27: =168*I1 -> 221.76 | I27: =G27-B27 -> 221.76 | M27: =168 -> 168
A28: Share premium | D28: =-(C28-B28) -> 0 | G28: =7328854*I1 -> 9674087.3 | I28: =G28-B28 -> 9674087.3 | M28: =7328854 -> 7328854
A29: Other reserve | D29: =-(C29-B29) -> 0 | I29: =G29-B29 -> 0
A30: BFWD retained earnings | D30: =-(C30-B30) -> 0 | G30: =-5711961*I1 -> -7539788.5 | I30: =G30-B30 -> -7539788.5 | M30: =-5711961 -> -5711961
A31: 2025 P&L | D31: =-(C31-B31) -> 0 | I31: =G31-B31 -> 0 | J31: =I31+'P&L'!AL39 -> 0
B32: =SUM(B27:B31) -> 0 | C32: =SUM(C27:C31) -> 0 | D32: =SUM(D27:D31) -> 0 | G32: =SUM(G27:G31) -> 2134520.5 | M32: =SUM(M27:M31) -> 1617061
A34: Difference | B34: =B24-B32 -> 0 | C34: =C24-C32 -> 0 | D34: =D24-D32 -> 0 | G34: =G24-G32 -> 0 | M34: =M24-M32 -> 0

Sheet All In One
B1: Opening Balance Sheet | C1: Movement | D1: 45627 | E1: Movement | F1: 45931 | G1: Movement | H1: =F1+31 -> 45962 | I1: Movement | J1: =H1+31 -> 45993 | K1: Movement | L1: =J1+31 -> 46024 | M1: Movement | N1: =L1+31 -> 46055 | O1: Movement | P1: =N1+31 -> 46086 | Q1: Movement | R1: =P1+31 -> 46117 | S1: Movement | T1: =R1+31 -> 46148 | V1: =T1+31 -> 46179 | X1: =V1+31 -> 46210 | Z1: =X1+31 -> 46241 | AB1: =Z1+31 -> 46272 | AD1: =AB1+31 -> 46303 | AF1: =AD1+31 -> 46334 | AH1: =AF1+31 -> 46365 | AJ1: =AH1+31 -> 46396 | AL1: =AJ1+31 -> 46427 | AN1: =AL1+31 -> 46458 | AP1: =AN1+31 -> 46489 | AR1: =AP1+31 -> 46520 | AT1: =AR1+31 -> 46551 | AV1: =AT1+31 -> 46582 | AX1: =AV1+31 -> 46613 | AZ1: =AX1+31 -> 46644 | BB1: =AZ1+31 -> 46675 | BD1: =BB1+31 -> 46706 | BF1: =BD1+31 -> 46737 | BH1: =BF1+31 -> 46768 | BJ1: =BH1+31 -> 46799 | BL1: =BJ1+31 -> 46830 | BN1: =BL1+31 -> 46861 | BP1: =BN1+31 -> 46892 | BR1: =BP1+31 -> 46923 | BT1: =BR1+31 -> 46954 | BV1: =BT1+31 -> 46985 | BX1: =BV1+31 -> 47016 | BZ1: =BX1+31 -> 47047 | CB1: =BZ1+31 -> 47078 | CD1: =CB1+31 -> 47109 | CF1: =CD1+31 -> 47140 | CH1: =CF1+31 -> 47171 | CJ1: =CH1+31 -> 47202 | CL1: =CJ1+31 -> 47233 | CN1: =CL1+31 -> 47264 | CP1: =CN1+31 -> 47295 | CR1: =CP1+31 -> 47326 | CT1: =CR1+31 -> 47357 | CV1: =CT1+31 -> 47388 | CX1: =CV1+31 -> 47419 | CZ1: =CX1+31 -> 47450 | DB1: =CZ1+30 -> 47480 | DD1: =DB1+31 -> 47511 | DF1: =DD1+30 -> 47541 | DH1: =DF1+31 -> 47572 | DJ1: =DH1+31 -> 47603 | DL1: =DJ1+30 -> 47633 | DN1: =DL1+30 -> 47663 | DP1: =DN1+30 -> 47693 | DR1: =DP1+30 -> 47723 | DT1: =DR1+30 -> 47753 | DV1: =DT1+30 -> 47783 | DX1: =DV1+30 -> 47813 | DZ1: =DX1+30 -> 47843 | EB1: =DZ1+30 -> 47873 | ED1: =EB1+30 -> 47903 | EF1: =ED1+30 -> 47933 | EH1: =EF1+30 -> 47963 | EJ1: =EH1+30 -> 47993 | EL1: =EJ1+30 -> 48023 | EN1: =EL1+30 -> 48053 | EP1: =EN1+30 -> 48083 | ER1: =EP1+30 -> 48113 | ET1: =ER1+30 -> 48143 | EV1: =ET1+30 -> 48173 | EX1: =EV1+30 -> 48203
A2: £'000
A4: Cash | B4: ='Balance Sheet'!G14 -> 2156488 | D4: =B4 -> 2156488 | F4: =D4+SUM(E6:E66) -> 1379580.2 | H4: =F4+SUM(G6:G66) -> 1145722.3 | J4: =H4+SUM(I6:I66) -> 1114771.9 | L4: =J4+SUM(K6:K65) -> 525369.07 | N4: =L4+SUM(M6:M65) -> 234504.52 | P4: =N4+SUM(O6:O65) -> 386849.97 | R4: =P4+SUM(Q6:Q65) -> 218691.12 | T4: =R4+SUM(S6:S66) -> -113381.73 | V4: =T4+SUM(U6:U66) -> -348684.37 | X4: =V4+SUM(W6:W66) -> -615345.67 | Z4: =X4+SUM(Y6:Y66) -> -873574.97 | AB4: =Z4+SUM(AA6:AA66) -> -1076995.3 | AD4: =AB4+SUM(AC6:AC66) -> -1235968.2 | AF4: =AD4+SUM(AE6:AE66) -> -1451911 | AH4: =AF4+SUM(AG6:AG66) -> -1552403.9 | AJ4: =AH4+SUM(AI6:AI66) -> -1730071.2 | AL4: =AJ4+SUM(AK6:AK66) -> -1906464.3 | AN4: =AL4+SUM(AM6:AM66) -> -2248839.1 | AP4: =AN4+SUM(AO6:AO66) -> -2411916.9 | AR4: =AP4+SUM(AQ6:AQ66) -> -2859590.1 | AT4: =AR4+SUM(AS6:AS66) -> -3366634.3 | AV4: =AT4+SUM(AU6:AU66) -> -3716325 | AX4: =AV4+SUM(AW6:AW66) -> -4040136.2 | AZ4: =AX4+SUM(AY6:AY66) -> -4291009.4 | BB4: =AZ4+SUM(BA6:BA66) -> -4488851.4 | BD4: =BB4+SUM(BC6:BC66) -> -4696615.9 | BF4: =BD4+SUM(BE6:BE66) -> -4881477.8 | BH4: =BF4+SUM(BG6:BG66) -> -5078815.3 | BJ4: =BH4+SUM(BI6:BI66) -> -5127625.5 | BL4: =BJ4+SUM(BK6:BK66) -> -5328038.9 | BN4: =BL4+SUM(BM6:BM66) -> -5289155 | BP4: =BN4+SUM(BO6:BO66) -> -5228321.3 | BR4: =BP4+SUM(BQ6:BQ66) -> -5416360.7 | BT4: =BR4+SUM(BS6:BS66) -> -5499948.4 | BV4: =BT4+SUM(BU6:BU66) -> -5503661 | BX4: =BV4+SUM(BW6:BW66) -> -5417218.7 | BZ4: =BX4+SUM(BY6:BY66) -> -5427463.8 | CB4: =BZ4+SUM(CA6:CA66) -> -5364459 | CD4: =CB4+SUM(CC6:CC66) -> -5216933.3 | CF4: =CD4+SUM(CE6:CE66) -> -4689759.4 | CH4: =CF4+SUM(CG6:CG66) -> -4220448.3 | CJ4: =CH4+SUM(CI6:CI66) -> -3827594.7 | CL4: =CJ4+SUM(CK6:CK66) -> -3349243.1 | CN4: =CL4+SUM(CM6:CM66) -> -2647637.4 | CP4: =CN4+SUM(CO6:CO66) -> -1638331.7 | CR4: =CP4+SUM(CQ6:CQ66) -> -767316.79 | CT4: =CR4+SUM(CS6:CS66) -> 228583.95 | CV4: =CT4+SUM(CU6:CU66) -> 1347709.7 | CX4: =CV4+SUM(CW6:CW66) -> 2709668.8 | CZ4: =CX4+SUM(CY6:CY66) -> 3976815.3 | DB4: =CZ4+SUM(DA6:DA66) -> 5474170.2 | DD4: =DB4+SUM(DC6:DC66) -> 7401074.8 | DF4: =DD4+SUM(DE6:DE66) -> 9685340.5 | DH4: =DF4+SUM(DG6:DG66) -> 12032523 | DJ4: =DH4+SUM(DI6:DI66) -> 14243764 | DL4: =DJ4+SUM(DK6:DK66) -> 16725176 | DN4: =DL4+SUM(DM6:DM66) -> 19446059 | DP4: =DN4+SUM(DO6:DO66) -> 22254983 | DR4: =DP4+SUM(DQ6:DQ66) -> 25240270 | DT4: =DR4+SUM(DS6:DS66) -> 28607699 | DV4: =DT4+SUM(DU6:DU66) -> 32359149 | DX4: =DV4+SUM(DW6:DW66) -> 36159952 | DZ4: =DX4+SUM(DY6:DY66) -> 40284131 | EB4: =DZ4+SUM(EA6:EA66) -> 44993139 | ED4: =EB4+SUM(EC6:EC66) -> 50055776 | EF4: =ED4+SUM(EE6:EE66) -> 55022475 | EH4: =EF4+SUM(EG6:EG66) -> 60138050 | EJ4: =EH4+SUM(EI6:EI66) -> 65713552 | EL4: =EJ4+SUM(EK6:EK66) -> 71415918 | EN4: =EL4+SUM(EM6:EM66) -> 77136493 | EP4: =EN4+SUM(EO6:EO66) -> 83240484 | ER4: =EP4+SUM(EQ6:EQ66) -> 89851475 | ET4: =ER4+SUM(ES6:ES66) -> 96384695 | EV4: =ET4+SUM(EU6:EU66) -> 1.0308733e+08 | EX4: =EV4+SUM(EW6:EW66) -> 1.1010514e+08
A6: Intangible Assets | B6: ='Balance Sheet'!G6 -> 0 | D6: =B6 -> 0 | E6: =D6-F6 -> 0 | F6: =Budgets!D67 -> 0 | G6: =F6-H6 -> 0 | H6: =Budgets!E67 -> 0 | I6: =H6-J6 -> 0 | J6: =Budgets!F67 -> 0 | K6: =J6-L6 -> 0 | L6: =Budgets!G67 -> 0 | M6: =L6-N6 -> 0 | N6: =Budgets!H67 -> 0 | O6: =N6-P6 -> 0 | P6: =Budgets!I67 -> 0 | Q6: =P6-R6 -> 0 | R6: =Budgets!J67 -> 0 | S6: =R6-T6 -> 0 | T6: =Budgets!K67 -> 0 | U6: =T6-V6 -> 0 | V6: =Budgets!L67 -> 0 | W6: =V6-X6 -> 0 | X6: =Budgets!M67 -> 0 | Y6: =X6-Z6 -> 0 | Z6: =Budgets!N67 -> 0 | AA6: =Z6-AB6 -> 0 | AB6: =Budgets!O67 -> 0 | AC6: =AB6-AD6 -> 0 | AD6: =Budgets!P67 -> 0 | AE6: =AD6-AF6 -> 0 | AF6: =Budgets!Q67 -> 0 | AG6: =AF6-AH6 -> 0 | AH6: =Budgets!R67 -> 0 | AI6: =AH6-AJ6 -> 0 | AJ6: =Budgets!S67 -> 0 | AK6: =AJ6-AL6 -> 0 | AL6: =Budgets!T67 -> 0 | AM6: =AL6-AN6 -> 0 | AN6: =Budgets!U67 -> 0 | AO6: =AN6-AP6 -> 0 | AP6: =Budgets!V67 -> 0 | AQ6: =AP6-AR6 -> 0 | AR6: =Budgets!W67 -> 0 | AS6: =AR6-AT6 -> 0 | AT6: =Budgets!X67 -> 0 | AU6: =AT6-AV6 -> 0 | AV6: =Budgets!Y67 -> 0 | AW6: =AV6-AX6 -> 0 | AX6: =Budgets!Z67 -> 0 | AY6: =AX6-AZ6 -> 0 | AZ6: =Budgets!AA67 -> 0 | BA6: =AZ6-AH6 -> 0 | BB6: =Budgets!AB67 -> 0 | BC6: =AH6-BD6 -> 0 | BD6: =Budgets!AC67 -> 0 | BE6: =BD6-BF6 -> 0 | BF6: =Budgets!AD67 -> 0 | BG6: =BF6-BH6 -> 0 | BH6: =Budgets!AE67 -> 0 | BI6: =BH6-BJ6 -> 0 | BJ6: =Budgets!AF67 -> 0 | BK6: =BJ6-BL6 -> 0 | BL6: =Budgets!AG67 -> 0 | BM6: =BL6-BN6 -> 0 | BN6: =Budgets!AH67 -> 0 | BO6: =BN6-BP6 -> 0 | BP6: =Budgets!AI67 -> 0 | BQ6: =BP6-BR6 -> 0 | BR6: =Budgets!AJ67 -> 0 | BS6: =BR6-BT6 -> 0 | BT6: =Budgets!AK67 -> 0 | BU6: =BT6-BV6 -> 0 | BV6: =Budgets!AL67 -> 0 | BW6: =BV6-BX6 -> 0 | BX6: =Budgets!AM67 -> 0 | BY6: =BX6-BZ6 -> 0 | BZ6: =Budgets!AN67 -> 0 | CA6: =BZ6-CB6 -> 0 | CB6: =Budgets!AO67 -> 0 | CC6: =CB6-CD6 -> 0 | CD6: =Budgets!AP67 -> 0 | CE6: =CD6-CF6 -> 0 | CF6: =Budgets!AQ67 -> 0 | CG6: =CF6-CH6 -> 0 | CH6: =Budgets!AR67 -> 0 | CI6: =CH6-CJ6 -> 0 | CJ6: =Budgets!AS67 -> 0 | CK6: =CJ6-CL6 -> 0 | CL6: =Budgets!AT67 -> 0 | CM6: =CL6-CN6 -> 0 | CN6: =Budgets!AU67 -> 0 | CO6: =CN6-CP6 -> 0 | CP6: =Budgets!AV67 -> 0 | CQ6: =CP6-CR6 -> 0 | CR6: =Budgets!AW67 -> 0 | CS6: =CR6-CT6 -> 0 | CT6: =Budgets!AX67 -> 0 | CU6: =CT6-CV6 -> 0 | CV6: =Budgets!AY67 -> 0 | CW6: =CV6-CX6 -> 0 | CX6: =Budgets!AZ67 -> 0 | CY6: =CX6-CZ6 -> 0 | CZ6: =Budgets!BA67 -> 0 | DA6: =CZ6-DB6 -> 0 | DB6: =Budgets!BB67 -> 0 | DC6: =DB6-DD6 -> 0 | DD6: =Budgets!BC67 -> 0 | DE6: =DD6-DF6 -> 0 | DF6: =Budgets!BD67 -> 0 | DG6: =DF6-DH6 -> 0 | DH6: =Budgets!BE67 -> 0 | DI6: =DH6-DJ6 -> 0 | DJ6: =Budgets!BF67 -> 0 | DK6: =DJ6-DL6 -> 0 | DL6: =Budgets!BG67 -> 0 | DM6: =DL6-DN6 -> 0 | DN6: =Budgets!BH67 -> 0 | DO6: =DN6-DP6 -> 0 | DP6: =Budgets!BI67 -> 0 | DQ6: =DP6-DR6 -> 0 | DR6: =Budgets!BJ67 -> 0 | DS6: =DR6-DT6 -> 0 | DT6: =Budgets!BK67 -> 0 | DU6: =DT6-DV6 -> 0 | DV6: =Budgets!BL67 -> 0 | DW6: =DV6-DX6 -> 0 | DX6: =Budgets!BM67 -> 0 | DY6: =DX6-DZ6 -> 0 | DZ6: =Budgets!BN67 -> 0 | EA6: =DZ6-EB6 -> 0 | EB6: =Budgets!BO67 -> 0 | EC6: =EB6-ED6 -> 0 | ED6: =Budgets!BP67 -> 0 | EE6: =ED6-EF6 -> 0 | EF6: =Budgets!BQ67 -> 0 | EG6: =EF6-EH6 -> 0 | EH6: =Budgets!BR67 -> 0 | EI6: =EH6-EJ6 -> 0 | EJ6: =Budgets!BS67 -> 0 | EK6: =EJ6-EL6 -> 0 | EL6: =Budgets!BT67 -> 0 | EM6: =EL6-EN6 -> 0 | EN6: =Budgets!BU67 -> 0 | EO6: =EN6-EP6 -> 0 | EP6: =Budgets!BV67 -> 0 | EQ6: =EP6-ER6 -> 0 | ER6: =Budgets!BW67 -> 0 | ES6: =ER6-ET6 -> 0 | ET6: =Budgets!BX67 -> 0 | EU6: =ET6-EV6 -> 0 | EV6: =Budgets!BY67 -> 0 | EW6: =EV6-EX6 -> 0 | EX6: =Budgets!BZ67 -> 0
A7: Tangible Assets | B7: ='Balance Sheet'!G7 -> 25864.08 | D7: =B7 -> 25864.08 | E7: =D7-F7 -> -19109.64 | F7: =Budgets!D68 -> 44973.72 | G7: =F7-H7 -> -661.16 | H7: =Budgets!E68 -> 45634.88 | I7: =H7-J7 -> 0 | J7: =Budgets!F68 -> 45634.88 | K7: =J7-L7 -> -1226.095 | L7: =Budgets!G68 -> 46860.975 | M7: =L7-N7 -> 2873.905 | N7: =Budgets!H68 -> 43987.07 | O7: =N7-P7 -> 3373.905 | P7: =Budgets!I68 -> 40613.165 | Q7: =P7-R7 -> 3873.905 | R7: =Budgets!J68 -> 36739.26 | S7: =R7-T7 -> 3873.905 | T7: =Budgets!K68 -> 32865.355 | U7: =T7-V7 -> 3873.905 | V7: =Budgets!L68 -> 28991.45 | W7: =V7-X7 -> 3873.905 | X7: =Budgets!M68 -> 25117.545 | Y7: =X7-Z7 -> 3873.905 | Z7: =Budgets!N68 -> 21243.64 | AA7: =Z7-AB7 -> 3873.905 | AB7: =Budgets!O68 -> 17369.735 | AC7: =AB7-AD7 -> 3873.905 | AD7: =Budgets!P68 -> 13495.83 | AE7: =AD7-AF7 -> 3873.905 | AF7: =Budgets!Q68 -> 9621.925 | AG7: =AF7-AH7 -> 3873.905 | AH7: =Budgets!R68 -> 5748.02 | AI7: =AH7-AJ7 -> 5123.905 | AJ7: =Budgets!S68 -> 624.115 | AK7: =AJ7-AL7 -> 5540.5717 | AL7: =Budgets!T68 -> -4916.4567 | AM7: =AL7-AN7 -> 5957.2383 | AN7: =Budgets!U68 -> -10873.695 | AO7: =AN7-AP7 -> -118626.1 | AP7: =Budgets!V68 -> 107752.4 | AQ7: =AP7-AR7 -> 1790.5717 | AR7: =Budgets!W68 -> 105961.83 | AS7: =AR7-AT7 -> -7376.095 | AT7: =Budgets!X68 -> 113337.92 | AU7: =AT7-AV7 -> 3040.5717 | AV7: =Budgets!Y68 -> 110297.35 | AW7: =AV7-AX7 -> 13040.572 | AX7: =Budgets!Z68 -> 97256.78 | AY7: =AX7-AZ7 -> 3457.2383 | AZ7: =Budgets!AA68 -> 93799.542 | BA7: =AZ7-BB7 -> 3873.905 | BB7: =Budgets!AB68 -> 89925.637 | BC7: =BB7-BD7 -> 13873.905 | BD7: =Budgets!AC68 -> 76051.732 | BE7: =BD7-BF7 -> 13873.905 | BF7: =Budgets!AD68 -> 62177.827 | BG7: =BF7-BH7 -> -7666.6667 | BH7: =Budgets!AE68 -> 69844.493 | BI7: =BH7-BJ7 -> 2250 | BJ7: =Budgets!AF68 -> 67594.493 | BK7: =BJ7-BL7 -> 2166.6667 | BL7: =Budgets!AG68 -> 65427.827 | BM7: =BL7-BN7 -> -7500 | BN7: =Budgets!AH68 -> 72927.827 | BO7: =BN7-BP7 -> 2916.6667 | BP7: =Budgets!AI68 -> 70011.16 | BQ7: =BP7-BR7 -> 3333.3333 | BR7: =Budgets!AJ68 -> 66677.827 | BS7: =BR7-BT7 -> 3750 | BT7: =Budgets!AK68 -> 62927.827 | BU7: =BT7-BV7 -> 4166.6667 | BV7: =Budgets!AL68 -> 58761.16 | BW7: =BV7-BX7 -> 4583.3333 | BX7: =Budgets!AM68 -> 54177.827 | BY7: =BX7-BZ7 -> -100416.67 | BZ7: =Budgets!AN68 -> 154594.49 | CA7: =BZ7-CB7 -> -47500 | CB7: =Budgets!AO68 -> 202094.49 | CC7: =CB7-CD7 -> 22500 | CD7: =Budgets!AP68 -> 179594.49 | CE7: =CD7-CF7 -> -103333.33 | CF7: =Budgets!AQ68 -> 282927.83 | CG7: =CF7-CH7 -> -21666.667 | CH7: =Budgets!AR68 -> 304594.49 | CI7: =CH7-CJ7 -> -77500 | CJ7: =Budgets!AS68 -> 382094.49 | CK7: =CJ7-CL7 -> -1666.6667 | CL7: =Budgets!AT68 -> 383761.16 | CM7: =CL7-CN7 -> 16416.667 | CN7: =Budgets!AU68 -> 367344.49 | CO7: =CN7-CP7 -> 16083.333 | CP7: =Budgets!AV68 -> 351261.16 | CQ7: =CP7-CR7 -> 16166.667 | CR7: =Budgets!AW68 -> 335094.49 | CS7: =CR7-CT7 -> 16666.667 | CT7: =Budgets!AX68 -> 318427.83 | CU7: =CT7-CV7 -> 28250 | CV7: =Budgets!AY68 -> 290177.83 | CW7: =CV7-CX7 -> 27833.333 | CX7: =Budgets!AZ68 -> 262344.49 | CY7: =CX7-CZ7 -> 27833.333 | CZ7: =Budgets!BA68 -> 234511.16 | DA7: =CZ7-DB7 -> 27833.333 | DB7: =Budgets!BB68 -> 206677.83 | DC7: =DB7-DD7 -> 27000 | DD7: =Budgets!BC68 -> 179677.83 | DE7: =DD7-DF7 -> 26583.333 | DF7: =Budgets!BD68 -> 153094.49 | DG7: =DF7-DH7 -> 26166.667 | DH7: =Budgets!BE68 -> 126927.83 | DI7: =DH7-DJ7 -> 25333.333 | DJ7: =Budgets!BF68 -> 101594.49 | DK7: =DJ7-DL7 -> -3833.3333 | DL7: =Budgets!BG68 -> 105427.83 | DM7: =DL7-DN7 -> 16166.667 | DN7: =Budgets!BH68 -> 89261.16 | DO7: =DN7-DP7 -> 16166.667 | DP7: =Budgets!BI68 -> 73094.493 | DQ7: =DP7-DR7 -> -98833.333 | DR7: =Budgets!BJ68 -> 171927.83 | DS7: =DR7-DT7 -> 21166.667 | DT7: =Budgets!BK68 -> 150761.16 | DU7: =DT7-DV7 -> 7000 | DV7: =Budgets!BL68 -> 143761.16 | DW7: =DV7-DX7 -> 14500 | DX7: =Budgets!BM68 -> 129261.16 | DY7: =DX7-DZ7 -> 24500 | DZ7: =Budgets!BN68 -> 104761.16 | EA7: =DZ7-EB7 -> 24500 | EB7: =Budgets!BO68 -> 80261.16 | EC7: =EB7-ED7 -> 24500 | ED7: =Budgets!BP68 -> 55761.16 | EE7: =ED7-EF7 -> 24500 | EF7: =Budgets!BQ68 -> 31261.16 | EG7: =EF7-EH7 -> 24500 | EH7: =Budgets!BR68 -> 6761.16 | EI7: =EH7-EJ7 -> 6761.16 | EJ7: =Budgets!BS68 -> 0 | EK7: =EJ7-EL7 -> 0 | EL7: =Budgets!BT68 -> 0 | EM7: =EL7-EN7 -> 0 | EN7: =Budgets!BU68 -> 0 | EO7: =EN7-EP7 -> 0 | EP7: =Budgets!BV68 -> 0 | EQ7: =EP7-ER7 -> 0 | ER7: =Budgets!BW68 -> 0 | ES7: =ER7-ET7 -> 0 | ET7: =Budgets!BX68 -> 0 | EU7: =ET7-EV7 -> 0 | EV7: =Budgets!BY68 -> 0 | EW7: =EV7-EX7 -> 0 | EX7: =Budgets!BZ68 -> 0
A8: Total Fixed Assets | B8: =SUM(B6:B7) -> 25864.08 | D8: =SUM(D6:D7) -> 25864.08 | F8: =SUM(F6:F7) -> 44973.72 | H8: =SUM(H6:H7) -> 45634.88 | J8: =SUM(H6:H7) -> 45634.88 | L8: =SUM(L6:L7) -> 46860.975 | N8: =SUM(N6:N7) -> 43987.07 | P8: =SUM(P6:P7) -> 40613.165 | R8: =SUM(R6:R7) -> 36739.26 | T8: =SUM(T6:T7) -> 32865.355 | V8: =SUM(V6:V7) -> 28991.45 | X8: =SUM(X6:X7) -> 25117.545 | Z8: =SUM(Z6:Z7) -> 21243.64 | AB8: =SUM(AB6:AB7) -> 17369.735 | AD8: =SUM(AD6:AD7) -> 13495.83 | AF8: =SUM(AF6:AF7) -> 9621.925 | AH8: =SUM(AH6:AH7) -> 5748.02 | AJ8: =SUM(AJ6:AJ7) -> 624.115 | AL8: =SUM(AL6:AL7) -> -4916.4567 | AN8: =SUM(AN6:AN7) -> -10873.695 | AP8: =SUM(AP6:AP7) -> 107752.4 | AR8: =SUM(AR6:AR7) -> 105961.83 | AT8: =SUM(AT6:AT7) -> 113337.92 | AV8: =SUM(AV6:AV7) -> 110297.35 | AX8: =SUM(AX6:AX7) -> 97256.78 | AZ8: =SUM(AZ6:AZ7) -> 93799.542 | BB8: =SUM(BB6:BB7) -> 89925.637 | BD8: =SUM(BD6:BD7) -> 76051.732 | BF8: =SUM(BF6:BF7) -> 62177.827 | BH8: =SUM(BH6:BH7) -> 69844.493 | BJ8: =SUM(BJ6:BJ7) -> 67594.493 | BL8: =SUM(BL6:BL7) -> 65427.827 | BN8: =SUM(BN6:BN7) -> 72927.827 | BP8: =SUM(BP6:BP7) -> 70011.16 | BR8: =SUM(BR6:BR7) -> 66677.827 | BT8: =SUM(BT6:BT7) -> 62927.827 | BV8: =SUM(BV6:BV7) -> 58761.16 | BX8: =SUM(BX6:BX7) -> 54177.827 | BZ8: =SUM(BZ6:BZ7) -> 154594.49 | CB8: =SUM(CB6:CB7) -> 202094.49 | CD8: =SUM(CD6:CD7) -> 179594.49 | CF8: =SUM(CF6:CF7) -> 282927.83 | CH8: =SUM(CH6:CH7) -> 304594.49 | CJ8: =SUM(CJ6:CJ7) -> 382094.49 | CL8: =SUM(CL6:CL7) -> 383761.16 | CN8: =SUM(CN6:CN7) -> 367344.49 | CP8: =SUM(CP6:CP7) -> 351261.16 | CR8: =SUM(CR6:CR7) -> 335094.49 | CT8: =SUM(CT6:CT7) -> 318427.83 | CV8: =SUM(CV6:CV7) -> 290177.83 | CX8: =SUM(CX6:CX7) -> 262344.49 | CZ8: =SUM(CZ6:CZ7) -> 234511.16 | DB8: =SUM(DB6:DB7) -> 206677.83 | DD8: =SUM(DD6:DD7) -> 179677.83 | DF8: =SUM(DF6:DF7) -> 153094.49 | DH8: =SUM(DH6:DH7) -> 126927.83 | DJ8: =SUM(DJ6:DJ7) -> 101594.49 | DL8: =SUM(DL6:DL7) -> 105427.83 | DN8: =SUM(DN6:DN7) -> 89261.16 | DP8: =SUM(DP6:DP7) -> 73094.493 | DR8: =SUM(DR6:DR7) -> 171927.83 | DT8: =SUM(DT6:DT7) -> 150761.16 | DV8: =SUM(DV6:DV7) -> 143761.16 | DX8: =SUM(DX6:DX7) -> 129261.16 | DZ8: =SUM(DZ6:DZ7) -> 104761.16 | EB8: =SUM(EB6:EB7) -> 80261.16 | ED8: =SUM(ED6:ED7) -> 55761.16 | EF8: =SUM(EF6:EF7) -> 31261.16 | EH8: =SUM(EH6:EH7) -> 6761.16 | EJ8: =SUM(EJ6:EJ7) -> 0 | EL8: =SUM(EL6:EL7) -> 0 | EN8: =SUM(EN6:EN7) -> 0 | EP8: =SUM(EP6:EP7) -> 0 | ER8: =SUM(ER6:ER7) -> 0 | ET8: =SUM(ET6:ET7) -> 0 | EV8: =SUM(EV6:EV7) -> 0 | EX8: =SUM(EX6:EX7) -> 0
B10: ='Balance Sheet'!G10 -> 0 | D10: =B10 -> 0 | F10: =Budgets!D71 -> 0 | H10: =Budgets!E71 -> 0 | J10: =Budgets!F71 -> 0 | L10: =Budgets!G71 -> 0 | N10: =Budgets!H71 -> 0 | P10: =Budgets!I71 -> 0 | Q10: =P10-R10 -> 0 | R10: =Budgets!J71 -> 0 | S10: =R10-T10 -> 0 | T10: =Budgets!K71 -> 0 | U10: =T10-V10 -> 0 | V10: =Budgets!L71 -> 0 | W10: =V10-X10 -> 0 | X10: =Budgets!M71 -> 0 | Y10: =X10-Z10 -> 0 | Z10: =Budgets!N71 -> 0 | AA10: =Z10-AB10 -> 0 | AB10: =Budgets!O71 -> 0 | AC10: =AB10-AD10 -> 0 | AD10: =Budgets!P71 -> 0 | AE10: =AD10-AF10 -> 0 | AF10: =Budgets!Q71 -> 0 | AG10: =AF10-AH10 -> 0 | AH10: =Budgets!R71 -> 0 | AI10: =AH10-AJ10 -> 0 | AJ10: =Budgets!S71 -> 0 | AK10: =AJ10-AL10 -> 0 | AL10: =Budgets!T71 -> 0 | AM10: =AL10-AN10 -> 0 | AN10: =Budgets!U71 -> 0 | AO10: =AN10-AP10 -> 0 | AP10: =Budgets!V71 -> 0 | AQ10: =AP10-AR10 -> 0 | AR10: =Budgets!W71 -> 0 | AS10: =AR10-AT10 -> 0 | AT10: =Budgets!X71 -> 0 | AU10: =AT10-AV10 -> 0 | AV10: =Budgets!Y71 -> 0 | AW10: =AV10-AX10 -> 0 | AX10: =Budgets!Z71 -> 0 | AY10: =AX10-AZ10 -> 0 | AZ10: =Budgets!AA71 -> 0 | BA10: =AZ10-BB10 -> 0 | BB10: =Budgets!AB71 -> 0 | BC10: =BB10-BD10 -> 0 | BD10: =Budgets!AC71 -> 0 | BE10: =BD10-BF10 -> 0 | BF10: =Budgets!AD71 -> 0 | BG10: =BF10-BH10 -> 0 | BH10: =Budgets!AE71 -> 0 | BI10: =BH10-BJ10 -> 0 | BJ10: =Budgets!AF71 -> 0 | BK10: =BJ10-BL10 -> 0 | BL10: =Budgets!AG71 -> 0 | BM10: =BL10-BN10 -> 0 | BN10: =Budgets!AH71 -> 0 | BO10: =BN10-BP10 -> 0 | BP10: =Budgets!AI71 -> 0 | BQ10: =BP10-BR10 -> 0 | BR10: =Budgets!AJ71 -> 0 | BS10: =BR10-BT10 -> 0 | BT10: =Budgets!AK71 -> 0 | BU10: =BT10-BV10 -> 0 | BV10: =Budgets!AL71 -> 0 | BW10: =BV10-BX10 -> 0 | BX10: =Budgets!AM71 -> 0 | BY10: =BX10-BZ10 -> 0 | BZ10: =Budgets!AN71 -> 0 | CA10: =BZ10-BO10 -> 0 | CB10: =Budgets!AO71 -> 0 | CC10: =CB10-BQ10 -> 0 | CD10: =Budgets!AP71 -> 0 | CE10: =CD10-CF10 -> 0 | CF10: =Budgets!AQ71 -> 0 | CG10: =CF10-CH10 -> 0 | CH10: =Budgets!AR71 -> 0 | CI10: =CH10-CJ10 -> 0 | CJ10: =Budgets!AS71 -> 0 | CK10: =CJ10-CL10 -> 0 | CL10: =Budgets!AT71 -> 0 | CM10: =CL10-CN10 -> 0 | CN10: =Budgets!AU71 -> 0 | CO10: =CN10-CP10 -> 0 | CP10: =Budgets!AV71 -> 0 | CQ10: =CP10-CR10 -> 0 | CR10: =Budgets!AW71 -> 0 | CS10: =CR10-CT10 -> 0 | CT10: =Budgets!AX71 -> 0 | CU10: =CT10-CV10 -> 0 | CV10: =Budgets!AY71 -> 0 | CW10: =CV10-CX10 -> 0 | CX10: =Budgets!AZ71 -> 0 | CY10: =CX10-CZ10 -> 0 | CZ10: =Budgets!BA71 -> 0 | DA10: =CZ10-DB10 -> 0 | DB10: =Budgets!BB71 -> 0 | DC10: =DB10-DD10 -> 0 | DD10: =Budgets!BC71 -> 0 | DE10: =DD10-DF10 -> 0 | DF10: =Budgets!BD71 -> 0 | DG10: =DF10-DH10 -> 0 | DH10: =Budgets!BE71 -> 0 | DI10: =DH10-DJ10 -> 0 | DJ10: =Budgets!BF71 -> 0 | DK10: =DJ10-DL10 -> 0 | DL10: =Budgets!BG71 -> 0 | DM10: =DL10-DN10 -> 0 | DN10: =Budgets!BH71 -> 0 | DO10: =DN10-DP10 -> 0 | DP10: =Budgets!BI71 -> 0 | DQ10: =DP10-DR10 -> 0 | DR10: =Budgets!BJ71 -> 0 | DS10: =DR10-DT10 -> 0 | DT10: =Budgets!BK71 -> 0 | DU10: =DT10-DV10 -> 0 | DV10: =Budgets!BL71 -> 0 | DW10: =DV10-DX10 -> 0 | DX10: =Budgets!BM71 -> 0 | DY10: =DX10-DZ10 -> 0 | DZ10: =Budgets!BN71 -> 0 | EA10: =DZ10-EB10 -> 0 | EB10: =Budgets!BO71 -> 0 | EC10: =EB10-ED10 -> 0 | ED10: =Budgets!BP71 -> 0 | EE10: =ED10-EF10 -> 0 | EF10: =Budgets!BQ71 -> 0 | EG10: =EF10-EH10 -> 0 | EH10: =Budgets!BR71 -> 0 | EI10: =EH10-EJ10 -> 0 | EJ10: =Budgets!BS71 -> 0 | EK10: =EJ10-EL10 -> 0 | EL10: =Budgets!BT71 -> 0 | EM10: =EL10-EN10 -> 0 | EN10: =Budgets!BU71 -> 0 | EO10: =EN10-EP10 -> 0 | EP10: =Budgets!BV71 -> 0 | EQ10: =EP10-ER10 -> 0 | ER10: =Budgets!BW71 -> 0 | ES10: =ER10-ET10 -> 0 | ET10: =Budgets!BX71 -> 0 | EU10: =ET10-EV10 -> 0 | EV10: =Budgets!BY71 -> 0 | EW10: =EV10-EX10 -> 0 | EX10: =Budgets!BZ71 -> 0
A11: Trade Debtors | B11: ='Balance Sheet'!G11 -> 646856.76 | D11: =B11 -> 646856.76 | E11: =D11-F11 -> 383396 | F11: =Budgets!D72 -> 263460.76 | G11: =F11-H11 -> -22120.92 | H11: =Budgets!E72 -> 285581.68 | I11: =H11-J11 -> 166042 | J11: =Budgets!F72 -> 119539.68 | K11: =J11-L11 -> 11536 | L11: =Budgets!G72 -> 108003.68 | M11: =L11-N11 -> -8000 | N11: =Budgets!H72 -> 116003.68 | O11: =N11-P11 -> -26900 | P11: =Budgets!I72 -> 142903.68 | Q11: =P11-R11 -> -27500 | R11: =Budgets!J72 -> 170403.68 | S11: =R11-T11 -> -40000 | T11: =Budgets!K72 -> 210403.68 | U11: =T11-V11 -> -34500 | V11: =Budgets!L72 -> 244903.68 | W11: =V11-X11 -> -80500 | X11: =Budgets!M72 -> 325403.68 | Y11: =X11-Z11 -> -107330 | Z11: =Budgets!N72 -> 432733.68 | AA11: =Z11-AB11 -> 21650 | AB11: =Budgets!O72 -> 411083.68 | AC11: =AB11-AD11 -> -41670 | AD11: =Budgets!P72 -> 452753.68 | AE11: =AD11-AF11 -> -56250 | AF11: =Budgets!Q72 -> 509003.68 | AG11: =AF11-AH11 -> 3000 | AH11: =Budgets!R72 -> 506003.68 | AI11: =AH11-AJ11 -> 78469.212 | AJ11: =Budgets!S72 -> 427534.47 | AK11: =AJ11-AL11 -> 98058.712 | AL11: =Budgets!T72 -> 329475.76 | AM11: =AL11-AN11 -> 27492.5 | AN11: =Budgets!U72 -> 301983.26 | AO11: =AN11-AP11 -> -239313.55 | AP11: =Budgets!V72 -> 541296.8 | AQ11: =AP11-AR11 -> -183320.05 | AR11: =Budgets!W72 -> 724616.85 | AS11: =AR11-AT11 -> 75187 | AT11: =Budgets!X72 -> 649429.85 | AU11: =AT11-AV11 -> -64912.5 | AV11: =Budgets!Y72 -> 714342.35 | AW11: =AV11-AX11 -> -182786.33 | AX11: =Budgets!Z72 -> 897128.68 | AY11: =AX11-AZ11 -> -109458.33 | AZ11: =Budgets!AA72 -> 1006587 | BA11: =AZ11-BB11 -> 1312.5 | BB11: =Budgets!AB72 -> 1005274.5 | BC11: =BB11-BD11 -> -49125 | BD11: =Budgets!AC72 -> 1054399.5 | BE11: =BD11-BF11 -> -184895.83 | BF11: =Budgets!AD72 -> 1239295.3 | BG11: =BF11-BH11 -> -113583.33 | BH11: =Budgets!AE72 -> 1352878.7 | BI11: =BH11-BJ11 -> -5812.5 | BJ11: =Budgets!AF72 -> 1358691.2 | BK11: =BJ11-BL11 -> -272770.83 | BL11: =Budgets!AG72 -> 1631462 | BM11: =BL11-BN11 -> -120000 | BN11: =Budgets!AH72 -> 1751462 | BO11: =BN11-BP11 -> -72500 | BP11: =Budgets!AI72 -> 1823962 | BQ11: =BP11-BR11 -> -124333.33 | BR11: =Budgets!AJ72 -> 1948295.3 | BS11: =BR11-BT11 -> 7250 | BT11: =Budgets!AK72 -> 1941045.3 | BU11: =BT11-BV11 -> -116187.5 | BV11: =Budgets!AL72 -> 2057232.8 | BW11: =BV11-BX11 -> -88562.5 | BX11: =Budgets!AM72 -> 2145795.3 | BY11: =BX11-BZ11 -> -183770.83 | BZ11: =Budgets!AN72 -> 2329566.2 | CA11: =BZ11-CB11 -> -480666.67 | CB11: =Budgets!AO72 -> 2810232.8 | CC11: =CB11-CD11 -> -111562.5 | CD11: =Budgets!AP72 -> 2921795.3 | CE11: =CD11-CF11 -> 121958.33 | CF11: =Budgets!AQ72 -> 2799837 | CG11: =CF11-CH11 -> -351916.67 | CH11: =Budgets!AR72 -> 3151753.7 | CI11: =CH11-CJ11 -> -244145.83 | CJ11: =Budgets!AS72 -> 3395899.5 | CK11: =CJ11-CL11 -> -386354.17 | CL11: =Budgets!AT72 -> 3782253.7 | CM11: =CL11-CN11 -> -297291.67 | CN11: =Budgets!AU72 -> 4079545.3 | CO11: =CN11-CP11 -> 108062.5 | CP11: =Budgets!AV72 -> 3971482.8 | CQ11: =CP11-CR11 -> -132770.83 | CR11: =Budgets!AW72 -> 4104253.7 | CS11: =CR11-CT11 -> -390458.33 | CT11: =Budgets!AX72 -> 4494712 | CU11: =CT11-CV11 -> -195020.83 | CV11: =Budgets!AY72 -> 4689732.8 | CW11: =CV11-CX11 -> -281395.83 | CX11: =Budgets!AZ72 -> 4971128.7 | CY11: =CX11-CZ11 -> -564104.17 | CZ11: =Budgets!BA72 -> 5535232.8 | DA11: =CZ11-DB11 -> -510687.5 | DB11: =Budgets!BB72 -> 6045920.3 | DC11: =DB11-DD11 -> -530708.33 | DD11: =Budgets!BC72 -> 6576628.7 | DE11: =DD11-DF11 -> -238395.83 | DF11: =Budgets!BD72 -> 6815024.5 | DG11: =DF11-DH11 -> -161250 | DH11: =Budgets!BE72 -> 6976274.5 | DI11: =DH11-DJ11 -> -430041.67 | DJ11: =Budgets!BF72 -> 7406316.2 | DK11: =DJ11-DL11 -> -465312.5 | DL11: =Budgets!BG72 -> 7871628.7 | DM11: =DL11-DN11 -> -305604.17 | DN11: =Budgets!BH72 -> 8177232.8 | DO11: =DN11-DP11 -> -353104.17 | DP11: =Budgets!BI72 -> 8530337 | DQ11: =DP11-DR11 -> -599562.5 | DR11: =Budgets!BJ72 -> 9129899.5 | DS11: =DR11-DT11 -> -550375 | DT11: =Budgets!BK72 -> 9680274.5 | DU11: =DT11-DV11 -> -593729.17 | DV11: =Budgets!BL72 -> 10274004 | DW11: =DV11-DX11 -> -738104.17 | DX11: =Budgets!BM72 -> 11012108 | DY11: =DX11-DZ11 -> -640958.33 | DZ11: =Budgets!BN72 -> 11653066 | EA11: =DZ11-EB11 -> -373291.67 | EB11: =Budgets!BO72 -> 12026358 | EC11: =EB11-ED11 -> -302937.5 | ED11: =Budgets!BP72 -> 12329295 | EE11: =ED11-EF11 -> -651541.67 | EF11: =Budgets!BQ72 -> 12980837 | EG11: =EF11-EH11 -> -561291.67 | EH11: =Budgets!BR72 -> 13542129 | EI11: =EH11-EJ11 -> -196833.33 | EJ11: =Budgets!BS72 -> 13738962 | EK11: =EJ11-EL11 -> -351625 | EL11: =Budgets!BT72 -> 14090587 | EM11: =EL11-EN11 -> -790416.67 | EN11: =Budgets!BU72 -> 14881004 | EO11: =EN11-EP11 -> -334229.17 | EP11: =Budgets!BV72 -> 15215233 | EQ11: =EP11-ER11 -> -176645.83 | ER11: =Budgets!BW72 -> 15391879 | ES11: =ER11-ET11 -> -739583.33 | ET11: =Budgets!BX72 -> 16131462 | EU11: =ET11-EV11 -> -60916.667 | EV11: =Budgets!BY72 -> 16192379 | EW11: =EV11-EX11 -> 317312.5 | EX11: =Budgets!BZ72 -> 15875066
A12: Other debtors | B12: ='Balance Sheet'!G12 -> 0 | D12: =B12 -> 0 | E12: =D12-F12 -> -495861.96 | F12: =Budgets!D73 -> 495861.96 | G12: =F12-H12 -> 112786.08 | H12: =Budgets!E73 -> 383075.88 | I12: =H12-J12 -> 256861.68 | J12: =Budgets!F73 -> 126214.2 | K12: =J12-L12 -> 119814.2 | L12: =Budgets!G73 -> 6400 | M12: =L12-N12 -> -6400 | N12: =Budgets!H73 -> 12800 | O12: =N12-P12 -> -6400 | P12: =Budgets!I73 -> 19200 | Q12: =P12-R12 -> -6400 | R12: =Budgets!J73 -> 25600 | S12: =R12-T12 -> -6400 | T12: =Budgets!K73 -> 32000 | U12: =T12-V12 -> -28000 | V12: =Budgets!L73 -> 60000 | W12: =V12-X12 -> 0 | X12: =Budgets!M73 -> 60000 | Y12: =X12-Z12 -> 0 | Z12: =Budgets!N73 -> 60000 | AA12: =Z12-AB12 -> 0 | AB12: =Budgets!O73 -> 60000 | AC12: =AB12-AD12 -> 0 | AD12: =Budgets!P73 -> 60000 | AE12: =AD12-AF12 -> 0 | AF12: =Budgets!Q73 -> 60000 | AG12: =AF12-AH12 -> 0 | AH12: =Budgets!R73 -> 60000 | AI12: =AH12-AJ12 -> -68750 | AJ12: =Budgets!S73 -> 128750 | AK12: =AJ12-AL12 -> -16666.667 | AL12: =Budgets!T73 -> 145416.67 | AM12: =AL12-AN12 -> -14583.333 | AN12: =Budgets!U73 -> 160000 | AO12: =AN12-AP12 -> -183516.67 | AP12: =Budgets!V73 -> 343516.67 | AQ12: =AP12-AR12 -> 25683.333 | AR12: =Budgets!W73 -> 317833.33 | AS12: =AR12-AT12 -> 4083.3333 | AT12: =Budgets!X73 -> 313750 | AU12: =AT12-AV12 -> 9166.6667 | AV12: =Budgets!Y73 -> 304583.33 | AW12: =AV12-AX12 -> 34166.667 | AX12: =Budgets!Z73 -> 270416.67 | AY12: =AX12-AZ12 -> 11250 | AZ12: =Budgets!AA73 -> 259166.67 | BA12: =AZ12-BB12 -> 13333.333 | BB12: =Budgets!AB73 -> 245833.33 | BC12: =BB12-BD12 -> 38333.333 | BD12: =Budgets!AC73 -> 207500 | BE12: =BD12-BF12 -> 38333.333 | BF12: =Budgets!AD73 -> 169166.67 | BG12: =BF12-BH12 -> -32500 | BH12: =Budgets!AE73 -> 201666.67 | BI12: =BH12-BJ12 -> -80416.667 | BJ12: =Budgets!AF73 -> 282083.33 | BK12: =BJ12-BL12 -> -28333.333 | BL12: =Budgets!AG73 -> 310416.67 | BM12: =BL12-BN12 -> -124166.67 | BN12: =Budgets!AH73 -> 434583.33 | BO12: =BN12-BP12 -> -119083.33 | BP12: =Budgets!AI73 -> 553666.67 | BQ12: =BP12-BR12 -> -23000 | BR12: =Budgets!AJ73 -> 576666.67 | BS12: =BR12-BT12 -> -17916.667 | BT12: =Budgets!AK73 -> 594583.33 | BU12: =BT12-BV12 -> -15833.333 | BV12: =Budgets!AL73 -> 610416.67 | BW12: =BV12-BX12 -> -38750 | BX12: =Budgets!AM73 -> 649166.67 | BY12: =BX12-BZ12 -> -146250 | BZ12: =Budgets!AN73 -> 795416.67 | CA12: =BZ12-CB12 -> 39166.667 | CB12: =Budgets!AO73 -> 756250 | CC12: =CB12-CD12 -> 66250 | CD12: =Budgets!AP73 -> 690000 | CE12: =CD12-CF12 -> 16250 | CF12: =Budgets!AQ73 -> 673750 | CG12: =CF12-CH12 -> -168333.33 | CH12: =Budgets!AR73 -> 842083.33 | CI12: =CH12-CJ12 -> 17083.333 | CJ12: =Budgets!AS73 -> 825000 | CK12: =CJ12-CL12 -> -42500 | CL12: =Budgets!AT73 -> 867500 | CM12: =CL12-CN12 -> -37416.667 | CN12: =Budgets!AU73 -> 904916.67 | CO12: =CN12-CP12 -> 56583.333 | CP12: =Budgets!AV73 -> 848333.33 | CQ12: =CP12-CR12 -> 36666.667 | CR12: =Budgets!AW73 -> 811666.67 | CS12: =CR12-CT12 -> 25000 | CT12: =Budgets!AX73 -> 786666.67 | CU12: =CT12-CV12 -> 25000 | CV12: =Budgets!AY73 -> 761666.67 | CW12: =CV12-CX12 -> -75000 | CX12: =Budgets!AZ73 -> 836666.67 | CY12: =CX12-CZ12 -> 100000 | CZ12: =Budgets!BA73 -> 736666.67 | DA12: =CZ12-DB12 -> 125000 | DB12: =Budgets!BB73 -> 611666.67 | DC12: =DB12-DD12 -> 0 | DD12: =Budgets!BC73 -> 611666.67 | DE12: =DD12-DF12 -> -100000 | DF12: =Budgets!BD73 -> 711666.67 | DG12: =DF12-DH12 -> 0 | DH12: =Budgets!BE73 -> 711666.67 | DI12: =DH12-DJ12 -> -25000 | DJ12: =Budgets!BF73 -> 736666.67 | DK12: =DJ12-DL12 -> -97000 | DL12: =Budgets!BG73 -> 833666.67 | DM12: =DL12-DN12 -> 47000 | DN12: =Budgets!BH73 -> 786666.67 | DO12: =DN12-DP12 -> 50000 | DP12: =Budgets!BI73 -> 736666.67 | DQ12: =DP12-DR12 -> 75000 | DR12: =Budgets!BJ73 -> 661666.67 | DS12: =DR12-DT12 -> -25000 | DT12: =Budgets!BK73 -> 686666.67 | DU12: =DT12-DV12 -> -100000 | DV12: =Budgets!BL73 -> 786666.67 | DW12: =DV12-DX12 -> 100000 | DX12: =Budgets!BM73 -> 686666.67 | DY12: =DX12-DZ12 -> 125000 | DZ12: =Budgets!BN73 -> 561666.67 | EA12: =DZ12-EB12 -> 0 | EB12: =Budgets!BO73 -> 561666.67 | EC12: =EB12-ED12 -> -75000 | ED12: =Budgets!BP73 -> 636666.67 | EE12: =ED12-EF12 -> -25000 | EF12: =Budgets!BQ73 -> 661666.67 | EG12: =EF12-EH12 -> -25000 | EH12: =Budgets!BR73 -> 686666.67 | EI12: =EH12-EJ12 -> -50000 | EJ12: =Budgets!BS73 -> 736666.67 | EK12: =EJ12-EL12 -> 25000 | EL12: =Budgets!BT73 -> 711666.67 | EM12: =EL12-EN12 -> 25000 | EN12: =Budgets!BU73 -> 686666.67 | EO12: =EN12-EP12 -> 75000 | EP12: =Budgets!BV73 -> 611666.67 | EQ12: =EP12-ER12 -> -25000 | ER12: =Budgets!BW73 -> 636666.67 | ES12: =ER12-ET12 -> -100000 | ET12: =Budgets!BX73 -> 736666.67 | EU12: =ET12-EV12 -> 100000 | EV12: =Budgets!BY73 -> 636666.67 | EW12: =EV12-EX12 -> 125000 | EX12: =Budgets!BZ73 -> 511666.67
A13: VAT | B13: ='Balance Sheet'!G13 -> 0 | D13: =B13 -> 0 | E13: =D13-F13 -> -38857.632 | F13: =Budgets!D74 -> 38857.632 | G13: =F13-H13 -> -4983.2496 | H13: =Budgets!E74 -> 43840.882 | I13: =H13-J13 -> -4471.8673 | J13: =Budgets!F74 -> 48312.749 | K13: =J13-L13 -> 39538.882 | L13: =Budgets!G74 -> 8773.8673 | M13: =L13-N13 -> -4302 | N13: =Budgets!H74 -> 13075.867 | O13: =N13-P13 -> -4764 | P13: =Budgets!I74 -> 17839.867 | Q13: =P13-R13 -> 9323.8673 | R13: =Budgets!J74 -> 8516 | S13: =R13-T13 -> -3964 | T13: =Budgets!K74 -> 12480 | U13: =T13-V13 -> -3062 | V13: =Budgets!L74 -> 15542 | W13: =V13-X13 -> 11126 | X13: =Budgets!M74 -> 4416 | Y13: =X13-Z13 -> -915.4 | Z13: =Budgets!N74 -> 5331.4 | AA13: =Z13-AB13 -> -3787 | AB13: =Budgets!O74 -> 9118.4 | AC13: =AB13-AD13 -> 1249.4 | AD13: =Budgets!P74 -> 7869 | AE13: =AD13-AF13 -> -662 | AF13: =Budgets!Q74 -> 8531 | AG13: =AF13-AH13 -> -142 | AH13: =Budgets!R74 -> 8673 | AI13: =AH13-AJ13 -> -1373.4842 | AJ13: =Budgets!S74 -> 10046.484 | AK13: =AJ13-AL13 -> -4192.9409 | AL13: =Budgets!T74 -> 14239.425 | AM13: =AL13-AN13 -> -8176.4176 | AN13: =Budgets!U74 -> 22415.843 | AO13: =AN13-AP13 -> 3994.0051 | AP13: =Budgets!V74 -> 18421.838 | AQ13: =AP13-AR13 -> -18043.35 | AR13: =Budgets!W74 -> 36465.188 | AS13: =AR13-AT13 -> -14349.16 | AT13: =Budgets!X74 -> 50814.348 | AU13: =AT13-AV13 -> 28014.671 | AV13: =Budgets!Y74 -> 22799.677 | AW13: =AV13-AX13 -> -5298.85 | AX13: =Budgets!Z74 -> 28098.527 | AY13: =AX13-AZ13 -> -16866.767 | AZ13: =Budgets!AA74 -> 44965.293 | BA13: =AZ13-BB13 -> 16662.593 | BB13: =Budgets!AB74 -> 28302.7 | BC13: =BB13-BD13 -> -6389.6833 | BD13: =Budgets!AC74 -> 34692.383 | BE13: =BD13-BF13 -> -3238.0167 | BF13: =Budgets!AD74 -> 37930.4 | BG13: =BF13-BH13 -> 23554.278 | BH13: =Budgets!AE74 -> 14376.122 | BI13: =BH13-BJ13 -> -5827.2717 | BJ13: =Budgets!AF74 -> 20203.393 | BK13: =BJ13-BL13 -> -14403.522 | BL13: =Budgets!AG74 -> 34606.915 | BM13: =BL13-BN13 -> 14549.872 | BN13: =Budgets!AH74 -> 20057.043 | BO13: =BN13-BP13 -> -2299.7717 | BP13: =Budgets!AI74 -> 22356.815 | BQ13: =BP13-BR13 -> -7927.6883 | BR13: =Budgets!AJ74 -> 30284.503 | BS13: =BR13-BT13 -> 14201.21 | BT13: =Budgets!AK74 -> 16083.293 | BU13: =BT13-BV13 -> -2814.7717 | BV13: =Budgets!AL74 -> 18898.065 | BW13: =BV13-BX13 -> -13525.188 | BX13: =Budgets!AM74 -> 32423.253 | BY13: =BX13-BZ13 -> 11690.377 | BZ13: =Budgets!AN74 -> 20732.877 | CA13: =BZ13-CB13 -> -5878.105 | CB13: =Budgets!AO74 -> 26610.982 | CC13: =CB13-CD13 -> -9161.4383 | CD13: =Budgets!AP74 -> 35772.42 | CE13: =CD13-CF13 -> 15587.076 | CF13: =Budgets!AQ74 -> 20185.344 | CG13: =CF13-CH13 -> -10001.823 | CH13: =Budgets!AR74 -> 30187.167 | CI13: =CH13-CJ13 -> -16190.573 | CJ13: =Budgets!AS74 -> 46377.74 | CK13: =CJ13-CL13 -> 15518.678 | CL13: =Budgets!AT74 -> 30859.062 | CM13: =CL13-CN13 -> -17240.573 | CN13: =Budgets!AU74 -> 48099.635 | CO13: =CN13-CP13 -> -15085.156 | CP13: =Budgets!AV74 -> 63184.791 | CQ13: =CP13-CR13 -> 29647.812 | CR13: =Budgets!AW74 -> 33536.979 | CS13: =CR13-CT13 -> -17718.489 | CT13: =Budgets!AX74 -> 51255.468 | CU13: =CT13-CV13 -> -18558.489 | CV13: =Budgets!AY74 -> 69813.958 | CW13: =CV13-CX13 -> 34742.395 | CX13: =Budgets!AZ74 -> 35071.562 | CY13: =CX13-CZ13 -> -16063.073 | CZ13: =Budgets!BA74 -> 51134.635 | DA13: =CZ13-DB13 -> -14857.656 | DB13: =Budgets!BB74 -> 65992.291 | DC13: =DB13-DD13 -> 34897.825 | DD13: =Budgets!BC74 -> 31094.466 | DE13: =DD13-DF13 -> -15786.81 | DF13: =Budgets!BD74 -> 46881.276 | DG13: =DF13-DH13 -> -16236.81 | DH13: =Budgets!BE74 -> 63118.085 | DI13: =DH13-DJ13 -> 31594.466 | DJ13: =Budgets!BF74 -> 31523.619 | DK13: =DJ13-DL13 -> -13181.393 | DL13: =Budgets!BG74 -> 44705.012 | DM13: =DL13-DN13 -> -13631.393 | DN13: =Budgets!BH74 -> 58336.406 | DO13: =DN13-DP13 -> 32729.036 | DP13: =Budgets!BI74 -> 25607.369 | DQ13: =DP13-DR13 -> -11525.976 | DR13: =Budgets!BJ74 -> 37133.346 | DS13: =DR13-DT13 -> -12125.976 | DT13: =Budgets!BK74 -> 49259.322 | DU13: =DT13-DV13 -> 25057.369 | DV13: =Budgets!BL74 -> 24201.953 | DW13: =DV13-DX13 -> -11625.976 | DX13: =Budgets!BM74 -> 35827.929 | DY13: =DX13-DZ13 -> -12075.976 | DZ13: =Budgets!BN74 -> 47903.906 | EA13: =DZ13-EB13 -> -13025.976 | EB13: =Budgets!BO74 -> 60929.882 | EC13: =EB13-ED13 -> -12575.976 | ED13: =Budgets!BP74 -> 73505.858 | EE13: =ED13-EF13 -> -11718.476 | EF13: =Budgets!BQ74 -> 85224.335 | EG13: =EF13-EH13 -> -11718.476 | EH13: =Budgets!BR74 -> 96942.811 | EI13: =EH13-EJ13 -> -15181.393 | EJ13: =Budgets!BS74 -> 112124.2 | EK13: =EJ13-EL13 -> -13112.643 | EL13: =Budgets!BT74 -> 125236.85 | EM13: =EL13-EN13 -> -13562.643 | EN13: =Budgets!BU74 -> 138799.49 | EO13: =EN13-EP13 -> -16336.81 | EP13: =Budgets!BV74 -> 155136.3 | EQ13: =EP13-ER13 -> -14420.143 | ER13: =Budgets!BW74 -> 169556.44 | ES13: =ER13-ET13 -> -15218.06 | ET13: =Budgets!BX74 -> 184774.5 | EU13: =ET13-EV13 -> -15386.81 | EV13: =Budgets!BY74 -> 200161.31 | EW13: =EV13-EX13 -> -18680.976 | EX13: =Budgets!BZ74 -> 218842.29
A14: Total Current Assets | B14: =SUM(B10:B13) -> 646856.76 | D14: =SUM(D10:D13) -> 646856.76 | F14: =SUM(F10:F13) -> 798180.35 | H14: =SUM(H10:H13) -> 712498.44 | J14: =SUM(J10:J13) -> 294066.63 | L14: =SUM(L10:L13) -> 123177.55 | N14: =SUM(N10:N13) -> 141879.55 | P14: =SUM(P10:P13) -> 179943.55 | R14: =SUM(R10:R13) -> 204519.68 | T14: =SUM(T10:T13) -> 254883.68 | V14: =SUM(V10:V13) -> 320445.68 | X14: =SUM(X10:X13) -> 389819.68 | Z14: =SUM(Z10:Z13) -> 498065.08 | AB14: =SUM(AB10:AB13) -> 480202.08 | AD14: =SUM(AD10:AD13) -> 520622.68 | AF14: =SUM(AF10:AF13) -> 577534.68 | AH14: =SUM(AH10:AH13) -> 574676.68 | AJ14: =SUM(AJ10:AJ13) -> 566330.95 | AL14: =SUM(AL10:AL13) -> 489131.85 | AN14: =SUM(AN10:AN13) -> 484399.1 | AP14: =SUM(AP10:AP13) -> 903235.31 | AR14: =SUM(AR10:AR13) -> 1078915.4 | AT14: =SUM(AT10:AT13) -> 1013994.2 | AV14: =SUM(AV10:AV13) -> 1041725.4 | AX14: =SUM(AX10:AX13) -> 1195643.9 | AZ14: =SUM(AZ10:AZ13) -> 1310719 | BB14: =SUM(BB10:BB13) -> 1279410.5 | BD14: =SUM(BD10:BD13) -> 1296591.9 | BF14: =SUM(BF10:BF13) -> 1446392.4 | BH14: =SUM(BH10:BH13) -> 1568921.5 | BJ14: =SUM(BJ10:BJ13) -> 1660977.9 | BL14: =SUM(BL10:BL13) -> 1976485.6 | BN14: =SUM(BN10:BN13) -> 2206102.4 | BP14: =SUM(BP10:BP13) -> 2399985.5 | BR14: =SUM(BR10:BR13) -> 2555246.5 | BT14: =SUM(BT10:BT13) -> 2551712 | BV14: =SUM(BV10:BV13) -> 2686547.6 | BX14: =SUM(BX10:BX13) -> 2827385.3 | BZ14: =SUM(BZ10:BZ13) -> 3145715.7 | CB14: =SUM(CB10:CB13) -> 3593093.8 | CD14: =SUM(CD10:CD13) -> 3647567.8 | CF14: =SUM(CF10:CF13) -> 3493772.4 | CH14: =SUM(CH10:CH13) -> 4024024.2 | CJ14: =SUM(CJ10:CJ13) -> 4267277.3 | CL14: =SUM(CL10:CL13) -> 4680612.7 | CN14: =SUM(CN10:CN13) -> 5032561.6 | CP14: =SUM(CP10:CP13) -> 4883001 | CR14: =SUM(CR10:CR13) -> 4949457.3 | CT14: =SUM(CT10:CT13) -> 5332634.1 | CV14: =SUM(CV10:CV13) -> 5521213.5 | CX14: =SUM(CX10:CX13) -> 5842866.9 | CZ14: =SUM(CZ10:CZ13) -> 6323034.1 | DB14: =SUM(DB10:DB13) -> 6723579.3 | DD14: =SUM(DD10:DD13) -> 7219389.8 | DF14: =SUM(DF10:DF13) -> 7573572.5 | DH14: =SUM(DH10:DH13) -> 7751059.3 | DJ14: =SUM(DJ10:DJ13) -> 8174506.5 | DL14: =SUM(DL10:DL13) -> 8750000.4 | DN14: =SUM(DN10:DN13) -> 9022235.9 | DP14: =SUM(DP10:DP13) -> 9292611 | DR14: =SUM(DR10:DR13) -> 9828699.5 | DT14: =SUM(DT10:DT13) -> 10416201 | DV14: =SUM(DV10:DV13) -> 11084872 | DX14: =SUM(DX10:DX13) -> 11734602 | DZ14: =SUM(DZ10:DZ13) -> 12262637 | EB14: =SUM(EB10:EB13) -> 12648954 | ED14: =SUM(ED10:ED13) -> 13039468 | EF14: =SUM(EF10:EF13) -> 13727728 | EH14: =SUM(EH10:EH13) -> 14325738 | EJ14: =SUM(EJ10:EJ13) -> 14587753 | EL14: =SUM(EL10:EL13) -> 14927491 | EN14: =SUM(EN10:EN13) -> 15706470 | EP14: =SUM(EP10:EP13) -> 15982036 | ER14: =SUM(ER10:ER13) -> 16198102 | ET14: =SUM(ET10:ET13) -> 17052903 | EV14: =SUM(EV10:EV13) -> 17029207 | EX14: =SUM(EX10:EX13) -> 16605575
A16: Trade Creditors | B16: ='Balance Sheet'!G17 -> -310568.28 | D16: =B16 -> -310568.28 | E16: =D16-F16 -> -265593.47 | F16: =Budgets!D78 -> -44974.808 | G16: =F16-H16 -> 33417.128 | H16: =Budgets!E78 -> -78391.936 | I16: =H16-J16 -> -6061.6829 | J16: =Budgets!F78 -> -72330.253 | K16: =J16-L16 -> -33404.445 | L16: =Budgets!G78 -> -38925.808 | M16: =L16-N16 -> 5304 | N16: =Budgets!H78 -> -44229.808 | O16: =N16-P16 -> 12396 | P16: =Budgets!I78 -> -56625.808 | Q16: =P16-R16 -> 37044 | R16: =Budgets!J78 -> -93669.808 | S16: =R16-T16 -> -50064 | T16: =Budgets!K78 -> -43605.808 | U16: =T16-V16 -> 74112 | V16: =Budgets!L78 -> -117717.81 | W16: =V16-X16 -> -50112 | X16: =Budgets!M78 -> -67605.808 | Y16: =X16-Z16 -> -33600 | Z16: =Budgets!N78 -> -34005.808 | AA16: =Z16-AB16 -> 24060 | AB16: =Budgets!O78 -> -58065.808 | AC16: =AB16-AD16 -> 120 | AD16: =Budgets!P78 -> -58185.808 | AE16: =AD16-AF16 -> -24000 | AF16: =Budgets!Q78 -> -34185.808 | AG16: =AF16-AH16 -> 12000 | AH16: =Budgets!R78 -> -46185.808 | AI16: =AH16-AJ16 -> 114115.8 | AJ16: =Budgets!S78 -> -160301.61 | AK16: =AJ16-AL16 -> -6000 | AL16: =Budgets!T78 -> -154301.61 | AM16: =AL16-AN16 -> -34740 | AN16: =Budgets!U78 -> -119561.61 | AO16: =AN16-AP16 -> 255840 | AP16: =Budgets!V78 -> -375401.61 | AQ16: =AP16-AR16 -> 13680 | AR16: =Budgets!W78 -> -389081.61 | AS16: =AR16-AT16 -> -233340 | AT16: =Budgets!X78 -> -155741.61 | AU16: =AT16-AV16 -> -25680 | AV16: =Budgets!Y78 -> -130061.61 | AW16: =AV16-AX16 -> -33600 | AX16: =Budgets!Z78 -> -96461.608 | AY16: =AX16-AZ16 -> 72000 | AZ16: =Budgets!AA78 -> -168461.61 | BA16: =AZ16-BB16 -> -15480 | BB16: =Budgets!AB78 -> -152981.61 | BC16: =BB16-BD16 -> -54000 | BD16: =Budgets!AC78 -> -98981.608 | BE16: =BD16-BF16 -> -18000 | BF16: =Budgets!AD78 -> -80981.608 | BG16: =BF16-BH16 -> 108658.59 | BH16: =Budgets!AE78 -> -189640.2 | BI16: =BH16-BJ16 -> 123480 | BJ16: =Budgets!AF78 -> -313120.2 | BK16: =BJ16-BL16 -> 84060 | BL16: =Budgets!AG78 -> -397180.2 | BM16: =BL16-BN16 -> -24000 | BN16: =Budgets!AH78 -> -373180.2 | BO16: =BN16-BP16 -> 116400 | BP16: =Budgets!AI78 -> -489580.2 | BQ16: =BP16-BR16 -> -80280 | BR16: =Budgets!AJ78 -> -409300.2 | BS16: =BR16-BT16 -> -128280 | BT16: =Budgets!AK78 -> -281020.2 | BU16: =BT16-BV16 -> -27600 | BV16: =Budgets!AL78 -> -253420.2 | BW16: =BV16-BX16 -> 102000 | BX16: =Budgets!AM78 -> -355420.2 | BY16: =BX16-BZ16 -> 108000 | BZ16: =Budgets!AN78 -> -463420.2 | CA16: =BZ16-CB16 -> -60000 | CB16: =Budgets!AO78 -> -403420.2 | CC16: =CB16-CD16 -> -228000 | CD16: =Budgets!AP78 -> -175420.2 | CE16: =CD16-CF16 -> 34279.519 | CF16: =Budgets!AQ78 -> -209699.72 | CG16: =CF16-CH16 -> 288000 | CH16: =Budgets!AR78 -> -497699.72 | CI16: =CH16-CJ16 -> 54060 | CJ16: =Budgets!AS78 -> -551759.72 | CK16: =CJ16-CL16 -> -144000 | CL16: =Budgets!AT78 -> -407759.72 | CM16: =CL16-CN16 -> 86400 | CN16: =Budgets!AU78 -> -494159.72 | CO16: =CN16-CP16 -> -104400 | CP16: =Budgets!AV78 -> -389759.72 | CQ16: =CP16-CR16 -> -86340 | CR16: =Budgets!AW78 -> -303419.72 | CS16: =CR16-CT16 -> 44400 | CT16: =Budgets!AX78 -> -347819.72 | CU16: =CT16-CV16 -> 42000 | CV16: =Budgets!AY78 -> -389819.72 | CW16: =CV16-CX16 -> 108000 | CX16: =Budgets!AZ78 -> -497819.72 | CY16: =CX16-CZ16 -> -90000 | CZ16: =Budgets!BA78 -> -407819.72 | DA16: =CZ16-DB16 -> -228000 | DB16: =Budgets!BB78 -> -179819.72 | DC16: =DB16-DD16 -> 112430.5 | DD16: =Budgets!BC78 -> -292250.21 | DE16: =DD16-DF16 -> 270000 | DF16: =Budgets!BD78 -> -562250.21 | DG16: =DF16-DH16 -> 12000 | DH16: =Budgets!BE78 -> -574250.21 | DI16: =DH16-DJ16 -> -102000 | DJ16: =Budgets!BF78 -> -472250.21 | DK16: =DJ16-DL16 -> 116400 | DL16: =Budgets!BG78 -> -588650.21 | DM16: =DL16-DN16 -> -74400 | DN16: =Budgets!BH78 -> -514250.21 | DO16: =DN16-DP16 -> -188400 | DP16: =Budgets!BI78 -> -325850.21 | DQ16: =DP16-DR16 -> -33600 | DR16: =Budgets!BJ78 -> -292250.21 | DS16: =DR16-DT16 -> 102000 | DT16: =Budgets!BK78 -> -394250.21 | DU16: =DT16-DV16 -> 198000 | DV16: =Budgets!BL78 -> -592250.21 | DW16: =DV16-DX16 -> -150000 | DX16: =Budgets!BM78 -> -442250.21 | DY16: =DX16-DZ16 -> -258000 | DZ16: =Budgets!BN78 -> -184250.21 | EA16: =DZ16-EB16 -> 120600 | EB16: =Budgets!BO78 -> -304850.21 | EC16: =EB16-ED16 -> 240000 | ED16: =Budgets!BP78 -> -544850.21 | EE16: =ED16-EF16 -> 30000 | EF16: =Budgets!BQ78 -> -574850.21 | EG16: =EF16-EH16 -> -60000 | EH16: =Budgets!BR78 -> -514850.21 | EI16: =EH16-EJ16 -> 30000 | EJ16: =Budgets!BS78 -> -544850.21 | EK16: =EJ16-EL16 -> -60000 | EL16: =Budgets!BT78 -> -484850.21 | EM16: =EL16-EN16 -> -90000 | EN16: =Budgets!BU78 -> -394850.21 | EO16: =EN16-EP16 -> -60000 | EP16: =Budgets!BV78 -> -334850.21 | EQ16: =EP16-ER16 -> 60000 | ER16: =Budgets!BW78 -> -394850.21 | ES16: =ER16-ET16 -> 210000 | ET16: =Budgets!BX78 -> -604850.21 | EU16: =ET16-EV16 -> -150000 | EV16: =Budgets!BY78 -> -454850.21 | EW16: =EV16-EX16 -> -270000 | EX16: =Budgets!BZ78 -> -184850.21
A17: Deferred Revenue | B17: ='Balance Sheet'!G18 -> 0 | D17: =B17 -> 0 | E17: =D17-F17 -> 0 | F17: =Budgets!D79 -> 0 | G17: =F17-H17 -> 0 | H17: =Budgets!E79 -> 0 | I17: =H17-J17 -> 0 | J17: =Budgets!F79 -> 0 | K17: =J17-L17 -> 0 | L17: =Budgets!G79 -> 0 | M17: =L17-N17 -> 0 | N17: =Budgets!H79 -> 0 | O17: =N17-P17 -> 0 | P17: =Budgets!I79 -> 0 | Q17: =P17-R17 -> 0 | R17: =Budgets!J79 -> 0 | S17: =R17-T17 -> 0 | T17: =Budgets!K79 -> 0 | U17: =T17-V17 -> 0 | V17: =Budgets!L79 -> 0 | W17: =V17-X17 -> 0 | X17: =Budgets!M79 -> 0 | Y17: =X17-Z17 -> 0 | Z17: =Budgets!N79 -> 0 | AA17: =Z17-AB17 -> 0 | AB17: =Budgets!O79 -> 0 | AC17: =AB17-AD17 -> 0 | AD17: =Budgets!P79 -> 0 | AE17: =AD17-AF17 -> 0 | AF17: =Budgets!Q79 -> 0 | AG17: =AF17-AH17 -> 0 | AH17: =Budgets!R79 -> 0 | AI17: =AH17-AJ17 -> 0 | AJ17: =Budgets!S79 -> 0 | AK17: =AJ17-AL17 -> 0 | AL17: =Budgets!T79 -> 0 | AM17: =AL17-AN17 -> 0 | AN17: =Budgets!U79 -> 0 | AO17: =AN17-AP17 -> 0 | AP17: =Budgets!V79 -> 0 | AQ17: =AP17-AR17 -> 0 | AR17: =Budgets!W79 -> 0 | AS17: =AR17-AT17 -> 0 | AT17: =Budgets!X79 -> 0 | AU17: =AT17-AV17 -> 0 | AV17: =Budgets!Y79 -> 0 | AW17: =AV17-AX17 -> 0 | AX17: =Budgets!Z79 -> 0 | AY17: =AX17-AZ17 -> 0 | AZ17: =Budgets!AA79 -> 0 | BA17: =AZ17-BB17 -> 0 | BB17: =Budgets!AB79 -> 0 | BC17: =BB17-BD17 -> 0 | BD17: =Budgets!AC79 -> 0 | BE17: =BD17-BF17 -> 0 | BF17: =Budgets!AD79 -> 0 | BG17: =BF17-BH17 -> 0 | BH17: =Budgets!AE79 -> 0 | BI17: =BH17-BJ17 -> 0 | BJ17: =Budgets!AF79 -> 0 | BK17: =BJ17-BL17 -> 0 | BL17: =Budgets!AG79 -> 0 | BM17: =BL17-BN17 -> 0 | BN17: =Budgets!AH79 -> 0 | BO17: =BN17-BP17 -> 0 | BP17: =Budgets!AI79 -> 0 | BQ17: =BP17-BR17 -> 0 | BR17: =Budgets!AJ79 -> 0 | BS17: =BR17-BT17 -> 0 | BT17: =Budgets!AK79 -> 0 | BU17: =BT17-BV17 -> 0 | BV17: =Budgets!AL79 -> 0 | BW17: =BV17-BX17 -> 0 | BX17: =Budgets!AM79 -> 0 | BY17: =BX17-BZ17 -> 0 | BZ17: =Budgets!AN79 -> 0 | CA17: =BZ17-CB17 -> 0 | CB17: =Budgets!AO79 -> 0 | CC17: =CB17-CD17 -> 0 | CD17: =Budgets!AP79 -> 0 | CE17: =CD17-CF17 -> 0 | CF17: =Budgets!AQ79 -> 0 | CG17: =CF17-CH17 -> 0 | CH17: =Budgets!AR79 -> 0 | CI17: =CH17-CJ17 -> 0 | CJ17: =Budgets!AS79 -> 0 | CK17: =CJ17-CL17 -> 0 | CL17: =Budgets!AT79 -> 0 | CM17: =CL17-CN17 -> 0 | CN17: =Budgets!AU79 -> 0 | CO17: =CN17-CP17 -> 0 | CP17: =Budgets!AV79 -> 0 | CQ17: =CP17-CR17 -> 0 | CR17: =Budgets!AW79 -> 0 | CS17: =CR17-CT17 -> 0 | CT17: =Budgets!AX79 -> 0 | CU17: =CT17-CV17 -> 0 | CV17: =Budgets!AY79 -> 0 | CW17: =CV17-CX17 -> 0 | CX17: =Budgets!AZ79 -> 0 | CY17: =CX17-CZ17 -> 0 | CZ17: =Budgets!BA79 -> 0 | DA17: =CZ17-DB17 -> 0 | DB17: =Budgets!BB79 -> 0 | DC17: =DB17-DD17 -> 0 | DD17: =Budgets!BC79 -> 0 | DE17: =DD17-DF17 -> 0 | DF17: =Budgets!BD79 -> 0 | DG17: =DF17-DH17 -> 0 | DH17: =Budgets!BE79 -> 0 | DI17: =DH17-DJ17 -> 0 | DJ17: =Budgets!BF79 -> 0 | DK17: =DJ17-DL17 -> 0 | DL17: =Budgets!BG79 -> 0 | DM17: =DL17-DN17 -> 0 | DN17: =Budgets!BH79 -> 0 | DO17: =DN17-DP17 -> 0 | DP17: =Budgets!BI79 -> 0 | DQ17: =DP17-DR17 -> 0 | DR17: =Budgets!BJ79 -> 0 | DS17: =DR17-DT17 -> 0 | DT17: =Budgets!BK79 -> 0 | DU17: =DT17-DV17 -> 0 | DV17: =Budgets!BL79 -> 0 | DW17: =DV17-DX17 -> 0 | DX17: =Budgets!BM79 -> 0 | DY17: =DX17-DZ17 -> 0 | DZ17: =Budgets!BN79 -> 0 | EA17: =DZ17-EB17 -> 0 | EB17: =Budgets!BO79 -> 0 | EC17: =EB17-ED17 -> 0 | ED17: =Budgets!BP79 -> 0 | EE17: =ED17-EF17 -> 0 | EF17: =Budgets!BQ79 -> 0 | EG17: =EF17-EH17 -> 0 | EH17: =Budgets!BR79 -> 0 | EI17: =EH17-EJ17 -> 0 | EJ17: =Budgets!BS79 -> 0 | EK17: =EJ17-EL17 -> 0 | EL17: =Budgets!BT79 -> 0 | EM17: =EL17-EN17 -> 0 | EN17: =Budgets!BU79 -> 0 | EO17: =EN17-EP17 -> 0 | EP17: =Budgets!BV79 -> 0 | EQ17: =EP17-ER17 -> 0 | ER17: =Budgets!BW79 -> 0 | ES17: =ER17-ET17 -> 0 | ET17: =Budgets!BX79 -> 0 | EU17: =ET17-EV17 -> 0 | EV17: =Budgets!BY79 -> 0 | EW17: =EV17-EX17 -> 0 | EX17: =Budgets!BZ79 -> 0
A18: Other creditors | B18: ='Balance Sheet'!G19 -> 0 | D18: =B18 -> 0 | E18: =D18-F18 -> 372248.63 | F18: =Budgets!D80 -> -372248.63 | G18: =F18-H18 -> 4983.2496 | H18: =Budgets!E80 -> -377231.88 | I18: =H18-J18 -> 4471.8673 | J18: =Budgets!F80 -> -381703.75 | K18: =J18-L18 -> -339538.88 | L18: =Budgets!G80 -> -42164.867 | M18: =L18-N18 -> 104302 | N18: =Budgets!H80 -> -146466.87 | O18: =N18-P18 -> 104764 | P18: =Budgets!I80 -> -251230.87 | Q18: =P18-R18 -> 196676.13 | R18: =Budgets!J80 -> -447907 | S18: =R18-T18 -> 3964 | T18: =Budgets!K80 -> -451871 | U18: =T18-V18 -> 3062 | V18: =Budgets!L80 -> -454933 | W18: =V18-X18 -> -28292.667 | X18: =Budgets!M80 -> -426640.33 | Y18: =X18-Z18 -> -16251.267 | Z18: =Budgets!N80 -> -410389.07 | AA18: =Z18-AB18 -> -67879.667 | AB18: =Budgets!O80 -> -342509.4 | AC18: =AB18-AD18 -> -1249.4 | AD18: =Budgets!P80 -> -341260 | AE18: =AD18-AF18 -> 662 | AF18: =Budgets!Q80 -> -341922 | AG18: =AF18-AH18 -> 142 | AH18: =Budgets!R80 -> -342064 | AI18: =AH18-AJ18 -> 1373.4842 | AJ18: =Budgets!S80 -> -343437.48 | AK18: =AJ18-AL18 -> 4192.9409 | AL18: =Budgets!T80 -> -347630.43 | AM18: =AL18-AN18 -> 8176.4176 | AN18: =Budgets!U80 -> -355806.84 | AO18: =AN18-AP18 -> -3994.0051 | AP18: =Budgets!V80 -> -351812.84 | AQ18: =AP18-AR18 -> 18043.35 | AR18: =Budgets!W80 -> -369856.19 | AS18: =AR18-AT18 -> 14349.16 | AT18: =Budgets!X80 -> -384205.35 | AU18: =AT18-AV18 -> -28014.671 | AV18: =Budgets!Y80 -> -356190.68 | AW18: =AV18-AX18 -> 5298.85 | AX18: =Budgets!Z80 -> -361489.53 | AY18: =AX18-AZ18 -> 16866.767 | AZ18: =Budgets!AA80 -> -378356.29 | BA18: =AZ18-BB18 -> -16662.593 | BB18: =Budgets!AB80 -> -361693.7 | BC18: =BB18-BD18 -> 6389.6833 | BD18: =Budgets!AC80 -> -368083.38 | BE18: =BD18-BF18 -> 3238.0167 | BF18: =Budgets!AD80 -> -371321.4 | BG18: =BF18-BH18 -> -23554.278 | BH18: =Budgets!AE80 -> -347767.12 | BI18: =BH18-BJ18 -> 5827.2717 | BJ18: =Budgets!AF80 -> -353594.39 | BK18: =BJ18-BL18 -> 14403.522 | BL18: =Budgets!AG80 -> -367997.92 | BM18: =BL18-BN18 -> -14549.872 | BN18: =Budgets!AH80 -> -353448.04 | BO18: =BN18-BP18 -> 2299.7717 | BP18: =Budgets!AI80 -> -355747.82 | BQ18: =BP18-BR18 -> 7927.6883 | BR18: =Budgets!AJ80 -> -363675.5 | BS18: =BR18-BT18 -> -14201.21 | BT18: =Budgets!AK80 -> -349474.29 | BU18: =BT18-BV18 -> 2814.7717 | BV18: =Budgets!AL80 -> -352289.07 | BW18: =BV18-BX18 -> 13525.188 | BX18: =Budgets!AM80 -> -365814.25 | BY18: =BX18-BZ18 -> -11690.377 | BZ18: =Budgets!AN80 -> -354123.88 | CA18: =BZ18-CB18 -> 5878.105 | CB18: =Budgets!AO80 -> -360001.98 | CC18: =CB18-CD18 -> 9161.4383 | CD18: =Budgets!AP80 -> -369163.42 | CE18: =CD18-CF18 -> -15587.076 | CF18: =Budgets!AQ80 -> -353576.34 | CG18: =CF18-CH18 -> 10001.823 | CH18: =Budgets!AR80 -> -363578.17 | CI18: =CH18-CJ18 -> 16190.573 | CJ18: =Budgets!AS80 -> -379768.74 | CK18: =CJ18-CL18 -> -15518.678 | CL18: =Budgets!AT80 -> -364250.06 | CM18: =CL18-CN18 -> 17240.573 | CN18: =Budgets!AU80 -> -381490.63 | CO18: =CN18-CP18 -> 15085.156 | CP18: =Budgets!AV80 -> -396575.79 | CQ18: =CP18-CR18 -> -29647.812 | CR18: =Budgets!AW80 -> -366927.98 | CS18: =CR18-CT18 -> 17718.489 | CT18: =Budgets!AX80 -> -384646.47 | CU18: =CT18-CV18 -> 18558.489 | CV18: =Budgets!AY80 -> -403204.96 | CW18: =CV18-CX18 -> -34742.395 | CX18: =Budgets!AZ80 -> -368462.56 | CY18: =CX18-CZ18 -> 16063.073 | CZ18: =Budgets!BA80 -> -384525.63 | DA18: =CZ18-DB18 -> 14857.656 | DB18: =Budgets!BB80 -> -399383.29 | DC18: =DB18-DD18 -> -34897.825 | DD18: =Budgets!BC80 -> -364485.47 | DE18: =DD18-DF18 -> 15786.81 | DF18: =Budgets!BD80 -> -380272.28 | DG18: =DF18-DH18 -> 16236.81 | DH18: =Budgets!BE80 -> -396509.09 | DI18: =DH18-DJ18 -> -31594.466 | DJ18: =Budgets!BF80 -> -364914.62 | DK18: =DJ18-DL18 -> 13181.393 | DL18: =Budgets!BG80 -> -378096.01 | DM18: =DL18-DN18 -> 13631.393 | DN18: =Budgets!BH80 -> -391727.41 | DO18: =DN18-DP18 -> -32729.036 | DP18: =Budgets!BI80 -> -358998.37 | DQ18: =DP18-DR18 -> 11525.976 | DR18: =Budgets!BJ80 -> -370524.35 | DS18: =DR18-DT18 -> 12125.976 | DT18: =Budgets!BK80 -> -382650.32 | DU18: =DT18-DV18 -> -25057.369 | DV18: =Budgets!BL80 -> -357592.95 | DW18: =DV18-DX18 -> 11625.976 | DX18: =Budgets!BM80 -> -369218.93 | DY18: =DX18-DZ18 -> 12075.976 | DZ18: =Budgets!BN80 -> -381294.91 | EA18: =DZ18-EB18 -> 13025.976 | EB18: =Budgets!BO80 -> -394320.88 | EC18: =EB18-ED18 -> 12575.976 | ED18: =Budgets!BP80 -> -406896.86 | EE18: =ED18-EF18 -> 11718.476 | EF18: =Budgets!BQ80 -> -418615.33 | EG18: =EF18-EH18 -> 11718.476 | EH18: =Budgets!BR80 -> -430333.81 | EI18: =EH18-EJ18 -> 15181.393 | EJ18: =Budgets!BS80 -> -445515.2 | EK18: =EJ18-EL18 -> 13112.643 | EL18: =Budgets!BT80 -> -458627.85 | EM18: =EL18-EN18 -> 13562.643 | EN18: =Budgets!BU80 -> -472190.49 | EO18: =EN18-EP18 -> 16336.81 | EP18: =Budgets!BV80 -> -488527.3 | EQ18: =EP18-ER18 -> 14420.143 | ER18: =Budgets!BW80 -> -502947.44 | ES18: =ER18-ET18 -> 15218.06 | ET18: =Budgets!BX80 -> -518165.5 | EU18: =ET18-EV18 -> 15386.81 | EV18: =Budgets!BY80 -> -533552.31 | EW18: =EV18-EX18 -> 18680.976 | EX18: =Budgets!BZ80 -> -552233.29
A19: Total Current Liabilities | B19: =SUM(B16:B18) -> -310568.28 | D19: =SUM(D16:D18) -> -310568.28 | F19: =SUM(F16:F18) -> -417223.44 | H19: =SUM(H16:H18) -> -455623.82 | J19: =SUM(J16:J18) -> -454034 | L19: =SUM(L16:L18) -> -81090.675 | N19: =SUM(N16:N18) -> -190696.68 | P19: =SUM(P16:P18) -> -307856.68 | R19: =SUM(R16:R18) -> -541576.81 | T19: =SUM(T16:T18) -> -495476.81 | V19: =SUM(V16:V18) -> -572650.81 | X19: =SUM(X16:X18) -> -494246.14 | Z19: =SUM(Z16:Z18) -> -444394.87 | AB19: =SUM(AB16:AB18) -> -400575.21 | AD19: =SUM(AD16:AD18) -> -399445.81 | AF19: =SUM(AF16:AF18) -> -376107.81 | AH19: =SUM(AH16:AH18) -> -388249.81 | AJ19: =SUM(AJ16:AJ18) -> -503739.09 | AL19: =SUM(AL16:AL18) -> -501932.03 | AN19: =SUM(AN16:AN18) -> -475368.45 | AP19: =SUM(AP16:AP18) -> -727214.45 | AR19: =SUM(AR16:AR18) -> -758937.8 | AT19: =SUM(AT16:AT18) -> -539946.96 | AV19: =SUM(AV16:AV18) -> -486252.28 | AX19: =SUM(AX16:AX18) -> -457951.13 | AZ19: =SUM(AZ16:AZ18) -> -546817.9 | BB19: =SUM(BB16:BB18) -> -514675.31 | BD19: =SUM(BD16:BD18) -> -467064.99 | BF19: =SUM(BF16:BF18) -> -452303.01 | BH19: =SUM(BH16:BH18) -> -537407.32 | BJ19: =SUM(BJ16:BJ18) -> -666714.59 | BL19: =SUM(BL16:BL18) -> -765178.11 | BN19: =SUM(BN16:BN18) -> -726628.24 | BP19: =SUM(BP16:BP18) -> -845328.01 | BR19: =SUM(BR16:BR18) -> -772975.7 | BT19: =SUM(BT16:BT18) -> -630494.49 | BV19: =SUM(BV16:BV18) -> -605709.26 | BX19: =SUM(BX16:BX18) -> -721234.45 | BZ19: =SUM(BZ16:BZ18) -> -817544.07 | CB19: =SUM(CB16:CB18) -> -763422.18 | CD19: =SUM(CD16:CD18) -> -544583.62 | CF19: =SUM(CF16:CF18) -> -563276.06 | CH19: =SUM(CH16:CH18) -> -861277.88 | CJ19: =SUM(CJ16:CJ18) -> -931528.46 | CL19: =SUM(CL16:CL18) -> -772009.78 | CN19: =SUM(CN16:CN18) -> -875650.35 | CP19: =SUM(CP16:CP18) -> -786335.51 | CR19: =SUM(CR16:CR18) -> -670347.7 | CT19: =SUM(CT16:CT18) -> -732466.19 | CV19: =SUM(CV16:CV18) -> -793024.68 | CX19: =SUM(CX16:CX18) -> -866282.28 | CZ19: =SUM(CZ16:CZ18) -> -792345.35 | DB19: =SUM(DB16:DB18) -> -579203.01 | DD19: =SUM(DD16:DD18) -> -656735.68 | DF19: =SUM(DF16:DF18) -> -942522.49 | DH19: =SUM(DH16:DH18) -> -970759.3 | DJ19: =SUM(DJ16:DJ18) -> -837164.83 | DL19: =SUM(DL16:DL18) -> -966746.23 | DN19: =SUM(DN16:DN18) -> -905977.62 | DP19: =SUM(DP16:DP18) -> -684848.58 | DR19: =SUM(DR16:DR18) -> -662774.56 | DT19: =SUM(DT16:DT18) -> -776900.54 | DV19: =SUM(DV16:DV18) -> -949843.17 | DX19: =SUM(DX16:DX18) -> -811469.14 | DZ19: =SUM(DZ16:DZ18) -> -565545.12 | EB19: =SUM(EB16:EB18) -> -699171.09 | ED19: =SUM(ED16:ED18) -> -951747.07 | EF19: =SUM(EF16:EF18) -> -993465.55 | EH19: =SUM(EH16:EH18) -> -945184.02 | EJ19: =SUM(EJ16:EJ18) -> -990365.42 | EL19: =SUM(EL16:EL18) -> -943478.06 | EN19: =SUM(EN16:EN18) -> -867040.7 | EP19: =SUM(EP16:EP18) -> -823377.51 | ER19: =SUM(ER16:ER18) -> -897797.66 | ET19: =SUM(ET16:ET18) -> -1123015.7 | EV19: =SUM(EV16:EV18) -> -988402.53 | EX19: =SUM(EX16:EX18) -> -737083.5
A21: Loans | B21: ='Balance Sheet'!G22 -> -384120 | D21: =B21 -> -384120 | E21: =D21-F21 -> -154440 | F21: =Budgets!D83 -> -229680 | G21: =F21-H21 -> 0 | H21: =Budgets!E83 -> -229680 | I21: =H21-J21 -> -12000 | J21: =Budgets!F83 -> -217680 | K21: =J21-L21 -> -12000 | L21: =Budgets!G83 -> -205680 | M21: =L21-N21 -> -12000 | N21: =Budgets!H83 -> -193680 | O21: =N21-P21 -> 0 | P21: =Budgets!I83 -> -193680 | Q21: =P21-R21 -> 0 | R21: =Budgets!J83 -> -193680 | S21: =R21-T21 -> 0 | T21: =Budgets!K83 -> -193680 | U21: =T21-V21 -> 0 | V21: =Budgets!L83 -> -193680 | W21: =V21-X21 -> 0 | X21: =Budgets!M83 -> -193680 | Y21: =X21-Z21 -> 0 | Z21: =Budgets!N83 -> -193680 | AA21: =Z21-AB21 -> 0 | AB21: =Budgets!O83 -> -193680 | AC21: =AB21-AD21 -> 0 | AD21: =Budgets!P83 -> -193680 | AE21: =AD21-AF21 -> 0 | AF21: =Budgets!Q83 -> -193680 | AG21: =AF21-AH21 -> 0 | AH21: =Budgets!R83 -> -193680 | AI21: =AH21-AJ21 -> 0 | AJ21: =Budgets!S83 -> -193680 | AK21: =AJ21-AL21 -> 0 | AL21: =Budgets!T83 -> -193680 | AM21: =AL21-AN21 -> 0 | AN21: =Budgets!U83 -> -193680 | AO21: =AN21-AP21 -> -12000 | AP21: =Budgets!V83 -> -181680 | AQ21: =AP21-AR21 -> -12000 | AR21: =Budgets!W83 -> -169680 | AS21: =AR21-AT21 -> -12000 | AT21: =Budgets!X83 -> -157680 | AU21: =AT21-AV21 -> -12000 | AV21: =Budgets!Y83 -> -145680 | AW21: =AV21-AX21 -> -12000 | AX21: =Budgets!Z83 -> -133680 | AY21: =AX21-AZ21 -> -12000 | AZ21: =Budgets!AA83 -> -121680 | BA21: =AZ21-BB21 -> -12000 | BB21: =Budgets!AB83 -> -109680 | BC21: =BB21-BD21 -> -12000 | BD21: =Budgets!AC83 -> -97680 | BE21: =BD21-BF21 -> -12000 | BF21: =Budgets!AD83 -> -85680 | BG21: =BF21-BH21 -> -12000 | BH21: =Budgets!AE83 -> -73680 | BI21: =BH21-BJ21 -> -12000 | BJ21: =Budgets!AF83 -> -61680 | BK21: =BJ21-BL21 -> -12000 | BL21: =Budgets!AG83 -> -49680 | BM21: =BL21-BN21 -> -12000 | BN21: =Budgets!AH83 -> -37680 | BO21: =BN21-BP21 -> -12000 | BP21: =Budgets!AI83 -> -25680 | BQ21: =BP21-BR21 -> -12000 | BR21: =Budgets!AJ83 -> -13680 | BS21: =BR21-BT21 -> -12000 | BT21: =Budgets!AK83 -> -1680 | BU21: =BT21-BV21 -> -1680 | BV21: =Budgets!AL83 -> 0 | BW21: =BV21-BX21 -> 0 | BX21: =Budgets!AM83 -> 0 | BY21: =BX21-BZ21 -> 0 | BZ21: =Budgets!AN83 -> 0 | CA21: =BZ21-CB21 -> 0 | CB21: =Budgets!AO83 -> 0 | CC21: =CB21-CD21 -> 0 | CD21: =Budgets!AP83 -> 0 | CE21: =CD21-CF21 -> 0 | CF21: =Budgets!AQ83 -> 0 | CG21: =CF21-CH21 -> 0 | CH21: =Budgets!AR83 -> 0 | CI21: =CH21-CJ21 -> 0 | CJ21: =Budgets!AS83 -> 0 | CK21: =CJ21-CL21 -> 0 | CL21: =Budgets!AT83 -> 0 | CM21: =CL21-CN21 -> 0 | CN21: =Budgets!AU83 -> 0 | CO21: =CN21-CP21 -> 0 | CP21: =Budgets!AV83 -> 0 | CQ21: =CP21-CR21 -> 0 | CR21: =Budgets!AW83 -> 0 | CS21: =CR21-CT21 -> 0 | CT21: =Budgets!AX83 -> 0 | CU21: =CT21-CV21 -> 0 | CV21: =Budgets!AY83 -> 0 | CW21: =CV21-CX21 -> 0 | CX21: =Budgets!AZ83 -> 0 | CY21: =CX21-CZ21 -> 0 | CZ21: =Budgets!BA83 -> 0 | DA21: =CZ21-DB21 -> 0 | DB21: =Budgets!BB83 -> 0 | DC21: =DB21-DD21 -> 0 | DD21: =Budgets!BC83 -> 0 | DE21: =DD21-DF21 -> 0 | DF21: =Budgets!BD83 -> 0 | DG21: =DF21-DH21 -> 0 | DH21: =Budgets!BE83 -> 0 | DI21: =DH21-DJ21 -> 0 | DJ21: =Budgets!BF83 -> 0 | DK21: =DJ21-DL21 -> 0 | DL21: =Budgets!BG83 -> 0 | DM21: =DL21-DN21 -> 0 | DN21: =Budgets!BH83 -> 0 | DO21: =DN21-DP21 -> 0 | DP21: =Budgets!BI83 -> 0 | DQ21: =DP21-DR21 -> 0 | DR21: =Budgets!BJ83 -> 0 | DS21: =DR21-DT21 -> 0 | DT21: =Budgets!BK83 -> 0 | DU21: =DT21-DV21 -> 0 | DV21: =Budgets!BL83 -> 0 | DW21: =DV21-DX21 -> 0 | DX21: =Budgets!BM83 -> 0 | DY21: =DX21-DZ21 -> 0 | DZ21: =Budgets!BN83 -> 0 | EA21: =DZ21-EB21 -> 0 | EB21: =Budgets!BO83 -> 0 | EC21: =EB21-ED21 -> 0 | ED21: =Budgets!BP83 -> 0 | EE21: =ED21-EF21 -> 0 | EF21: =Budgets!BQ83 -> 0 | EG21: =EF21-EH21 -> 0 | EH21: =Budgets!BR83 -> 0 | EI21: =EH21-EJ21 -> 0 | EJ21: =Budgets!BS83 -> 0 | EK21: =EJ21-EL21 -> 0 | EL21: =Budgets!BT83 -> 0 | EM21: =EL21-EN21 -> 0 | EN21: =Budgets!BU83 -> 0 | EO21: =EN21-EP21 -> 0 | EP21: =Budgets!BV83 -> 0 | EQ21: =EP21-ER21 -> 0 | ER21: =Budgets!BW83 -> 0 | ES21: =ER21-ET21 -> 0 | ET21: =Budgets!BX83 -> 0 | EU21: =ET21-EV21 -> 0 | EV21: =Budgets!BY83 -> 0 | EW21: =EV21-EX21 -> 0 | EX21: =Budgets!BZ83 -> 0
A23: Net Assets | B23: =B4+B8+B14+B19+B21 -> 2134520.5 | D23: =D4+D8+D14+D19+D21 -> 2134520.5 | F23: =F4+F8+F14+F19+F21 -> 1575830.9 | H23: =H4+H8+H14+H19+H21 -> 1218551.8 | J23: =J4+J8+J14+J19+J21 -> 782759.37 | L23: =L4+L8+L14+L19+L21 -> 408636.91 | N23: =N4+N8+N14+N19+N21 -> 35994.458 | P23: =P4+P8+P14+P19+P21 -> 105870 | R23: =R4+R8+R14+R19+R21 -> -275306.75 | T23: =T4+T8+T14+T19+T21 -> -514789.51 | V23: =V4+V8+V14+V19+V21 -> -765578.05 | X23: =X4+X8+X14+X19+X21 -> -888334.59 | Z23: =Z4+Z8+Z14+Z19+Z21 -> -992341.13 | AB23: =AB4+AB8+AB14+AB19+AB21 -> -1173678.7 | AD23: =AD4+AD8+AD14+AD19+AD21 -> -1294975.5 | AF23: =AF4+AF8+AF14+AF19+AF21 -> -1434542.2 | AH23: =AH4+AH8+AH14+AH19+AH21 -> -1553909 | AJ23: =AJ4+AJ8+AJ14+AJ19+AJ21 -> -1860535.2 | AL23: =AL4+AL8+AL14+AL19+AL21 -> -2117860.9 | AN23: =AN4+AN8+AN14+AN19+AN21 -> -2444362.1 | AP23: =AP4+AP8+AP14+AP19+AP21 -> -2309823.6 | AR23: =AR4+AR8+AR14+AR19+AR21 -> -2603330.7 | AT23: =AT4+AT8+AT14+AT19+AT21 -> -2936929.2 | AV23: =AV4+AV8+AV14+AV19+AV21 -> -3196234.6 | AX23: =AX4+AX8+AX14+AX19+AX21 -> -3338866.7 | AZ23: =AZ4+AZ8+AZ14+AZ19+AZ21 -> -3554988.8 | BB23: =BB4+BB8+BB14+BB19+BB21 -> -3743870.5 | BD23: =BD4+BD8+BD14+BD19+BD21 -> -3888717.2 | BF23: =BF4+BF8+BF14+BF19+BF21 -> -3910890.6 | BH23: =BH4+BH8+BH14+BH19+BH21 -> -4051136.6 | BJ23: =BJ4+BJ8+BJ14+BJ19+BJ21 -> -4127447.7 | BL23: =BL4+BL8+BL14+BL19+BL21 -> -4100983.5 | BN23: =BN4+BN8+BN14+BN19+BN21 -> -3774433 | BP23: =BP4+BP8+BP14+BP19+BP21 -> -3629332.7 | BR23: =BR4+BR8+BR14+BR19+BR21 -> -3581092.1 | BT23: =BT4+BT8+BT14+BT19+BT21 -> -3517483 | BV23: =BV4+BV8+BV14+BV19+BV21 -> -3364061.5 | BX23: =BX4+BX8+BX14+BX19+BX21 -> -3256890 | BZ23: =BZ4+BZ8+BZ14+BZ19+BZ21 -> -2944697.7 | CB23: =CB4+CB8+CB14+CB19+CB21 -> -2332692.8 | CD23: =CD4+CD8+CD14+CD19+CD21 -> -1934354.7 | CF23: =CF4+CF8+CF14+CF19+CF21 -> -1476335.3 | CH23: =CH4+CH8+CH14+CH19+CH21 -> -753107.5 | CJ23: =CJ4+CJ8+CJ14+CJ19+CJ21 -> -109751.38 | CL23: =CL4+CL8+CL14+CL19+CL21 -> 943121 | CN23: =CN4+CN8+CN14+CN19+CN21 -> 1876618.4 | CP23: =CP4+CP8+CP14+CP19+CP21 -> 2809594.9 | CR23: =CR4+CR8+CR14+CR19+CR21 -> 3846887.3 | CT23: =CT4+CT8+CT14+CT19+CT21 -> 5147179.7 | CV23: =CV4+CV8+CV14+CV19+CV21 -> 6366076.3 | CX23: =CX4+CX8+CX14+CX19+CX21 -> 7948597.9 | CZ23: =CZ4+CZ8+CZ14+CZ19+CZ21 -> 9742015.3 | DB23: =DB4+DB8+DB14+DB19+DB21 -> 11825224 | DD23: =DD4+DD8+DD14+DD19+DD21 -> 14143407 | DF23: =DF4+DF8+DF14+DF19+DF21 -> 16469485 | DH23: =DH4+DH8+DH14+DH19+DH21 -> 18939751 | DJ23: =DJ4+DJ8+DJ14+DJ19+DJ21 -> 21682700 | DL23: =DL4+DL8+DL14+DL19+DL21 -> 24613858 | DN23: =DN4+DN8+DN14+DN19+DN21 -> 27651578 | DP23: =DP4+DP8+DP14+DP19+DP21 -> 30935840 | DR23: =DR4+DR8+DR14+DR19+DR21 -> 34578123 | DT23: =DT4+DT8+DT14+DT19+DT21 -> 38397760 | DV23: =DV4+DV8+DV14+DV19+DV21 -> 42637939 | DX23: =DX4+DX8+DX14+DX19+DX21 -> 47212347 | DZ23: =DZ4+DZ8+DZ14+DZ19+DZ21 -> 52085984 | EB23: =EB4+EB8+EB14+EB19+EB21 -> 57023183 | ED23: =ED4+ED8+ED14+ED19+ED21 -> 62199258 | EF23: =EF4+EF8+EF14+EF19+EF21 -> 67787999 | EH23: =EH4+EH8+EH14+EH19+EH21 -> 73525365 | EJ23: =EJ4+EJ8+EJ14+EJ19+EJ21 -> 79310939 | EL23: =EL4+EL8+EL14+EL19+EL21 -> 85399931 | EN23: =EN4+EN8+EN14+EN19+EN21 -> 91975922 | EP23: =EP4+EP8+EP14+EP19+EP21 -> 98399142 | ER23: =ER4+ER8+ER14+ER19+ER21 -> 1.0515178e+08 | ET23: =ET4+ET8+ET14+ET19+ET21 -> 1.1231458e+08 | EV23: =EV4+EV8+EV14+EV19+EV21 -> 1.1912814e+08 | EX23: =EX4+EX8+EX14+EX19+EX21 -> 1.2597363e+08
A25: Share Cap
A26: Share capital | B26: ='Balance Sheet'!G27 -> 221.76 | D26: =B26 -> 221.76 | E26: =F26-D26 -> 24.24 | F26: =Budgets!D88 -> 246 | G26: =H26-H26 -> 0 | H26: =Budgets!E88 -> 246 | I26: =J26-J26 -> 0 | J26: =Budgets!F88 -> 246 | K26: =L26-L26 -> 0 | L26: =Budgets!G88 -> 246 | M26: =N26-N26 -> 0 | N26: =Budgets!H88 -> 246 | O26: =P26-P26 -> 0 | P26: =Budgets!I88 -> 246 | Q26: =R26-R26 -> 0 | R26: =Budgets!J88 -> 246 | S26: =T26-T26 -> 0 | T26: =Budgets!K88 -> 246 | U26: =V26-V26 -> 0 | V26: =Budgets!L88 -> 246 | W26: =X26-X26 -> 0 | X26: =Budgets!M88 -> 246 | Y26: =Z26-Z26 -> 0 | Z26: =Budgets!N88 -> 246 | AA26: =AB26-AB26 -> 0 | AB26: =Budgets!O88 -> 246 | AC26: =AD26-AD26 -> 0 | AD26: =Budgets!P88 -> 246 | AE26: =AF26-AF26 -> 0 | AF26: =Budgets!Q88 -> 246 | AG26: =AH26-AH26 -> 0 | AH26: =Budgets!R88 -> 246 | AI26: =AJ26-AJ26 -> 0 | AJ26: =Budgets!S88 -> 246 | AK26: =AL26-AL26 -> 0 | AL26: =Budgets!T88 -> 246 | AM26: =AN26-AN26 -> 0 | AN26: =Budgets!U88 -> 246 | AO26: =AP26-AP26 -> 0 | AP26: =Budgets!V88 -> 246 | AQ26: =AR26-AR26 -> 0 | AR26: =Budgets!W88 -> 246 | AS26: =AT26-AT26 -> 0 | AT26: =Budgets!X88 -> 246 | AU26: =AV26-AV26 -> 0 | AV26: =Budgets!Y88 -> 246 | AW26: =AX26-AX26 -> 0 | AX26: =Budgets!Z88 -> 246 | AY26: =AZ26-AZ26 -> 0 | AZ26: =Budgets!AA88 -> 246 | BA26: =AH26-AH26 -> 0 | BB26: =Budgets!AB88 -> 246 | BC26: =BD26-BD26 -> 0 | BD26: =Budgets!AC88 -> 246 | BE26: =BF26-BF26 -> 0 | BF26: =Budgets!AD88 -> 246 | BG26: =BH26-BH26 -> 0 | BH26: =Budgets!AE88 -> 246 | BI26: =BJ26-BJ26 -> 0 | BJ26: =Budgets!AF88 -> 246 | BK26: =BL26-BL26 -> 0 | BL26: =Budgets!AG88 -> 246 | BM26: =BN26-BN26 -> 0 | BN26: =Budgets!AH88 -> 246 | BO26: =BP26-BP26 -> 0 | BP26: =Budgets!AI88 -> 246 | BQ26: =BR26-BR26 -> 0 | BR26: =Budgets!AJ88 -> 246 | BS26: =BT26-BT26 -> 0 | BT26: =Budgets!AK88 -> 246 | BU26: =BV26-BV26 -> 0 | BV26: =Budgets!AL88 -> 246 | BW26: =BX26-BX26 -> 0 | BX26: =Budgets!AM88 -> 246 | BY26: =BZ26-BZ26 -> 0 | BZ26: =Budgets!AN88 -> 246 | CA26: =BZ26-CB26 -> 0 | CB26: =Budgets!AO88 -> 246 | CC26: =CB26-CD26 -> 0 | CD26: =Budgets!AP88 -> 246 | CE26: =CF26-CF26 -> 0 | CF26: =Budgets!AQ88 -> 246 | CG26: =CH26-CH26 -> 0 | CH26: =Budgets!AR88 -> 246 | CI26: =CJ26-CJ26 -> 0 | CJ26: =Budgets!AS88 -> 246 | CK26: =CL26-CL26 -> 0 | CL26: =Budgets!AT88 -> 246 | CM26: =CN26-CN26 -> 0 | CN26: =Budgets!AU88 -> 246 | CO26: =CP26-CP26 -> 0 | CP26: =Budgets!AV88 -> 246 | CQ26: =CR26-CR26 -> 0 | CR26: =Budgets!AW88 -> 246 | CS26: =CT26-CT26 -> 0 | CT26: =Budgets!AX88 -> 246 | CU26: =CV26-CV26 -> 0 | CV26: =Budgets!AY88 -> 246 | CW26: =CX26-CX26 -> 0 | CX26: =Budgets!AZ88 -> 246 | CY26: =CZ26-CZ26 -> 0 | CZ26: =Budgets!BA88 -> 246 | DA26: =DB26-DB26 -> 0 | DB26: =Budgets!BB88 -> 246 | DC26: =DD26-DD26 -> 0 | DD26: =Budgets!BC88 -> 246 | DE26: =DF26-DF26 -> 0 | DF26: =Budgets!BD88 -> 246 | DG26: =DH26-DH26 -> 0 | DH26: =Budgets!BE88 -> 246 | DI26: =DJ26-DJ26 -> 0 | DJ26: =Budgets!BF88 -> 246 | DK26: =DL26-DL26 -> 0 | DL26: =Budgets!BG88 -> 246 | DM26: =DN26-DN26 -> 0 | DN26: =Budgets!BH88 -> 246 | DO26: =DP26-DP26 -> 0 | DP26: =Budgets!BI88 -> 246 | DQ26: =DR26-DR26 -> 0 | DR26: =Budgets!BJ88 -> 246 | DS26: =DT26-DT26 -> 0 | DT26: =Budgets!BK88 -> 246 | DU26: =DV26-DV26 -> 0 | DV26: =Budgets!BL88 -> 246 | DW26: =DX26-DX26 -> 0 | DX26: =Budgets!BM88 -> 246 | DY26: =DZ26-DZ26 -> 0 | DZ26: =Budgets!BN88 -> 246 | EA26: =EB26-EB26 -> 0 | EB26: =Budgets!BO88 -> 246 | EC26: =ED26-ED26 -> 0 | ED26: =Budgets!BP88 -> 246 | EE26: =EF26-EF26 -> 0 | EF26: =Budgets!BQ88 -> 246 | EG26: =EH26-EH26 -> 0 | EH26: =Budgets!BR88 -> 246 | EI26: =EJ26-EJ26 -> 0 | EJ26: =Budgets!BS88 -> 246 | EK26: =EL26-EL26 -> 0 | EL26: =Budgets!BT88 -> 246 | EM26: =EN26-EN26 -> 0 | EN26: =Budgets!BU88 -> 246 | EO26: =EP26-EP26 -> 0 | EP26: =Budgets!BV88 -> 246 | EQ26: =ER26-ER26 -> 0 | ER26: =Budgets!BW88 -> 246 | ES26: =ET26-ET26 -> 0 | ET26: =Budgets!BX88 -> 246 | EU26: =EV26-EV26 -> 0 | EV26: =Budgets!BY88 -> 246 | EW26: =EX26-EX26 -> 0 | EX26: =Budgets!BZ88 -> 246
A27: Share premium | B27: ='Balance Sheet'!G28 -> 9674087.3 | D27: =B27 -> 9674087.3 | E27: =F27-D27 -> 2642592.7 | F27: =Budgets!D89 -> 12316680 | G27: =H27-F27 -> 0 | H27: =Budgets!E89 -> 12316680 | I27: =J27-H27 -> 0 | J27: =Budgets!F89 -> 12316680 | K27: =L27-J27 -> 0 | L27: =Budgets!G89 -> 12316680 | M27: =N27-L27 -> 0 | N27: =Budgets!H89 -> 12316680 | O27: =P27-N27 -> 0 | P27: =Budgets!I89 -> 12316680 | Q27: =R27-P27 -> 0 | R27: =Budgets!J89 -> 12316680 | S27: =T27-R27 -> 0 | T27: =Budgets!K89 -> 12316680 | U27: =V27-T27 -> 0 | V27: =Budgets!L89 -> 12316680 | W27: =X27-V27 -> 0 | X27: =Budgets!M89 -> 12316680 | Y27: =Z27-X27 -> 0 | Z27: =Budgets!N89 -> 12316680 | AA27: =AB27-Z27 -> 0 | AB27: =Budgets!O89 -> 12316680 | AC27: =AD27-AB27 -> 0 | AD27: =Budgets!P89 -> 12316680 | AE27: =AF27-AD27 -> 0 | AF27: =Budgets!Q89 -> 12316680 | AG27: =AH27-AF27 -> 0 | AH27: =Budgets!R89 -> 12316680 | AI27: =AJ27-AH27 -> 0 | AJ27: =Budgets!S89 -> 12316680 | AK27: =AL27-AJ27 -> 0 | AL27: =Budgets!T89 -> 12316680 | AM27: =AN27-AL27 -> 0 | AN27: =Budgets!U89 -> 12316680 | AO27: =AP27-AN27 -> 0 | AP27: =Budgets!V89 -> 12316680 | AQ27: =AR27-AP27 -> 0 | AR27: =Budgets!W89 -> 12316680 | AS27: =AT27-AR27 -> 0 | AT27: =Budgets!X89 -> 12316680 | AU27: =AV27-AT27 -> 0 | AV27: =Budgets!Y89 -> 12316680 | AW27: =AX27-AV27 -> 0 | AX27: =Budgets!Z89 -> 12316680 | AY27: =AZ27-AX27 -> 0 | AZ27: =Budgets!AA89 -> 12316680 | BA27: =AH27-AZ27 -> 0 | BB27: =Budgets!AB89 -> 12316680 | BC27: =BD27-AH27 -> 0 | BD27: =Budgets!AC89 -> 12316680 | BE27: =BF27-BD27 -> 0 | BF27: =Budgets!AD89 -> 12316680 | BG27: =BH27-BF27 -> 0 | BH27: =Budgets!AE89 -> 12316680 | BI27: =BJ27-BH27 -> 0 | BJ27: =Budgets!AF89 -> 12316680 | BK27: =BL27-BJ27 -> 0 | BL27: =Budgets!AG89 -> 12316680 | BM27: =BN27-BL27 -> 0 | BN27: =Budgets!AH89 -> 12316680 | BO27: =BP27-BN27 -> 0 | BP27: =Budgets!AI89 -> 12316680 | BQ27: =BR27-BP27 -> 0 | BR27: =Budgets!AJ89 -> 12316680 | BS27: =BT27-BR27 -> 0 | BT27: =Budgets!AK89 -> 12316680 | BU27: =BV27-BT27 -> 0 | BV27: =Budgets!AL89 -> 12316680 | BW27: =BX27-BV27 -> 0 | BX27: =Budgets!AM89 -> 12316680 | BY27: =BZ27-BX27 -> 0 | BZ27: =Budgets!AN89 -> 12316680 | CA27: =BZ27-CB27 -> 0 | CB27: =Budgets!AO89 -> 12316680 | CC27: =CB27-CD27 -> 0 | CD27: =Budgets!AP89 -> 12316680 | CE27: =CF27-CD27 -> 0 | CF27: =Budgets!AQ89 -> 12316680 | CG27: =CH27-CF27 -> 0 | CH27: =Budgets!AR89 -> 12316680 | CI27: =CJ27-CH27 -> 0 | CJ27: =Budgets!AS89 -> 12316680 | CK27: =CL27-CJ27 -> 0 | CL27: =Budgets!AT89 -> 12316680 | CM27: =CN27-CL27 -> 0 | CN27: =Budgets!AU89 -> 12316680 | CO27: =CP27-CN27 -> 0 | CP27: =Budgets!AV89 -> 12316680 | CQ27: =CR27-CP27 -> 0 | CR27: =Budgets!AW89 -> 12316680 | CS27: =CT27-CR27 -> 0 | CT27: =Budgets!AX89 -> 12316680 | CU27: =CV27-CT27 -> 0 | CV27: =Budgets!AY89 -> 12316680 | CW27: =CX27-CV27 -> 0 | CX27: =Budgets!AZ89 -> 12316680 | CY27: =CZ27-CX27 -> 0 | CZ27: =Budgets!BA89 -> 12316680 | DA27: =DB27-CZ27 -> 0 | DB27: =Budgets!BB89 -> 12316680 | DC27: =DD27-DB27 -> 0 | DD27: =Budgets!BC89 -> 12316680 | DE27: =DF27-DD27 -> 0 | DF27: =Budgets!BD89 -> 12316680 | DG27: =DH27-DF27 -> 0 | DH27: =Budgets!BE89 -> 12316680 | DI27: =DJ27-DH27 -> 0 | DJ27: =Budgets!BF89 -> 12316680 | DK27: =DL27-DJ27 -> 0 | DL27: =Budgets!BG89 -> 12316680 | DM27: =DN27-DL27 -> 0 | DN27: =Budgets!BH89 -> 12316680 | DO27: =DP27-DN27 -> 0 | DP27: =Budgets!BI89 -> 12316680 | DQ27: =DR27-DP27 -> 0 | DR27: =Budgets!BJ89 -> 12316680 | DS27: =DT27-DR27 -> 0 | DT27: =Budgets!BK89 -> 12316680 | DU27: =DV27-DT27 -> 0 | DV27: =Budgets!BL89 -> 12316680 | DW27: =DX27-DV27 -> 0 | DX27: =Budgets!BM89 -> 12316680 | DY27: =DZ27-DX27 -> 0 | DZ27: =Budgets!BN89 -> 12316680 | EA27: =EB27-DZ27 -> 0 | EB27: =Budgets!BO89 -> 12316680 | EC27: =ED27-EB27 -> 0 | ED27: =Budgets!BP89 -> 12316680 | EE27: =EF27-ED27 -> 0 | EF27: =Budgets!BQ89 -> 12316680 | EG27: =EH27-EF27 -> 0 | EH27: =Budgets!BR89 -> 12316680 | EI27: =EJ27-EH27 -> 0 | EJ27: =Budgets!BS89 -> 12316680 | EK27: =EL27-EJ27 -> 0 | EL27: =Budgets!BT89 -> 12316680 | EM27: =EN27-EL27 -> 0 | EN27: =Budgets!BU89 -> 12316680 | EO27: =EP27-EN27 -> 0 | EP27: =Budgets!BV89 -> 12316680 | EQ27: =ER27-EP27 -> 0 | ER27: =Budgets!BW89 -> 12316680 | ES27: =ET27-ER27 -> 0 | ET27: =Budgets!BX89 -> 12316680 | EU27: =EV27-ET27 -> 0 | EV27: =Budgets!BY89 -> 12316680 | EW27: =EX27-EV27 -> 0 | EX27: =Budgets!BZ89 -> 12316680
A28: Other reserve | B28: ='Balance Sheet'!G29 -> 0 | D28: =B28 -> 0 | E28: =F28-F28 -> 0 | F28: =Budgets!D90 -> 0 | G28: =H28-H28 -> 0 | H28: =Budgets!E90 -> 0 | I28: =J28-J28 -> 0 | J28: =Budgets!F90 -> 0 | K28: =L28-L28 -> 0 | L28: =Budgets!G90 -> 0 | M28: =N28-N28 -> 0 | N28: =Budgets!H90 -> 0 | O28: =P28-P28 -> 0 | P28: =Budgets!I90 -> 0 | Q28: =R28-R28 -> 0 | R28: =Budgets!J90 -> 0 | S28: =T28-T28 -> 0 | T28: =Budgets!K90 -> 0 | U28: =V28-V28 -> 0 | V28: =Budgets!L90 -> 0 | W28: =X28-X28 -> 0 | X28: =Budgets!M90 -> 0 | Y28: =Z28-Z28 -> 0 | Z28: =Budgets!N90 -> 0 | AA28: =AB28-AB28 -> 0 | AB28: =Budgets!O90 -> 0 | AC28: =AD28-AD28 -> 0 | AD28: =Budgets!P90 -> 0 | AE28: =AF28-AF28 -> 0 | AF28: =Budgets!Q90 -> 0 | AG28: =AH28-AH28 -> 0 | AH28: =Budgets!R90 -> 0 | AI28: =AJ28-AJ28 -> 0 | AJ28: =Budgets!S90 -> 0 | AK28: =AL28-AL28 -> 0 | AL28: =Budgets!T90 -> 0 | AM28: =AN28-AN28 -> 0 | AN28: =Budgets!U90 -> 0 | AO28: =AP28-AP28 -> 0 | AP28: =Budgets!V90 -> 0 | AQ28: =AR28-AR28 -> 0 | AR28: =Budgets!W90 -> 0 | AS28: =AT28-AT28 -> 0 | AT28: =Budgets!X90 -> 0 | AU28: =AV28-AV28 -> 0 | AV28: =Budgets!Y90 -> 0 | AW28: =AX28-AX28 -> 0 | AX28: =Budgets!Z90 -> 0 | AY28: =AZ28-AZ28 -> 0 | AZ28: =Budgets!AA90 -> 0 | BA28: =AH28-AH28 -> 0 | BB28: =Budgets!AB90 -> 0 | BC28: =BD28-BD28 -> 0 | BD28: =Budgets!AC90 -> 0 | BE28: =BF28-BF28 -> 0 | BF28: =Budgets!AD90 -> 0 | BG28: =BH28-BH28 -> 0 | BH28: =Budgets!AE90 -> 0 | BI28: =BJ28-BJ28 -> 0 | BJ28: =Budgets!AF90 -> 0 | BK28: =BL28-BL28 -> 0 | BL28: =Budgets!AG90 -> 0 | BM28: =BN28-BN28 -> 0 | BN28: =Budgets!AH90 -> 0 | BO28: =BP28-BP28 -> 0 | BP28: =Budgets!AI90 -> 0 | BQ28: =BR28-BR28 -> 0 | BR28: =Budgets!AJ90 -> 0 | BS28: =BT28-BT28 -> 0 | BT28: =Budgets!AK90 -> 0 | BU28: =BV28-BV28 -> 0 | BV28: =Budgets!AL90 -> 0 | BW28: =BX28-BX28 -> 0 | BX28: =Budgets!AM90 -> 0 | BY28: =BZ28-BZ28 -> 0 | BZ28: =Budgets!AN90 -> 0 | CA28: =BZ28-CB28 -> 0 | CB28: =Budgets!AO90 -> 0 | CC28: =CB28-CD28 -> 0 | CD28: =Budgets!AP90 -> 0 | CE28: =CF28-CF28 -> 0 | CF28: =Budgets!AQ90 -> 0 | CG28: =CH28-CH28 -> 0 | CH28: =Budgets!AR90 -> 0 | CI28: =CJ28-CJ28 -> 0 | CJ28: =Budgets!AS90 -> 0 | CK28: =CL28-CL28 -> 0 | CL28: =Budgets!AT90 -> 0 | CM28: =CN28-CN28 -> 0 | CN28: =Budgets!AU90 -> 0 | CO28: =CP28-CP28 -> 0 | CP28: =Budgets!AV90 -> 0 | CQ28: =CR28-CR28 -> 0 | CR28: =Budgets!AW90 -> 0 | CS28: =CT28-CT28 -> 0 | CT28: =Budgets!AX90 -> 0 | CU28: =CV28-CV28 -> 0 | CV28: =Budgets!AY90 -> 0 | CW28: =CX28-CX28 -> 0 | CX28: =Budgets!AZ90 -> 0 | CY28: =CZ28-CZ28 -> 0 | CZ28: =Budgets!BA90 -> 0 | DA28: =DB28-DB28 -> 0 | DB28: =Budgets!BB90 -> 0 | DC28: =DD28-DD28 -> 0 | DD28: =Budgets!BC90 -> 0 | DE28: =DF28-DF28 -> 0 | DF28: =Budgets!BD90 -> 0 | DG28: =DH28-DH28 -> 0 | DH28: =Budgets!BE90 -> 0 | DI28: =DJ28-DJ28 -> 0 | DJ28: =Budgets!BF90 -> 0 | DK28: =DL28-DL28 -> 0 | DL28: =Budgets!BG90 -> 0 | DM28: =DN28-DN28 -> 0 | DN28: =Budgets!BH90 -> 0 | DO28: =DP28-DP28 -> 0 | DP28: =Budgets!BI90 -> 0 | DQ28: =DR28-DR28 -> 0 | DR28: =Budgets!BJ90 -> 0 | DS28: =DT28-DT28 -> 0 | DT28: =Budgets!BK90 -> 0 | DU28: =DV28-DV28 -> 0 | DV28: =Budgets!BL90 -> 0 | DW28: =DX28-DX28 -> 0 | DX28: =Budgets!BM90 -> 0 | DY28: =DZ28-DZ28 -> 0 | DZ28: =Budgets!BN90 -> 0 | EA28: =EB28-EB28 -> 0 | EB28: =Budgets!BO90 -> 0 | EC28: =ED28-ED28 -> 0 | ED28: =Budgets!BP90 -> 0 | EE28: =EF28-EF28 -> 0 | EF28: =Budgets!BQ90 -> 0 | EG28: =EH28-EH28 -> 0 | EH28: =Budgets!BR90 -> 0 | EI28: =EJ28-EJ28 -> 0 | EJ28: =Budgets!BS90 -> 0 | EK28: =EL28-EL28 -> 0 | EL28: =Budgets!BT90 -> 0 | EM28: =EN28-EN28 -> 0 | EN28: =Budgets!BU90 -> 0 | EO28: =EP28-EP28 -> 0 | EP28: =Budgets!BV90 -> 0 | EQ28: =ER28-ER28 -> 0 | ER28: =Budgets!BW90 -> 0 | ES28: =ET28-ET28 -> 0 | ET28: =Budgets!BX90 -> 0 | EU28: =EV28-EV28 -> 0 | EV28: =Budgets!BY90 -> 0 | EW28: =EX28-EX28 -> 0 | EX28: =Budgets!BZ90 -> 0
A29: BFWD retained earnings | B29: ='Balance Sheet'!G30 -> -7539788.5 | D29: =B29 -> -7539788.5 | E29: =F29-F29 -> 0 | F29: =Budgets!D91 -> -7539788.5 | G29: =H29-H29 -> 0 | H29: =Budgets!E91 -> -7539788.5 | I29: =J29-J29 -> 0 | J29: =Budgets!F91 -> -7539788.5 | K29: =L29-L29 -> 0 | L29: =Budgets!G91 -> -7539788.5 | M29: =N29-N29 -> 0 | N29: =Budgets!H91 -> -7539788.5 | O29: =P29-P29 -> 0 | P29: =Budgets!I91 -> -7539788.5 | Q29: =R29-R29 -> 0 | R29: =Budgets!J91 -> -7539788.5 | S29: =T29-T29 -> 0 | T29: =Budgets!K91 -> -7539788.5 | U29: =V29-V29 -> 0 | V29: =Budgets!L91 -> -7539788.5 | W29: =X29-X29 -> 0 | X29: =Budgets!M91 -> -7539788.5 | Y29: =Z29-Z29 -> 0 | Z29: =Budgets!N91 -> -7539788.5 | AA29: =AB29-AB29 -> 0 | AB29: =Budgets!O91 -> -7539788.5 | AC29: =AD29-AD29 -> 0 | AD29: =Budgets!P91 -> -7539788.5 | AE29: =AF29-AF29 -> 0 | AF29: =Budgets!Q91 -> -7539788.5 | AG29: =AH29-AH29 -> 0 | AH29: =Budgets!R91 -> -7539788.5 | AI29: =AJ29-AJ29 -> 0 | AJ29: =Budgets!S91 -> -7539788.5 | AK29: =AL29-AL29 -> 0 | AL29: =Budgets!T91 -> -7539788.5 | AM29: =AN29-AN29 -> 0 | AN29: =Budgets!U91 -> -7539788.5 | AO29: =AP29-AP29 -> 0 | AP29: =Budgets!V91 -> -7539788.5 | AQ29: =AR29-AR29 -> 0 | AR29: =Budgets!W91 -> -7539788.5 | AS29: =AT29-AT29 -> 0 | AT29: =Budgets!X91 -> -7539788.5 | AU29: =AV29-AV29 -> 0 | AV29: =Budgets!Y91 -> -7539788.5 | AW29: =AX29-AX29 -> 0 | AX29: =Budgets!Z91 -> -7539788.5 | AY29: =AZ29-AZ29 -> 0 | AZ29: =Budgets!AA91 -> -7539788.5 | BA29: =AH29-AH29 -> 0 | BB29: =Budgets!AB91 -> -7539788.5 | BC29: =BD29-BD29 -> 0 | BD29: =Budgets!AC91 -> -7539788.5 | BE29: =BF29-BF29 -> 0 | BF29: =Budgets!AD91 -> -7539788.5 | BG29: =BH29-BH29 -> 0 | BH29: =Budgets!AE91 -> -7539788.5 | BI29: =BJ29-BJ29 -> 0 | BJ29: =Budgets!AF91 -> -7539788.5 | BK29: =BL29-BL29 -> 0 | BL29: =Budgets!AG91 -> -7539788.5 | BM29: =BN29-BN29 -> 0 | BN29: =Budgets!AH91 -> -7539788.5 | BO29: =BP29-BP29 -> 0 | BP29: =Budgets!AI91 -> -7539788.5 | BQ29: =BR29-BR29 -> 0 | BR29: =Budgets!AJ91 -> -7539788.5 | BS29: =BT29-BT29 -> 0 | BT29: =Budgets!AK91 -> -7539788.5 | BU29: =BV29-BV29 -> 0 | BV29: =Budgets!AL91 -> -7539788.5 | BW29: =BX29-BX29 -> 0 | BX29: =Budgets!AM91 -> -7539788.5 | BY29: =BZ29-BZ29 -> 0 | BZ29: =Budgets!AN91 -> -7539788.5 | CA29: =BZ29-CB29 -> 0 | CB29: =Budgets!AO91 -> -7539788.5 | CC29: =CB29-CD29 -> 0 | CD29: =Budgets!AP91 -> -7539788.5 | CE29: =CF29-CF29 -> 0 | CF29: =Budgets!AQ91 -> -7539788.5 | CG29: =CH29-CH29 -> 0 | CH29: =Budgets!AR91 -> -7539788.5 | CI29: =CJ29-CJ29 -> 0 | CJ29: =Budgets!AS91 -> -7539788.5 | CK29: =CL29-CL29 -> 0 | CL29: =Budgets!AT91 -> -7539788.5 | CM29: =CN29-CN29 -> 0 | CN29: =Budgets!AU91 -> -7539788.5 | CO29: =CP29-CP29 -> 0 | CP29: =Budgets!AV91 -> -7539788.5 | CQ29: =CR29-CR29 -> 0 | CR29: =Budgets!AW91 -> -7539788.5 | CS29: =CT29-CT29 -> 0 | CT29: =Budgets!AX91 -> -7539788.5 | CU29: =CV29-CV29 -> 0 | CV29: =Budgets!AY91 -> -7539788.5 | CW29: =CX29-CX29 -> 0 | CX29: =Budgets!AZ91 -> -7539788.5 | CY29: =CZ29-CZ29 -> 0 | CZ29: =Budgets!BA91 -> -7539788.5 | DA29: =DB29-DB29 -> 0 | DB29: =Budgets!BB91 -> -7539788.5 | DC29: =DD29-DD29 -> 0 | DD29: =Budgets!BC91 -> -7539788.5 | DE29: =DF29-DF29 -> 0 | DF29: =Budgets!BD91 -> -7539788.5 | DG29: =DH29-DH29 -> 0 | DH29: =Budgets!BE91 -> -7539788.5 | DI29: =DJ29-DJ29 -> 0 | DJ29: =Budgets!BF91 -> -7539788.5 | DK29: =DL29-DL29 -> 0 | DL29: =Budgets!BG91 -> -7539788.5 | DM29: =DN29-DN29 -> 0 | DN29: =Budgets!BH91 -> -7539788.5 | DO29: =DP29-DP29 -> 0 | DP29: =Budgets!BI91 -> -7539788.5 | DQ29: =DR29-DR29 -> 0 | DR29: =Budgets!BJ91 -> -7539788.5 | DS29: =DT29-DT29 -> 0 | DT29: =Budgets!BK91 -> -7539788.5 | DU29: =DV29-DV29 -> 0 | DV29: =Budgets!BL91 -> -7539788.5 | DW29: =DX29-DX29 -> 0 | DX29: =Budgets!BM91 -> -7539788.5 | DY29: =DZ29-DZ29 -> 0 | DZ29: =Budgets!BN91 -> -7539788.5 | EA29: =EB29-EB29 -> 0 | EB29: =Budgets!BO91 -> -7539788.5 | EC29: =ED29-ED29 -> 0 | ED29: =Budgets!BP91 -> -7539788.5 | EE29: =EF29-EF29 -> 0 | EF29: =Budgets!BQ91 -> -7539788.5 | EG29: =EH29-EH29 -> 0 | EH29: =Budgets!BR91 -> -7539788.5 | EI29: =EJ29-EJ29 -> 0 | EJ29: =Budgets!BS91 -> -7539788.5 | EK29: =EL29-EL29 -> 0 | EL29: =Budgets!BT91 -> -7539788.5 | EM29: =EN29-EN29 -> 0 | EN29: =Budgets!BU91 -> -7539788.5 | EO29: =EP29-EP29 -> 0 | EP29: =Budgets!BV91 -> -7539788.5 | EQ29: =ER29-ER29 -> 0 | ER29: =Budgets!BW91 -> -7539788.5 | ES29: =ET29-ET29 -> 0 | ET29: =Budgets!BX91 -> -7539788.5 | EU29: =EV29-EV29 -> 0 | EV29: =Budgets!BY91 -> -7539788.5 | EW29: =EX29-EX29 -> 0 | EX29: =Budgets!BZ91 -> -7539788.5
A30: 2022 retained earnings | B30: ='Balance Sheet'!G31 -> 0 | D30: =B30 -> 0 | F30: =Budgets!D92 -> -3201306.6 | H30: =Budgets!E92 -> -3558585.7 | J30: =Budgets!F92 -> -3994378.1 | L30: =J30+L67 -> -4350869.2 | N30: =Budgets!H92 -> -4741143 | P30: =Budgets!I92 -> -4671267.5 | R30: =Budgets!J92 -> -5052444.2 | T30: =Budgets!K92 -> -5291927 | V30: =Budgets!L92 -> -5542715.5 | X30: =Budgets!M92 -> -5665472.1 | Z30: =Budgets!N92 -> -5769478.6 | AB30: =Budgets!O92 -> -5950816.1 | AD30: =AB30+AD67 -> -6072112.9 | AF30: =AD30+AF67 -> -6211679.7 | AH30: =AF30+AH67 -> -6331046.5 | AJ30: =AH30+AJ67 -> -6637672.7 | AL30: =AJ30+AL67 -> -6894998.4 | AN30: =AL30+AN67 -> -7221499.6 | AP30: =AN30+AP67 -> -7416961.1 | AR30: =AP30+AR67 -> -7710468.2 | AT30: =AR30+AT67 -> -8044066.7 | AV30: =AT30+AV67 -> -8303372.1 | AX30: =AV30+AX67 -> -8446004.2 | AZ30: =AX30+AZ67 -> -8662126.3 | BB30: =Budgets!AB92 -> -8521008 | BD30: =Budgets!AC92 -> -8665854.7 | BF30: =Budgets!AD92 -> -8688028.1 | BH30: =Budgets!AE92 -> -8828274.1 | BJ30: =BH30+BJ67 -> -8904585.2 | BL30: =BJ30+BL67 -> -8878121 | BN30: =BL30+BN67 -> -8551570.5 | BP30: =BN30+BP67 -> -8406470.1 | BR30: =BP30+BR67 -> -8358229.5 | BT30: =BR30+BT67 -> -8294620.5 | BV30: =BT30+BV67 -> -8141199 | BX30: =BV30+BX67 -> -8034027.5 | BZ30: =BX30+BZ67 -> -7721835.2 | CB30: =BZ30+CB67 -> -7109830.3 | CD30: =CB30+CD67 -> -6711492.2 | CF30: =CD30+CF67 -> -6253472.7 | CH30: =CF30+CH67 -> -5530245 | CJ30: =CH30+CJ67 -> -4886888.9 | CL30: =CJ30+CL67 -> -3834016.5 | CN30: =CL30+CN67 -> -2900519.1 | CP30: =CN30+CP67 -> -1967542.6 | CR30: =CP30+CR67 -> -930250.15 | CT30: =CR30+CT67 -> 370042.26 | CV30: =CT30+CV67 -> 1588938.8 | CX30: =CV30+CX67 -> 3171460.4 | CZ30: =CX30+CZ67 -> 4964877.8 | DB30: =CZ30+DB67 -> 7048086.9 | DD30: =DB30+DD67 -> 9366269.3 | DF30: =DD30+DF67 -> 11692348 | DH30: =DF30+DH67 -> 14162613 | DJ30: =DH30+DJ67 -> 16905563 | DL30: =DJ30+DL67 -> 19836721 | DN30: =DL30+DN67 -> 22874441 | DP30: =DN30+DP67 -> 26158703 | DR30: =DP30+DR67 -> 29800986 | DT30: =DR30+DT67 -> 33620623 | DV30: =DT30+DV67 -> 37860801 | DX30: =DV30+DX67 -> 42435209 | DZ30: =DX30+DZ67 -> 47308846 | EB30: =DZ30+EB67 -> 52246046 | ED30: =EB30+ED67 -> 57422120 | EF30: =ED30+EF67 -> 63010861 | EH30: =EF30+EH67 -> 68748227 | EJ30: =EH30+EJ67 -> 74533802 | EL30: =EJ30+EL67 -> 80622793 | EN30: =EL30+EN67 -> 87198784 | EP30: =EN30+EP67 -> 93622005 | ER30: =EP30+ER67 -> 1.0037464e+08 | ET30: =ER30+ET67 -> 1.0753745e+08 | EV30: =ET30+EV67 -> 1.14351e+08 | EX30: =EV30+EX67 -> 1.2119649e+08
A31: Equity | B31: =SUM(B26:B30) -> 2134520.5 | D31: =SUM(D26:D30) -> 2134520.5 | F31: =SUM(F26:F30) -> 1575830.9 | H31: =SUM(H26:H30) -> 1218551.8 | J31: =SUM(J26:J30) -> 782759.37 | L31: =SUM(L26:L30) -> 426268.32 | N31: =SUM(N26:N30) -> 35994.458 | P31: =SUM(P26:P30) -> 105870 | R31: =SUM(R26:R30) -> -275306.75 | T31: =SUM(T26:T30) -> -514789.51 | V31: =SUM(V26:V30) -> -765578.05 | X31: =SUM(X26:X30) -> -888334.59 | Z31: =SUM(Z26:Z30) -> -992341.13 | AB31: =SUM(AB26:AB30) -> -1173678.7 | AD31: =SUM(AD26:AD30) -> -1294975.5 | AF31: =SUM(AF26:AF30) -> -1434542.2 | AH31: =SUM(AH26:AH30) -> -1553909 | AJ31: =SUM(AJ26:AJ30) -> -1860535.2 | AL31: =SUM(AL26:AL30) -> -2117860.9 | AN31: =SUM(AN26:AN30) -> -2444362.1 | AP31: =SUM(AP26:AP30) -> -2639823.6 | AR31: =SUM(AR26:AR30) -> -2933330.7 | AT31: =SUM(AT26:AT30) -> -3266929.2 | AV31: =SUM(AV26:AV30) -> -3526234.6 | AX31: =SUM(AX26:AX30) -> -3668866.7 | AZ31: =SUM(AZ26:AZ30) -> -3884988.8 | BB31: =SUM(BB26:BB30) -> -3743870.5 | BD31: =SUM(BD26:BD30) -> -3888717.2 | BF31: =SUM(BF26:BF30) -> -3910890.6 | BH31: =SUM(BH26:BH30) -> -4051136.6 | BJ31: =SUM(BJ26:BJ30) -> -4127447.7 | BL31: =SUM(BL26:BL30) -> -4100983.5 | BN31: =SUM(BN26:BN30) -> -3774433 | BP31: =SUM(BP26:BP30) -> -3629332.7 | BR31: =SUM(BR26:BR30) -> -3581092.1 | BT31: =SUM(BT26:BT30) -> -3517483 | BV31: =SUM(BV26:BV30) -> -3364061.5 | BX31: =SUM(BX26:BX30) -> -3256890 | BZ31: =SUM(BZ26:BZ30) -> -2944697.7 | CB31: =SUM(CB26:CB30) -> -2332692.8 | CD31: =SUM(CD26:CD30) -> -1934354.7 | CF31: =SUM(CF26:CF30) -> -1476335.3 | CH31: =SUM(CH26:CH30) -> -753107.5 | CJ31: =SUM(CJ26:CJ30) -> -109751.38 | CL31: =SUM(CL26:CL30) -> 943121 | CN31: =SUM(CN26:CN30) -> 1876618.4 | CP31: =SUM(CP26:CP30) -> 2809594.9 | CR31: =SUM(CR26:CR30) -> 3846887.3 | CT31: =SUM(CT26:CT30) -> 5147179.7 | CV31: =SUM(CV26:CV30) -> 6366076.3 | CX31: =SUM(CX26:CX30) -> 7948597.9 | CZ31: =SUM(CZ26:CZ30) -> 9742015.3 | DB31: =SUM(DB26:DB30) -> 11825224 | DD31: =SUM(DD26:DD30) -> 14143407 | DF31: =SUM(DF26:DF30) -> 16469485 | DH31: =SUM(DH26:DH30) -> 18939751 | DJ31: =SUM(DJ26:DJ30) -> 21682700 | DL31: =SUM(DL26:DL30) -> 24613858 | DN31: =SUM(DN26:DN30) -> 27651578 | DP31: =SUM(DP26:DP30) -> 30935840 | DR31: =SUM(DR26:DR30) -> 34578123 | DT31: =SUM(DT26:DT30) -> 38397760 | DV31: =SUM(DV26:DV30) -> 42637939 | DX31: =SUM(DX26:DX30) -> 47212347 | DZ31: =SUM(DZ26:DZ30) -> 52085984 | EB31: =SUM(EB26:EB30) -> 57023183 | ED31: =SUM(ED26:ED30) -> 62199258 | EF31: =SUM(EF26:EF30) -> 67787999 | EH31: =SUM(EH26:EH30) -> 73525365 | EJ31: =SUM(EJ26:EJ30) -> 79310939 | EL31: =SUM(EL26:EL30) -> 85399931 | EN31: =SUM(EN26:EN30) -> 91975922 | EP31: =SUM(EP26:EP30) -> 98399142 | ER31: =SUM(ER26:ER30) -> 1.0515178e+08 | ET31: =SUM(ET26:ET30) -> 1.1231458e+08 | EV31: =SUM(EV26:EV30) -> 1.1912814e+08 | EX31: =SUM(EX26:EX30) -> 1.2597363e+08
A35: Revenue
A36: Ui/Europe | D36: =C36 -> 0 | E36: =Budgets!D6 -> 598158 | F36: =E36 -> 598158 | G36: =Budgets!E6 -> 75913.92 | H36: =G36 -> 75913.92 | I36: =Budgets!F6 -> 32708 | J36: =I36 -> 32708 | K36: =Budgets!G6 -> 8000 | L36: =I36 -> 32708 | M36: =Budgets!H19 -> 8000 | N36: =M36 -> 8000 | O36: =Budgets!I19 -> 34900 | P36: =O36 -> 34900 | Q36: =Budgets!J19 -> 35500 | R36: =Q36 -> 35500 | S36: =Budgets!K19 -> 74900 | T36: =S36 -> 74900 | U36: =Budgets!L19 -> 70000 | V36: =U36 -> 70000 | W36: =Budgets!M19 -> 155400 | X36: =W36 -> 155400 | Y36: =Budgets!N19 -> 177330 | Z36: =Y36 -> 177330 | AA36: =Budgets!O19 -> 133750 | AB36: =AA36 -> 133750 | AC36: =Budgets!P19 -> 219000 | AD36: =AC36 -> 219000 | AE36: =Budgets!Q19 -> 190000 | AF36: =AE36 -> 190000 | AG36: =Budgets!R19 -> 216000 | AH36: =AG36 -> 216000 | AI36: =Budgets!S19 -> 111530.79 | AJ36: =AI36 -> 111530.79 | AK36: =Budgets!T19 -> 117941.29 | AL36: =AK36 -> 117941.29 | AM36: =Budgets!U19 -> 84038.288 | AN36: =AM36 -> 84038.288 | AO36: =Budgets!V19 -> 357254.83 | AP36: =AO36 -> 357254.83 | AQ36: =Budgets!W19 -> 267358.33 | AR36: =AQ36 -> 267358.33 | AS36: =Budgets!X19 -> 282067.83 | AT36: =AS36 -> 282067.83 | AU36: =Budgets!Y19 -> 332270.83 | AV36: =AU36 -> 332270.83 | AW36: =Budgets!Z19 -> 464854.17 | AX36: =AW36 -> 464854.17 | AY36: =Budgets!AA19 -> 441729.17 | AZ36: =AY36 -> 441729.17 | BA36: =Budgets!AB19 -> 463541.67 | BB36: =BA36 -> 463541.67 | BC36: =Budgets!AC19 -> 490854.17 | BD36: =BC36 -> 490854.17 | BE36: =Budgets!AD19 -> 648437.5 | BF36: =BE36 -> 648437.5 | BG36: =Budgets!AE19 -> 604437.5 | BH36: =BG36 -> 604437.5 | BI36: =Budgets!AF19 -> 654250 | BJ36: =BI36 -> 654250 | BK36: =Budgets!AG19 -> 877208.33 | BL36: =BK36 -> 877208.33 | BM36: =Budgets!AH19 -> 774250 | BN36: =BM36 -> 774250 | BO36: =Budgets!AI19 -> 949708.33 | BP36: =BO36 -> 949708.33 | BQ36: =Budgets!AJ19 -> 898583.33 | BR36: =BQ36 -> 898583.33 | BS36: =Budgets!AK19 -> 942458.33 | BT36: =BS36 -> 942458.33 | BU36: =Budgets!AL19 -> 1014770.8 | BV36: =BU36 -> 1014770.8 | BW36: =Budgets!AM19 -> 1031020.8 | BX36: =BW36 -> 1031020.8 | BY36: =Budgets!AN19 -> 1198541.7 | BZ36: =BY36 -> 1198541.7 | CA36: =Budgets!AO19 -> 1511687.5 | CB36: =CA36 -> 1511687.5 | CC36: =Budgets!AP19 -> 1310104.2 | CD36: =CC36 -> 1310104.2 | CE36: =Budgets!AQ19 -> 1389729.2 | CF36: =CE36 -> 1389729.2 | CG36: =Budgets!AR19 -> 1662020.8 | CH36: =CG36 -> 1662020.8 | CI36: =Budgets!AS19 -> 1633875 | CJ36: =CI36 -> 1633875 | CK36: =Budgets!AT19 -> 2048375 | CL36: =CK36 -> 2048375 | CM36: =Budgets!AU19 -> 1931166.7 | CN36: =CM36 -> 1931166.7 | CO36: =Budgets!AV19 -> 1940312.5 | CP36: =CO36 -> 1940312.5 | CQ36: =Budgets!AW19 -> 2063937.5 | CR36: =CQ36 -> 2063937.5 | CS36: =Budgets!AX19 -> 2330770.8 | CT36: =CS36 -> 2330770.8 | CU36: =Budgets!AY19 -> 2258958.3 | CV36: =CU36 -> 2258958.3 | CW36: =Budgets!AZ19 -> 2612166.7 | CX36: =CW36 -> 2612166.7 | CY36: =Budgets!BA19 -> 2823062.5 | CZ36: =CY36 -> 2823062.5 | DA36: =Budgets!BB19 -> 3122854.2 | DB36: =DA36 -> 3122854.2 | DC36: =Budgets!BC19 -> 3353770.8 | DD36: =DC36 -> 3353770.8 | DE36: =Budgets!BD19 -> 3361250 | DF36: =DE36 -> 3361250 | DG36: =Budgets!BE19 -> 3515020.8 | DH36: =DG36 -> 3515020.8 | DI36: =Budgets!BF19 -> 3791291.7 | DJ36: =DI36 -> 3791291.7 | DK36: =Budgets!BG19 -> 3980333.3 | DL36: =DK36 -> 3980333.3 | DM36: =Budgets!BH19 -> 4096895.8 | DN36: =DM36 -> 4096895.8 | DO36: =Budgets!BI19 -> 4333437.5 | DP36: =DO36 -> 4333437.5 | DQ36: =Budgets!BJ19 -> 4696458.3 | DR36: =DQ36 -> 4696458.3 | DS36: =Budgets!BK19 -> 4883812.5 | DT36: =DS36 -> 4883812.5 | DU36: =Budgets!BL19 -> 5290187.5 | DV36: =DU36 -> 5290187.5 | DW36: =Budgets!BM19 -> 5621916.7 | DX36: =DW36 -> 5621916.7 | DY36: =Budgets!BN19 -> 5931145.8 | DZ36: =DY36 -> 5931145.8 | EA36: =Budgets!BO19 -> 5995208.3 | EB36: =EA36 -> 5995208.3 | EC36: =Budgets!BP19 -> 6234083.3 | ED36: =EC36 -> 6234083.3 | EE36: =Budgets!BQ19 -> 6646750 | EF36: =EE36 -> 6646750 | EG36: =Budgets!BR19 -> 6795375 | EH36: =EG36 -> 6795375 | EI36: =Budgets!BS19 -> 6843583.3 | EJ36: =EI36 -> 6843583.3 | EK36: =Budgets!BT19 -> 7147000 | EL36: =EK36 -> 7147000 | EM36: =Budgets!BU19 -> 7634000 | EN36: =EM36 -> 7634000 | EO36: =Budgets!BV19 -> 7481229.2 | EP36: =EO36 -> 7481229.2 | EQ36: =Budgets!BW19 -> 7810645.8 | ER36: =EQ36 -> 7810645.8 | ES36: =Budgets!BX19 -> 8220812.5 | ET36: =ES36 -> 8220812.5 | EU36: =Budgets!BY19 -> 7871562.5 | EV36: =EU36 -> 7871562.5 | EW36: =Budgets!BZ19 -> 7903500 | EX36: =EW36 -> 7903500
A37: USA
A38: RoW
A39: Total Revenue | D39: =SUM(D36:D38) -> 0 | F39: =SUM(F36:F38) -> 598158 | H39: =SUM(H36:H38) -> 75913.92 | J39: =SUM(J36:J38) -> 32708 | L39: =SUM(L36:L38) -> 32708 | N39: =SUM(N36:N38) -> 8000 | P39: =SUM(P36:P38) -> 34900 | R39: =SUM(R36:R38) -> 35500 | T39: =SUM(T36:T38) -> 74900 | V39: =SUM(V36:V38) -> 70000 | X39: =SUM(X36:X38) -> 155400 | Z39: =SUM(Z36:Z38) -> 177330 | AB39: =SUM(AB36:AB38) -> 133750 | AD39: =SUM(AD36:AD38) -> 219000 | AF39: =SUM(AF36:AF38) -> 190000 | AH39: =SUM(AH36:AH38) -> 216000 | AJ39: =SUM(AJ36:AJ38) -> 111530.79 | AL39: =SUM(AL36:AL38) -> 117941.29 | AN39: =SUM(AN36:AN38) -> 84038.288 | AP39: =SUM(AP36:AP38) -> 357254.83 | AR39: =SUM(AR36:AR38) -> 267358.33 | AT39: =SUM(AT36:AT38) -> 282067.83 | AV39: =SUM(AV36:AV38) -> 332270.83 | AX39: =SUM(AX36:AX38) -> 464854.17 | AZ39: =SUM(AZ36:AZ38) -> 441729.17 | BB39: =SUM(AH36:AH38) -> 216000 | BD39: =SUM(BD36:BD38) -> 490854.17 | BF39: =SUM(BF36:BF38) -> 648437.5 | BH39: =SUM(BH36:BH38) -> 604437.5 | BJ39: =SUM(BJ36:BJ38) -> 654250 | BL39: =SUM(BL36:BL38) -> 877208.33 | BN39: =SUM(BN36:BN38) -> 774250 | BP39: =SUM(BP36:BP38) -> 949708.33 | BR39: =SUM(BR36:BR38) -> 898583.33 | BT39: =SUM(BT36:BT38) -> 942458.33 | BV39: =SUM(BV36:BV38) -> 1014770.8 | BX39: =SUM(BX36:BX38) -> 1031020.8 | BZ39: =SUM(BZ36:BZ38) -> 1198541.7 | CB39: =SUM(CB36:CB38) -> 1511687.5 | CD39: =SUM(CD36:CD38) -> 1310104.2 | CF39: =SUM(CF36:CF38) -> 1389729.2 | CH39: =SUM(CH36:CH38) -> 1662020.8 | CJ39: =SUM(CJ36:CJ38) -> 1633875 | CL39: =SUM(CL36:CL38) -> 2048375 | CN39: =SUM(CN36:CN38) -> 1931166.7 | CP39: =SUM(CP36:CP38) -> 1940312.5 | CR39: =SUM(CR36:CR38) -> 2063937.5 | CT39: =SUM(CT36:CT38) -> 2330770.8 | CV39: =SUM(CV36:CV38) -> 2258958.3 | CX39: =SUM(CX36:CX38) -> 2612166.7 | CZ39: =SUM(CZ36:CZ38) -> 2823062.5 | DB39: =SUM(DB36:DB38) -> 3122854.2 | DD39: =SUM(DD36:DD38) -> 3353770.8 | DF39: =SUM(DF36:DF38) -> 3361250 | DH39: =SUM(DH36:DH38) -> 3515020.8 | DJ39: =SUM(DJ36:DJ38) -> 3791291.7 | DL39: =SUM(DL36:DL38) -> 3980333.3 | DN39: =SUM(DN36:DN38) -> 4096895.8 | DP39: =SUM(DP36:DP38) -> 4333437.5 | DR39: =SUM(DR36:DR38) -> 4696458.3 | DT39: =SUM(DT36:DT38) -> 4883812.5 | DV39: =SUM(DV36:DV38) -> 5290187.5 | DX39: =SUM(DX36:DX38) -> 5621916.7 | DZ39: =SUM(DZ36:DZ38) -> 5931145.8 | EB39: =SUM(EB36:EB38) -> 5995208.3 | ED39: =SUM(ED36:ED38) -> 6234083.3 | EF39: =SUM(EF36:EF38) -> 6646750 | EH39: =SUM(EH36:EH38) -> 6795375 | EJ39: =SUM(EJ36:EJ38) -> 6843583.3 | EL39: =SUM(EL36:EL38) -> 7147000 | EN39: =SUM(EN36:EN38) -> 7634000 | EP39: =SUM(EP36:EP38) -> 7481229.2 | ER39: =SUM(ER36:ER38) -> 7810645.8 | ET39: =SUM(ET36:ET38) -> 8220812.5 | EV39: =SUM(EV36:EV38) -> 7871562.5 | EX39: =SUM(EX36:EX38) -> 7903500
A41: Cost of Sales
A42: Direct costs | D42: =C42 -> 0 | E42: =Budgets!D26 -> -79623.72 | F42: =E42 -> -79623.72 | G42: =Budgets!E26 -> -11505.12 | H42: =G42 -> -11505.12 | I42: =Budgets!F26 -> -9450.5004 | J42: =I42 -> -9450.5004 | K42: =Budgets!G26 -> -2373.905 | L42: =I42 -> -9450.5004 | M42: =Budgets!H26 -> -2873.905 | N42: =M42 -> -2873.905 | O42: =Budgets!I26 -> -8373.905 | P42: =O42 -> -8373.905 | Q42: =Budgets!J26 -> -3873.905 | R42: =Q42 -> -3873.905 | S42: =Budgets!K26 -> -8873.905 | T42: =S42 -> -8873.905 | U42: =Budgets!L26 -> -3873.905 | V42: =U42 -> -3873.905 | W42: =Budgets!M26 -> -3873.905 | X42: =W42 -> -3873.905 | Y42: =Budgets!N26 -> -3873.905 | Z42: =Y42 -> -3873.905 | AA42: =Budgets!O26 -> -3873.905 | AB42: =AA42 -> -3873.905 | AC42: =Budgets!P26 -> -3873.905 | AD42: =AC42 -> -3873.905 | AE42: =Budgets!Q26 -> -3873.905 | AF42: =AE42 -> -3873.905 | AG42: =Budgets!R26 -> -3873.905 | AH42: =AG42 -> -3873.905 | AI42: =Budgets!S26 -> -11373.905 | AJ42: =AI42 -> -11373.905 | AK42: =Budgets!T26 -> -13873.905 | AL42: =AK42 -> -13873.905 | AM42: =Budgets!U26 -> -16373.905 | AN42: =AM42 -> -16373.905 | AO42: =Budgets!V26 -> -43457.238 | AP42: =AO42 -> -43457.238 | AQ42: =Budgets!W26 -> -43873.905 | AR42: =AQ42 -> -43873.905 | AS42: =Budgets!X26 -> -44707.238 | AT42: =AS42 -> -44707.238 | AU42: =Budgets!Y26 -> -47207.238 | AV42: =AU42 -> -47207.238 | AW42: =Budgets!Z26 -> -47207.238 | AX42: =AW42 -> -47207.238 | AY42: =Budgets!AA26 -> -49707.238 | AZ42: =AY42 -> -49707.238 | BA42: =Budgets!AB26 -> -52207.238 | BB42: =BA42 -> -52207.238 | BC42: =Budgets!AC26 -> -52207.238 | BD42: =BC42 -> -52207.238 | BE42: =Budgets!AD26 -> -52207.238 | BF42: =BE42 -> -52207.238 | BG42: =Budgets!AE26 -> -54833.333 | BH42: =BG42 -> -54833.333 | BI42: =Budgets!AF26 -> -56833.333 | BJ42: =BI42 -> -56833.333 | BK42: =Budgets!AG26 -> -58833.333 | BL42: =BK42 -> -58833.333 | BM42: =Budgets!AH26 -> -63333.333 | BN42: =BM42 -> -63333.333 | BO42: =Budgets!AI26 -> -65833.333 | BP42: =BO42 -> -65833.333 | BQ42: =Budgets!AJ26 -> -68333.333 | BR42: =BQ42 -> -68333.333 | BS42: =Budgets!AK26 -> -70833.333 | BT42: =BS42 -> -70833.333 | BU42: =Budgets!AL26 -> -73333.333 | BV42: =BU42 -> -73333.333 | BW42: =Budgets!AM26 -> -75833.333 | BX42: =BW42 -> -75833.333 | BY42: =Budgets!AN26 -> -98333.333 | BZ42: =BY42 -> -98333.333 | CA42: =Budgets!AO26 -> -111666.67 | CB42: =CA42 -> -111666.67 | CC42: =Budgets!AP26 -> -113750 | CD42: =CC42 -> -113750 | CE42: =Budgets!AQ26 -> -117916.67 | CF42: =CE42 -> -117916.67 | CG42: =Budgets!AR26 -> -135000 | CH42: =CG42 -> -135000 | CI42: =Budgets!AS26 -> -149583.33 | CJ42: =CI42 -> -149583.33 | CK42: =Budgets!AT26 -> -160833.33 | CL42: =CK42 -> -160833.33 | CM42: =Budgets!AU26 -> -163000 | CN42: =CM42 -> -163000 | CO42: =Budgets!AV26 -> -162666.67 | CP42: =CO42 -> -162666.67 | CQ42: =Budgets!AW26 -> -164833.33 | CR42: =CQ42 -> -164833.33 | CS42: =Budgets!AX26 -> -178666.67 | CT42: =CS42 -> -178666.67 | CU42: =Budgets!AY26 -> -178250 | CV42: =CU42 -> -178250 | CW42: =Budgets!AZ26 -> -177833.33 | CX42: =CW42 -> -177833.33 | CY42: =Budgets!BA26 -> -177833.33 | CZ42: =CY42 -> -177833.33 | DA42: =Budgets!BB26 -> -177833.33 | DB42: =DA42 -> -177833.33 | DC42: =Budgets!BC26 -> -177000 | DD42: =DC42 -> -177000 | DE42: =Budgets!BD26 -> -176583.33 | DF42: =DE42 -> -176583.33 | DG42: =Budgets!BE26 -> -176166.67 | DH42: =DG42 -> -176166.67 | DI42: =Budgets!BF26 -> -175333.33 | DJ42: =DI42 -> -175333.33 | DK42: =Budgets!BG26 -> -176166.67 | DL42: =DK42 -> -176166.67 | DM42: =Budgets!BH26 -> -176166.67 | DN42: =DM42 -> -176166.67 | DO42: =Budgets!BI26 -> -176166.67 | DP42: =DO42 -> -176166.67 | DQ42: =Budgets!BJ26 -> -181166.67 | DR42: =DQ42 -> -181166.67 | DS42: =Budgets!BK26 -> -181166.67 | DT42: =DS42 -> -181166.67 | DU42: =Budgets!BL26 -> -177000 | DV42: =DU42 -> -177000 | DW42: =Budgets!BM26 -> -174500 | DX42: =DW42 -> -174500 | DY42: =Budgets!BN26 -> -174500 | DZ42: =DY42 -> -174500 | EA42: =Budgets!BO26 -> -174500 | EB42: =EA42 -> -174500 | EC42: =Budgets!BP26 -> -174500 | ED42: =EC42 -> -174500 | EE42: =Budgets!BQ26 -> -174500 | EF42: =EE42 -> -174500 | EG42: =Budgets!BR26 -> -174500 | EH42: =EG42 -> -174500 | EI42: =Budgets!BS26 -> -174500 | EJ42: =EI42 -> -174500 | EK42: =Budgets!BT26 -> -174500 | EL42: =EK42 -> -174500 | EM42: =Budgets!BU26 -> -174500 | EN42: =EM42 -> -174500 | EO42: =Budgets!BV26 -> -174500 | EP42: =EO42 -> -174500 | EQ42: =Budgets!BW26 -> -174500 | ER42: =EQ42 -> -174500 | ES42: =Budgets!BX26 -> -174500 | ET42: =ES42 -> -174500 | EU42: =Budgets!BY26 -> -174500 | EV42: =EU42 -> -174500 | EW42: =Budgets!BZ26 -> -174500 | EX42: =EW42 -> -174500
A43: Total Cost of Sales | D43: =SUM(D42) -> 0 | F43: =SUM(F42) -> -79623.72 | H43: =SUM(H42) -> -11505.12 | J43: =SUM(J42) -> -9450.5004 | L43: =SUM(L42) -> -9450.5004 | N43: =SUM(N42) -> -2873.905 | P43: =SUM(P42) -> -8373.905 | R43: =SUM(R42) -> -3873.905 | T43: =SUM(T42) -> -8873.905 | V43: =SUM(V42) -> -3873.905 | X43: =SUM(X42) -> -3873.905 | Z43: =SUM(Z42) -> -3873.905 | AB43: =SUM(AB42) -> -3873.905 | AD43: =SUM(AD42) -> -3873.905 | AF43: =SUM(AF42) -> -3873.905 | AH43: =SUM(AH42) -> -3873.905 | AJ43: =SUM(AJ42) -> -11373.905 | AL43: =SUM(AL42) -> -13873.905 | AN43: =SUM(AN42) -> -16373.905 | AP43: =SUM(AP42) -> -43457.238 | AR43: =SUM(AR42) -> -43873.905 | AT43: =SUM(AT42) -> -44707.238 | AV43: =SUM(AV42) -> -47207.238 | AX43: =SUM(AX42) -> -47207.238 | AZ43: =SUM(AZ42) -> -49707.238 | BB43: =SUM(AH42) -> -3873.905 | BD43: =SUM(BD42) -> -52207.238 | BF43: =SUM(BF42) -> -52207.238 | BH43: =SUM(BH42) -> -54833.333 | BJ43: =SUM(BJ42) -> -56833.333 | BL43: =SUM(BL42) -> -58833.333 | BN43: =SUM(BN42) -> -63333.333 | BP43: =SUM(BP42) -> -65833.333 | BR43: =SUM(BR42) -> -68333.333 | BT43: =SUM(BT42) -> -70833.333 | BV43: =SUM(BV42) -> -73333.333 | BX43: =SUM(BX42) -> -75833.333 | BZ43: =SUM(BZ42) -> -98333.333 | CB43: =SUM(CB42) -> -111666.67 | CD43: =SUM(CD42) -> -113750 | CF43: =SUM(CF42) -> -117916.67 | CH43: =SUM(CH42) -> -135000 | CJ43: =SUM(CJ42) -> -149583.33 | CL43: =SUM(CL42) -> -160833.33 | CN43: =SUM(CN42) -> -163000 | CP43: =SUM(CP42) -> -162666.67 | CR43: =SUM(CR42) -> -164833.33 | CT43: =SUM(CT42) -> -178666.67 | CV43: =SUM(CV42) -> -178250 | CX43: =SUM(CX42) -> -177833.33 | CZ43: =SUM(CZ42) -> -177833.33 | DB43: =SUM(DB42) -> -177833.33 | DD43: =SUM(DD42) -> -177000 | DF43: =SUM(DF42) -> -176583.33 | DH43: =SUM(DH42) -> -176166.67 | DJ43: =SUM(DJ42) -> -175333.33 | DL43: =SUM(DL42) -> -176166.67 | DN43: =SUM(DN42) -> -176166.67 | DP43: =SUM(DP42) -> -176166.67 | DR43: =SUM(DR42) -> -181166.67 | DT43: =SUM(DT42) -> -181166.67 | DV43: =SUM(DV42) -> -177000 | DX43: =SUM(DX42) -> -174500 | DZ43: =SUM(DZ42) -> -174500 | EB43: =SUM(EB42) -> -174500 | ED43: =SUM(ED42) -> -174500 | EF43: =SUM(EF42) -> -174500 | EH43: =SUM(EH42) -> -174500 | EJ43: =SUM(EJ42) -> -174500 | EL43: =SUM(EL42) -> -174500 | EN43: =SUM(EN42) -> -174500 | EP43: =SUM(EP42) -> -174500 | ER43: =SUM(ER42) -> -174500 | ET43: =SUM(ET42) -> -174500 | EV43: =SUM(EV42) -> -174500 | EX43: =SUM(EX42) -> -174500
A45: GROSS PROFIT
A47: Operating Expenses
A48: Sales & Marieting | D48: =C48 -> 0 | E48: =Budgets!D32 -> -776274.95 | F48: =E48 -> -776274.95 | G48: =Budgets!E32 -> -67100.447 | H48: =G48 -> -67100.447 | I48: =Budgets!F32 -> -76601.778 | J48: =I48 -> -76601.778 | K48: =Budgets!G32 -> -61428.447 | L48: =K48 -> -61428.447 | M48: =Budgets!H32 -> -61428.447 | N48: =M48 -> -61428.447 | O48: =Budgets!I32 -> -64656.447 | P48: =O48 -> -64656.447 | Q48: =Budgets!J32 -> -102348.45 | R48: =Q48 -> -102348.45 | S48: =Budgets!K32 -> -50128.447 | T48: =S48 -> -50128.447 | U48: =Budgets!L32 -> -101068.45 | V48: =U48 -> -101068.45 | W48: =Budgets!M32 -> -68436.447 | X48: =W48 -> -68436.447 | Y48: =Budgets!N32 -> -71616.447 | Z48: =Y48 -> -71616.447 | AA48: =Budgets!O32 -> -74727.447 | AB48: =AA48 -> -74727.447 | AC48: =Budgets!P32 -> -87068.447 | AD48: =AC48 -> -87068.447 | AE48: =Budgets!Q32 -> -96338.447 | AF48: =AE48 -> -96338.447 | AG48: =Budgets!R32 -> -92138.447 | AH48: =AG48 -> -92138.447 | AI48: =Budgets!S32 -> -126163.95 | AJ48: =AI48 -> -126163.95 | AK48: =Budgets!T32 -> -110773.95 | AL48: =AK48 -> -110773.95 | AM48: =Budgets!U32 -> -122246.45 | AN48: =AM48 -> -122246.45 | AO48: =Budgets!V32 -> -200807.37 | AP48: =AO48 -> -200807.37 | AQ48: =Budgets!W32 -> -178539.87 | AR48: =AQ48 -> -178539.87 | AS48: =Budgets!X32 -> -216027.37 | AT48: =AS48 -> -216027.37 | AU48: =Budgets!Y32 -> -229437.37 | AV48: =AU48 -> -229437.37 | AW48: =Budgets!Z32 -> -245347.37 | AX48: =AW48 -> -245347.37 | AY48: =Budgets!AA32 -> -233212.37 | AZ48: =AY48 -> -233212.37 | BA48: =Budgets!AB32 -> -262684.45 | BB48: =BA48 -> -262684.45 | BC48: =Budgets!AC32 -> -265961.95 | BD48: =BC48 -> -265961.95 | BE48: =Budgets!AD32 -> -290871.95 | BF48: =BE48 -> -290871.95 | BG48: =Budgets!AE32 -> -294668.23 | BH48: =BG48 -> -294668.23 | BI48: =Budgets!AF32 -> -300645.73 | BJ48: =BI48 -> -300645.73 | BK48: =Budgets!AG32 -> -339400.73 | BL48: =BK48 -> -339400.73 | BM48: =Budgets!AH32 -> -322558.7 | BN48: =BM48 -> -322558.7 | BO48: =Budgets!AI32 -> -346967.2 | BP48: =BO48 -> -346967.2 | BQ48: =Budgets!AJ32 -> -345233.7 | BR48: =BQ48 -> -345233.7 | BS48: =Budgets!AK32 -> -358222.2 | BT48: =BS48 -> -358222.2 | BU48: =Budgets!AL32 -> -358222.2 | BV48: =BU48 -> -358222.2 | BW48: =Budgets!AM32 -> -358222.2 | BX48: =BW48 -> -358222.2 | BY48: =Budgets!AN32 -> -358222.2 | BZ48: =BY48 -> -358222.2 | CA48: =Budgets!AO32 -> -358222.2 | CB48: =CA48 -> -358222.2 | CC48: =Budgets!AP32 -> -358222.2 | CD48: =CC48 -> -358222.2 | CE48: =Budgets!AQ32 -> -360402.29 | CF48: =CE48 -> -360402.29 | CG48: =Budgets!AR32 -> -360402.29 | CH48: =CG48 -> -360402.29 | CI48: =Budgets!AS32 -> -363902.29 | CJ48: =CI48 -> -363902.29 | CK48: =Budgets!AT32 -> -367873.83 | CL48: =CK48 -> -367873.83 | CM48: =Budgets!AU32 -> -367873.83 | CN48: =CM48 -> -367873.83 | CO48: =Budgets!AV32 -> -367873.83 | CP48: =CO48 -> -367873.83 | CQ48: =Budgets!AW32 -> -371373.83 | CR48: =CQ48 -> -371373.83 | CS48: =Budgets!AX32 -> -371373.83 | CT48: =CS48 -> -371373.83 | CU48: =Budgets!AY32 -> -371373.83 | CV48: =CU48 -> -371373.83 | CW48: =Budgets!AZ32 -> -371373.83 | CX48: =CW48 -> -371373.83 | CY48: =Budgets!BA32 -> -371373.83 | CZ48: =CY48 -> -371373.83 | DA48: =Budgets!BB32 -> -371373.83 | DB48: =DA48 -> -371373.83 | DC48: =Budgets!BC32 -> -373662.93 | DD48: =DC48 -> -373662.93 | DE48: =Budgets!BD32 -> -373662.93 | DF48: =DE48 -> -373662.93 | DG48: =Budgets!BE32 -> -373662.93 | DH48: =DG48 -> -373662.93 | DI48: =Budgets!BF32 -> -377833.05 | DJ48: =DI48 -> -377833.05 | DK48: =Budgets!BG32 -> -377833.05 | DL48: =DK48 -> -377833.05 | DM48: =Budgets!BH32 -> -377833.05 | DN48: =DM48 -> -377833.05 | DO48: =Budgets!BI32 -> -377833.05 | DP48: =DO48 -> -377833.05 | DQ48: =Budgets!BJ32 -> -377833.05 | DR48: =DQ48 -> -377833.05 | DS48: =Budgets!BK32 -> -377833.05 | DT48: =DS48 -> -377833.05 | DU48: =Budgets!BL32 -> -377833.05 | DV48: =DU48 -> -377833.05 | DW48: =Budgets!BM32 -> -377833.05 | DX48: =DW48 -> -377833.05 | DY48: =Budgets!BN32 -> -377833.05 | DZ48: =DY48 -> -377833.05 | EA48: =Budgets!BO32 -> -377833.05 | EB48: =EA48 -> -377833.05 | EC48: =Budgets!BP32 -> -377833.05 | ED48: =EC48 -> -377833.05 | EE48: =Budgets!BQ32 -> -377833.05 | EF48: =EE48 -> -377833.05 | EG48: =Budgets!BR32 -> -377833.05 | EH48: =EG48 -> -377833.05 | EI48: =Budgets!BS32 -> -377833.05 | EJ48: =EI48 -> -377833.05 | EK48: =Budgets!BT32 -> -377833.05 | EL48: =EK48 -> -377833.05 | EM48: =Budgets!BU32 -> -377833.05 | EN48: =EM48 -> -377833.05 | EO48: =Budgets!BV32 -> -377833.05 | EP48: =EO48 -> -377833.05 | EQ48: =Budgets!BW32 -> -377833.05 | ER48: =EQ48 -> -377833.05 | ES48: =Budgets!BX32 -> -377833.05 | ET48: =ES48 -> -377833.05 | EU48: =Budgets!BY32 -> -377833.05 | EV48: =EU48 -> -377833.05 | EW48: =Budgets!BZ32 -> -377833.05 | EX48: =EW48 -> -377833.05
A49: Product development | D49: =C49 -> 0 | E49: =Budgets!D34 -> -1530642.8 | F49: =E49 -> -1530642.8 | G49: =Budgets!E34 -> -158085.68 | H49: =G49 -> -158085.68 | I49: =Budgets!F34 -> -158085.68 | J49: =I49 -> -158085.68 | K49: =Budgets!G34 -> -145438.56 | L49: =K49 -> -145438.56 | M49: =Budgets!H34 -> -145438.56 | N49: =M49 -> -145438.56 | O49: =Budgets!I34 -> -145438.56 | P49: =O49 -> -145438.56 | Q49: =Budgets!J34 -> -130264.61 | R49: =Q49 -> -130264.61 | S49: =Budgets!K34 -> -118115.12 | T49: =S49 -> -118115.12 | U49: =Budgets!L34 -> -94009.988 | V49: =U49 -> -94009.988 | W49: =Budgets!M34 -> -94009.988 | X49: =W49 -> -94009.988 | Y49: =Budgets!N34 -> -94009.988 | Z49: =Y49 -> -94009.988 | AA49: =Budgets!O34 -> -94009.988 | AB49: =AA49 -> -94009.988 | AC49: =Budgets!P34 -> -106278.24 | AD49: =AC49 -> -106278.24 | AE49: =Budgets!Q34 -> -106278.24 | AF49: =AE49 -> -106278.24 | AG49: =Budgets!R34 -> -106278.24 | AH49: =AG49 -> -106278.24 | AI49: =Budgets!S34 -> -106278.24 | AJ49: =AI49 -> -106278.24 | AK49: =Budgets!T34 -> -106278.24 | AL49: =AK49 -> -106278.24 | AM49: =Budgets!U34 -> -106278.24 | AN49: =AM49 -> -106278.24 | AO49: =Budgets!V34 -> -123246.99 | AP49: =AO49 -> -123246.99 | AQ49: =Budgets!W34 -> -173246.99 | AR49: =AQ49 -> -173246.99 | AS49: =Budgets!X34 -> -123246.99 | AT49: =AS49 -> -123246.99 | AU49: =Budgets!Y34 -> -123246.99 | AV49: =AU49 -> -123246.99 | AW49: =Budgets!Z34 -> -123246.99 | AX49: =AW49 -> -123246.99 | AY49: =Budgets!AA34 -> -173246.99 | AZ49: =AY49 -> -173246.99 | BA49: =Budgets!AB34 -> -123246.99 | BB49: =BA49 -> -123246.99 | BC49: =Budgets!AC34 -> -123246.99 | BD49: =BC49 -> -123246.99 | BE49: =Budgets!AD34 -> -123246.99 | BF49: =BE49 -> -123246.99 | BG49: =Budgets!AE34 -> -123246.99 | BH49: =BG49 -> -123246.99 | BI49: =Budgets!AF34 -> -123246.99 | BJ49: =BI49 -> -123246.99 | BK49: =Budgets!AG34 -> -173246.99 | BL49: =BK49 -> -173246.99 | BM49: =Budgets!AH34 -> -128182.51 | BN49: =BM49 -> -128182.51 | BO49: =Budgets!AI34 -> -128182.51 | BP49: =BO49 -> -128182.51 | BQ49: =Budgets!AJ34 -> -140450.76 | BR49: =BQ49 -> -140450.76 | BS49: =Budgets!AK34 -> -140450.76 | BT49: =BS49 -> -140450.76 | BU49: =Budgets!AL34 -> -140450.76 | BV49: =BU49 -> -140450.76 | BW49: =Budgets!AM34 -> -190450.76 | BX49: =BW49 -> -190450.76 | BY49: =Budgets!AN34 -> -140450.76 | BZ49: =BY49 -> -140450.76 | CA49: =Budgets!AO34 -> -140450.76 | CB49: =CA49 -> -140450.76 | CC49: =Budgets!AP34 -> -140450.76 | CD49: =CC49 -> -140450.76 | CE49: =Budgets!AQ34 -> -140450.76 | CF49: =CE49 -> -140450.76 | CG49: =Budgets!AR34 -> -140450.76 | CH49: =CG49 -> -140450.76 | CI49: =Budgets!AS34 -> -140450.76 | CJ49: =CI49 -> -140450.76 | CK49: =Budgets!AT34 -> -145633.06 | CL49: =CK49 -> -145633.06 | CM49: =Budgets!AU34 -> -145633.06 | CN49: =CM49 -> -145633.06 | CO49: =Budgets!AV34 -> -145633.06 | CP49: =CO49 -> -145633.06 | CQ49: =Budgets!AW34 -> -145633.06 | CR49: =CQ49 -> -145633.06 | CS49: =Budgets!AX34 -> -145633.06 | CT49: =CS49 -> -145633.06 | CU49: =Budgets!AY34 -> -145633.06 | CV49: =CU49 -> -145633.06 | CW49: =Budgets!AZ34 -> -145633.06 | CX49: =CW49 -> -145633.06 | CY49: =Budgets!BA34 -> -145633.06 | CZ49: =CY49 -> -145633.06 | DA49: =Budgets!BB34 -> -145633.06 | DB49: =DA49 -> -145633.06 | DC49: =Budgets!BC34 -> -145633.06 | DD49: =DC49 -> -145633.06 | DE49: =Budgets!BD34 -> -145633.06 | DF49: =DE49 -> -145633.06 | DG49: =Budgets!BE34 -> -145633.06 | DH49: =DG49 -> -145633.06 | DI49: =Budgets!BF34 -> -151074.47 | DJ49: =DI49 -> -151074.47 | DK49: =Budgets!BG34 -> -151074.47 | DL49: =DK49 -> -151074.47 | DM49: =Budgets!BH34 -> -151074.47 | DN49: =DM49 -> -151074.47 | DO49: =Budgets!BI34 -> -151074.47 | DP49: =DO49 -> -151074.47 | DQ49: =Budgets!BJ34 -> -151074.47 | DR49: =DQ49 -> -151074.47 | DS49: =Budgets!BK34 -> -151074.47 | DT49: =DS49 -> -151074.47 | DU49: =Budgets!BL34 -> -151074.47 | DV49: =DU49 -> -151074.47 | DW49: =Budgets!BM34 -> -151074.47 | DX49: =DW49 -> -151074.47 | DY49: =Budgets!BN34 -> -151074.47 | DZ49: =DY49 -> -151074.47 | EA49: =Budgets!BO34 -> -151074.47 | EB49: =EA49 -> -151074.47 | EC49: =Budgets!BP34 -> -151074.47 | ED49: =EC49 -> -151074.47 | EE49: =Budgets!BQ34 -> -151074.47 | EF49: =EE49 -> -151074.47 | EG49: =Budgets!BR34 -> -151074.47 | EH49: =EG49 -> -151074.47 | EI49: =Budgets!BS34 -> -151074.47 | EJ49: =EI49 -> -151074.47 | EK49: =Budgets!BT34 -> -151074.47 | EL49: =EK49 -> -151074.47 | EM49: =Budgets!BU34 -> -151074.47 | EN49: =EM49 -> -151074.47 | EO49: =Budgets!BV34 -> -151074.47 | EP49: =EO49 -> -151074.47 | EQ49: =Budgets!BW34 -> -151074.47 | ER49: =EQ49 -> -151074.47 | ES49: =Budgets!BX34 -> -151074.47 | ET49: =ES49 -> -151074.47 | EU49: =Budgets!BY34 -> -151074.47 | EV49: =EU49 -> -151074.47 | EW49: =Budgets!BZ34 -> -151074.47 | EX49: =EW49 -> -151074.47
A50: G&A | E50: =Budgets!D36 -> -1123747.5 | F50: =E50 -> -1123747.5 | G50: =Budgets!E36 -> -138087.51 | H50: =G50 -> -138087.51 | I50: =Budgets!F36 -> -152538.35 | J50: =I50 -> -152538.35 | K50: =Budgets!G36 -> -101057.43 | L50: =K50 -> -101057.43 | M50: =Budgets!H36 -> -99077.43 | N50: =M50 -> -99077.43 | O50: =Budgets!I36 -> -101651.43 | P50: =O50 -> -101651.43 | Q50: =Budgets!J36 -> -108365.67 | R50: =Q50 -> -108365.67 | S50: =Budgets!K36 -> -65441.171 | T50: =S50 -> -65441.171 | U50: =Budgets!L36 -> -53583.211 | V50: =U50 -> -53583.211 | W50: =Budgets!M36 -> -53583.211 | X50: =W50 -> -53583.211 | Y50: =Budgets!N36 -> -53583.211 | Z50: =Y50 -> -53583.211 | AA50: =Budgets!O36 -> -63883.211 | AB50: =AA50 -> -63883.211 | AC50: =Budgets!P36 -> -74483.211 | AD50: =AC50 -> -74483.211 | AE50: =Budgets!Q36 -> -54483.211 | AF50: =AE50 -> -54483.211 | AG50: =Budgets!R36 -> -54483.211 | AH50: =AG50 -> -54483.211 | AI50: =Budgets!S36 -> -95407.911 | AJ50: =AI50 -> -95407.911 | AK50: =Budgets!T36 -> -65407.911 | AL50: =AK50 -> -65407.911 | AM50: =Budgets!U36 -> -76707.911 | AN50: =AM50 -> -76707.911 | AO50: =Budgets!V36 -> -103359.07 | AP50: =AO50 -> -103359.07 | AQ50: =Budgets!W36 -> -83359.066 | AR50: =AQ50 -> -83359.066 | AS50: =Budgets!X36 -> -117259.07 | AT50: =AS50 -> -117259.07 | AU50: =Budgets!Y36 -> -87259.066 | AV50: =AU50 -> -87259.066 | AW50: =Budgets!Z36 -> -87259.066 | AX50: =AW50 -> -87259.066 | AY50: =Budgets!AA36 -> -87259.066 | AZ50: =AY50 -> -87259.066 | BA50: =Budgets!AB36 -> -109859.07 | BB50: =BA50 -> -109859.07 | BC50: =Budgets!AC36 -> -89859.066 | BD50: =BC50 -> -89859.066 | BE50: =Budgets!AD36 -> -89859.066 | BF50: =BE50 -> -89859.066 | BG50: =Budgets!AE36 -> -144929.43 | BH50: =BG50 -> -144929.43 | BI50: =Budgets!AF36 -> -122829.43 | BJ50: =BI50 -> -122829.43 | BK50: =Budgets!AG36 -> -142257.55 | BL50: =BK50 -> -142257.55 | BM50: =Budgets!AH36 -> -133561.06 | BN50: =BM50 -> -133561.06 | BO50: =Budgets!AI36 -> -133561.06 | BP50: =BO50 -> -133561.06 | BQ50: =Budgets!AJ36 -> -156261.06 | BR50: =BQ50 -> -156261.06 | BS50: =Budgets!AK36 -> -167039.18 | BT50: =BS50 -> -167039.18 | BU50: =Budgets!AL36 -> -147039.18 | BV50: =BU50 -> -147039.18 | BW50: =Budgets!AM36 -> -147039.18 | BX50: =BW50 -> -147039.18 | BY50: =Budgets!AN36 -> -147039.18 | BZ50: =BY50 -> -147039.18 | CA50: =Budgets!AO36 -> -147039.18 | CB50: =CA50 -> -147039.18 | CC50: =Budgets!AP36 -> -147039.18 | CD50: =CC50 -> -147039.18 | CE50: =Budgets!AQ36 -> -170636.18 | CF50: =CE50 -> -170636.18 | CG50: =Budgets!AR36 -> -160636.18 | CH50: =CG50 -> -160636.18 | CI50: =Budgets!AS36 -> -172038.68 | CJ50: =CI50 -> -172038.68 | CK50: =Budgets!AT36 -> -163407.38 | CL50: =CK50 -> -163407.38 | CM50: =Budgets!AU36 -> -163407.38 | CN50: =CM50 -> -163407.38 | CO50: =Budgets!AV36 -> -163407.38 | CP50: =CO50 -> -163407.38 | CQ50: =Budgets!AW36 -> -174809.88 | CR50: =CQ50 -> -174809.88 | CS50: =Budgets!AX36 -> -164809.88 | CT50: =CS50 -> -164809.88 | CU50: =Budgets!AY36 -> -164809.88 | CV50: =CU50 -> -164809.88 | CW50: =Budgets!AZ36 -> -164809.88 | CX50: =CW50 -> -164809.88 | CY50: =Budgets!BA36 -> -164809.88 | CZ50: =CY50 -> -164809.88 | DA50: =Budgets!BB36 -> -164809.88 | DB50: =DA50 -> -164809.88 | DC50: =Budgets!BC36 -> -169297.45 | DD50: =DC50 -> -169297.45 | DE50: =Budgets!BD36 -> -169297.45 | DF50: =DE50 -> -169297.45 | DG50: =Budgets!BE36 -> -169297.45 | DH50: =DG50 -> -169297.45 | DI50: =Budgets!BF36 -> -170734.58 | DJ50: =DI50 -> -170734.58 | DK50: =Budgets!BG36 -> -170734.58 | DL50: =DK50 -> -170734.58 | DM50: =Budgets!BH36 -> -170734.58 | DN50: =DM50 -> -170734.58 | DO50: =Budgets!BI36 -> -170734.58 | DP50: =DO50 -> -170734.58 | DQ50: =Budgets!BJ36 -> -170734.58 | DR50: =DQ50 -> -170734.58 | DS50: =Budgets!BK36 -> -170734.58 | DT50: =DS50 -> -170734.58 | DU50: =Budgets!BL36 -> -170734.58 | DV50: =DU50 -> -170734.58 | DW50: =Budgets!BM36 -> -170734.58 | DX50: =DW50 -> -170734.58 | DY50: =Budgets!BN36 -> -170734.58 | DZ50: =DY50 -> -170734.58 | EA50: =Budgets!BO36 -> -170734.58 | EB50: =EA50 -> -170734.58 | EC50: =Budgets!BP36 -> -170734.58 | ED50: =EC50 -> -170734.58 | EE50: =Budgets!BQ36 -> -170734.58 | EF50: =EE50 -> -170734.58 | EG50: =Budgets!BR36 -> -170734.58 | EH50: =EG50 -> -170734.58 | EI50: =Budgets!BS36 -> -170734.58 | EJ50: =EI50 -> -170734.58 | EK50: =Budgets!BT36 -> -170734.58 | EL50: =EK50 -> -170734.58 | EM50: =Budgets!BU36 -> -170734.58 | EN50: =EM50 -> -170734.58 | EO50: =Budgets!BV36 -> -170734.58 | EP50: =EO50 -> -170734.58 | EQ50: =Budgets!BW36 -> -170734.58 | ER50: =EQ50 -> -170734.58 | ES50: =Budgets!BX36 -> -170734.58 | ET50: =ES50 -> -170734.58 | EU50: =Budgets!BY36 -> -170734.58 | EV50: =EU50 -> -170734.58 | EW50: =Budgets!BZ36 -> -170734.58 | EX50: =EW50 -> -170734.58
A51: Product Support | E51: =Budgets!D38 -> -305518.66 | F51: =E51 -> -305518.66 | G51: =Budgets!E38 -> -71824.116 | H51: =G51 -> -71824.116 | I51: =Budgets!F38 -> -71824.116 | J51: =I51 -> -71824.116 | K51: =Budgets!G38 -> -71824.116 | L51: =K51 -> -71824.116 | M51: =Budgets!H38 -> -71824.116 | N51: =M51 -> -71824.116 | O51: =Budgets!I38 -> -81824.116 | P51: =O51 -> -81824.116 | Q51: =Budgets!J38 -> -71824.116 | R51: =Q51 -> -71824.116 | S51: =Budgets!K38 -> -71824.116 | T51: =S51 -> -71824.116 | U51: =Budgets!L38 -> -68252.991 | V51: =U51 -> -68252.991 | W51: =Budgets!M38 -> -58252.991 | X51: =W51 -> -58252.991 | Y51: =Budgets!N38 -> -58252.991 | Z51: =Y51 -> -58252.991 | AA51: =Budgets!O38 -> -78592.991 | AB51: =AA51 -> -78592.991 | AC51: =Budgets!P38 -> -68592.991 | AD51: =AC51 -> -68592.991 | AE51: =Budgets!Q38 -> -68592.991 | AF51: =AE51 -> -68592.991 | AG51: =Budgets!R38 -> -78592.991 | AH51: =AG51 -> -78592.991 | AI51: =Budgets!S38 -> -78932.991 | AJ51: =AI51 -> -78932.991 | AK51: =Budgets!T38 -> -78932.991 | AL51: =AK51 -> -78932.991 | AM51: =Budgets!U38 -> -88932.991 | AN51: =AM51 -> -88932.991 | AO51: =Budgets!V38 -> -81845.64 | AP51: =AO51 -> -81845.64 | AQ51: =Budgets!W38 -> -81845.64 | AR51: =AQ51 -> -81845.64 | AS51: =Budgets!X38 -> -114425.62 | AT51: =AS51 -> -114425.62 | AU51: =Budgets!Y38 -> -104425.62 | AV51: =AU51 -> -104425.62 | AW51: =Budgets!Z38 -> -104425.62 | AX51: =AW51 -> -104425.62 | AY51: =Budgets!AA38 -> -114425.62 | AZ51: =AY51 -> -114425.62 | BA51: =Budgets!AB38 -> -104425.62 | BB51: =BA51 -> -104425.62 | BC51: =Budgets!AC38 -> -104425.62 | BD51: =BC51 -> -104425.62 | BE51: =Budgets!AD38 -> -114425.62 | BF51: =BE51 -> -114425.62 | BG51: =Budgets!AE38 -> -127005.59 | BH51: =BG51 -> -127005.59 | BI51: =Budgets!AF38 -> -127005.59 | BJ51: =BI51 -> -127005.59 | BK51: =Budgets!AG38 -> -137005.59 | BL51: =BK51 -> -137005.59 | BM51: =Budgets!AH38 -> -130063.87 | BN51: =BM51 -> -130063.87 | BO51: =Budgets!AI38 -> -130063.87 | BP51: =BO51 -> -130063.87 | BQ51: =Budgets!AJ38 -> -140063.87 | BR51: =BQ51 -> -140063.87 | BS51: =Budgets!AK38 -> -142303.85 | BT51: =BS51 -> -142303.85 | BU51: =Budgets!AL38 -> -142303.85 | BV51: =BU51 -> -142303.85 | BW51: =Budgets!AM38 -> -152303.85 | BX51: =BW51 -> -152303.85 | BY51: =Budgets!AN38 -> -142303.85 | BZ51: =BY51 -> -142303.85 | CA51: =Budgets!AO38 -> -142303.85 | CB51: =CA51 -> -142303.85 | CC51: =Budgets!AP38 -> -152303.85 | CD51: =CC51 -> -152303.85 | CE51: =Budgets!AQ38 -> -142303.85 | CF51: =CE51 -> -142303.85 | CG51: =Budgets!AR38 -> -142303.85 | CH51: =CG51 -> -142303.85 | CI51: =Budgets!AS38 -> -164543.82 | CJ51: =CI51 -> -164543.82 | CK51: =Budgets!AT38 -> -157755.02 | CL51: =CK51 -> -157755.02 | CM51: =Budgets!AU38 -> -157755.02 | CN51: =CM51 -> -157755.02 | CO51: =Budgets!AV38 -> -167755.02 | CP51: =CO51 -> -167755.02 | CQ51: =Budgets!AW38 -> -169994.99 | CR51: =CQ51 -> -169994.99 | CS51: =Budgets!AX38 -> -169994.99 | CT51: =CS51 -> -169994.99 | CU51: =Budgets!AY38 -> -179994.99 | CV51: =CU51 -> -179994.99 | CW51: =Budgets!AZ38 -> -169994.99 | CX51: =CW51 -> -169994.99 | CY51: =Budgets!BA38 -> -169994.99 | CZ51: =CY51 -> -169994.99 | DA51: =Budgets!BB38 -> -179994.99 | DB51: =DA51 -> -179994.99 | DC51: =Budgets!BC38 -> -169994.99 | DD51: =DC51 -> -169994.99 | DE51: =Budgets!BD38 -> -169994.99 | DF51: =DE51 -> -169994.99 | DG51: =Budgets!BE38 -> -179994.99 | DH51: =DG51 -> -179994.99 | DI51: =Budgets!BF38 -> -173366.75 | DJ51: =DI51 -> -173366.75 | DK51: =Budgets!BG38 -> -173366.75 | DL51: =DK51 -> -173366.75 | DM51: =Budgets!BH38 -> -183366.75 | DN51: =DM51 -> -183366.75 | DO51: =Budgets!BI38 -> -173366.75 | DP51: =DO51 -> -173366.75 | DQ51: =Budgets!BJ38 -> -173366.75 | DR51: =DQ51 -> -173366.75 | DS51: =Budgets!BK38 -> -183366.75 | DT51: =DS51 -> -183366.75 | DU51: =Budgets!BL38 -> -173366.75 | DV51: =DU51 -> -173366.75 | DW51: =Budgets!BM38 -> -173366.75 | DX51: =DW51 -> -173366.75 | DY51: =Budgets!BN38 -> -183366.75 | DZ51: =DY51 -> -183366.75 | EA51: =Budgets!BO38 -> -183866.75 | EB51: =EA51 -> -183866.75 | EC51: =Budgets!BP38 -> -183866.75 | ED51: =EC51 -> -183866.75 | EE51: =Budgets!BQ38 -> -183866.75 | EF51: =EE51 -> -183866.75 | EG51: =Budgets!BR38 -> -183866.75 | EH51: =EG51 -> -183866.75 | EI51: =Budgets!BS38 -> -183866.75 | EJ51: =EI51 -> -183866.75 | EK51: =Budgets!BT38 -> -183866.75 | EL51: =EK51 -> -183866.75 | EM51: =Budgets!BU38 -> -183866.75 | EN51: =EM51 -> -183866.75 | EO51: =Budgets!BV38 -> -183866.75 | EP51: =EO51 -> -183866.75 | EQ51: =Budgets!BW38 -> -183866.75 | ER51: =EQ51 -> -183866.75 | ES51: =Budgets!BX38 -> -183866.75 | ET51: =ES51 -> -183866.75 | EU51: =Budgets!BY38 -> -183866.75 | EV51: =EU51 -> -183866.75 | EW51: =Budgets!BZ38 -> -183866.75 | EX51: =EW51 -> -183866.75
A52: Total Opex | D52: =SUM(D48:D50) -> 0 | F52: =SUM(F48:F51) -> -3736183.8 | H52: =SUM(H48:H51) -> -435097.75 | J52: =SUM(J48:J51) -> -459049.92 | L52: =SUM(L48:L51) -> -379748.55 | N52: =SUM(N48:N51) -> -377768.55 | P52: =SUM(P48:P51) -> -393570.55 | R52: =SUM(R48:R51) -> -412802.85 | T52: =SUM(T48:T51) -> -305508.85 | V52: =SUM(V48:V51) -> -316914.64 | X52: =SUM(X48:X51) -> -274282.64 | Z52: =SUM(Z48:Z51) -> -277462.64 | AB52: =SUM(AB48:AB51) -> -311213.64 | AD52: =SUM(AD48:AD51) -> -336422.88 | AF52: =SUM(AF48:AF51) -> -325692.88 | AH52: =SUM(AH48:AH51) -> -331492.88 | AJ52: =SUM(AJ48:AJ51) -> -406783.08 | AL52: =SUM(AL48:AL51) -> -361393.08 | AN52: =SUM(AN48:AN51) -> -394165.58 | AP52: =SUM(AP48:AP51) -> -509259.06 | AR52: =SUM(AR48:AR51) -> -516991.56 | AT52: =SUM(AT48:AT51) -> -570959.04 | AV52: =SUM(AV48:AV51) -> -544369.04 | AX52: =SUM(AX48:AX51) -> -560279.04 | AZ52: =SUM(AZ48:AZ51) -> -608144.04 | BB52: =SUM(AH48:AH51) -> -331492.88 | BD52: =SUM(BD48:BD51) -> -583493.62 | BF52: =SUM(BF48:BF51) -> -618403.62 | BH52: =SUM(BH48:BH51) -> -689850.23 | BJ52: =SUM(BJ48:BJ51) -> -673727.73 | BL52: =SUM(BL48:BL51) -> -791910.85 | BN52: =SUM(BN48:BN51) -> -714366.14 | BP52: =SUM(BP48:BP51) -> -738774.65 | BR52: =SUM(BR48:BR51) -> -782009.39 | BT52: =SUM(BT48:BT51) -> -808015.99 | BV52: =SUM(BV48:BV51) -> -788015.99 | BX52: =SUM(BX48:BX51) -> -848015.99 | BZ52: =SUM(BZ48:BZ51) -> -788015.99 | CB52: =SUM(CB48:CB51) -> -788015.99 | CD52: =SUM(CD48:CD51) -> -798015.99 | CF52: =SUM(CF48:CF51) -> -813793.08 | CH52: =SUM(CH48:CH51) -> -803793.08 | CJ52: =SUM(CJ48:CJ51) -> -840935.55 | CL52: =SUM(CL48:CL51) -> -834669.29 | CN52: =SUM(CN48:CN51) -> -834669.29 | CP52: =SUM(CP48:CP51) -> -844669.29 | CR52: =SUM(CR48:CR51) -> -861811.76 | CT52: =SUM(CT48:CT51) -> -851811.76 | CV52: =SUM(CV48:CV51) -> -861811.76 | CX52: =SUM(CX48:CX51) -> -851811.76 | CZ52: =SUM(CZ48:CZ51) -> -851811.76 | DB52: =SUM(DB48:DB51) -> -861811.76 | DD52: =SUM(DD48:DD51) -> -858588.43 | DF52: =SUM(DF48:DF51) -> -858588.43 | DH52: =SUM(DH48:DH51) -> -868588.43 | DJ52: =SUM(DJ48:DJ51) -> -873008.85 | DL52: =SUM(DL48:DL51) -> -873008.85 | DN52: =SUM(DN48:DN51) -> -883008.85 | DP52: =SUM(DP48:DP51) -> -873008.85 | DR52: =SUM(DR48:DR51) -> -873008.85 | DT52: =SUM(DT48:DT51) -> -883008.85 | DV52: =SUM(DV48:DV51) -> -873008.85 | DX52: =SUM(DX48:DX51) -> -873008.85 | DZ52: =SUM(DZ48:DZ51) -> -883008.85 | EB52: =SUM(EB48:EB51) -> -883508.85 | ED52: =SUM(ED48:ED51) -> -883508.85 | EF52: =SUM(EF48:EF51) -> -883508.85 | EH52: =SUM(EH48:EH51) -> -883508.85 | EJ52: =SUM(EJ48:EJ51) -> -883508.85 | EL52: =SUM(EL48:EL51) -> -883508.85 | EN52: =SUM(EN48:EN51) -> -883508.85 | EP52: =SUM(EP48:EP51) -> -883508.85 | ER52: =SUM(ER48:ER51) -> -883508.85 | ET52: =SUM(ET48:ET51) -> -883508.85 | EV52: =SUM(EV48:EV51) -> -883508.85 | EX52: =SUM(EX48:EX51) -> -883508.85
A53: EBITDA | D53: =D39+D43+D52 -> 0 | F53: =F39+F43+F52 -> -3217649.5 | H53: =H39+H43+H52 -> -370688.95 | J53: =J39+J43+J52 -> -435792.42 | L53: =L39+L43+L52 -> -356491.05 | N53: =N39+N43+N52 -> -372642.46 | P53: =P39+P43+P52 -> -367044.46 | R53: =R39+R43+R52 -> -381176.75 | T53: =T39+T43+T52 -> -239482.76 | V53: =V39+V43+V52 -> -250788.54 | X53: =X39+X43+X52 -> -122756.54 | Z53: =Z39+Z43+Z52 -> -104006.54 | AB53: =AB39+AB43+AB52 -> -181337.54 | AD53: =AD39+AD43+AD52 -> -121296.79 | AF53: =AF39+AF43+AF52 -> -139566.79 | AH53: =AH39+AH43+AH52 -> -119366.79 | AJ53: =AJ39+AJ43+AJ52 -> -306626.2 | AL53: =AL39+AL43+AL52 -> -257325.7 | AN53: =AN39+AN43+AN52 -> -326501.2 | AP53: =AP39+AP43+AP52 -> -195461.47 | AR53: =AR39+AR43+AR52 -> -293507.13 | AT53: =AT39+AT43+AT52 -> -333598.44 | AV53: =AV39+AV43+AV52 -> -259305.44 | AX53: =AX39+AX43+AX52 -> -142632.11 | AZ53: =AZ39+AZ43+AZ52 -> -216122.11 | BB53: =AH39+AH43+AH52 -> -119366.79 | BD53: =BD39+BD43+BD52 -> -144846.69 | BF53: =BF39+BF43+BF52 -> -22173.357 | BH53: =BH39+BH43+BH52 -> -140246.06 | BJ53: =BJ39+BJ43+BJ52 -> -76311.062 | BL53: =BL39+BL43+BL52 -> 26464.152 | BN53: =BN39+BN43+BN52 -> -3449.4747 | BP53: =BP39+BP43+BP52 -> 145100.35 | BR53: =BR39+BR43+BR52 -> 48240.61 | BT53: =BT39+BT43+BT52 -> 63609.008 | BV53: =BV39+BV43+BV52 -> 153421.51 | BX53: =BX39+BX43+BX52 -> 107171.51 | BZ53: =BZ39+BZ43+BZ52 -> 312192.34 | CB53: =CB39+CB43+CB52 -> 612004.84 | CD53: =CD39+CD43+CD52 -> 398338.17 | CF53: =CF39+CF43+CF52 -> 458019.42 | CH53: =CH39+CH43+CH52 -> 723227.76 | CJ53: =CJ39+CJ43+CJ52 -> 643356.11 | CL53: =CL39+CL43+CL52 -> 1052872.4 | CN53: =CN39+CN43+CN52 -> 933497.38 | CP53: =CP39+CP43+CP52 -> 932976.55 | CR53: =CR39+CR43+CR52 -> 1037292.4 | CT53: =CT39+CT43+CT52 -> 1300292.4 | CV53: =CV39+CV43+CV52 -> 1218896.6 | CX53: =CX39+CX43+CX52 -> 1582521.6 | CZ53: =CZ39+CZ43+CZ52 -> 1793417.4 | DB53: =DB39+DB43+DB52 -> 2083209.1 | DD53: =DD39+DD43+DD52 -> 2318182.4 | DF53: =DF39+DF43+DF52 -> 2326078.2 | DH53: =DH39+DH43+DH52 -> 2470265.7 | DJ53: =DJ39+DJ43+DJ52 -> 2742949.5 | DL53: =DL39+DL43+DL52 -> 2931157.8 | DN53: =DN39+DN43+DN52 -> 3037720.3 | DP53: =DP39+DP43+DP52 -> 3284262 | DR53: =DR39+DR43+DR52 -> 3642282.8 | DT53: =DT39+DT43+DT52 -> 3819637 | DV53: =DV39+DV43+DV52 -> 4240178.7 | DX53: =DX39+DX43+DX52 -> 4574407.8 | DZ53: =DZ39+DZ43+DZ52 -> 4873637 | EB53: =EB39+EB43+EB52 -> 4937199.5 | ED53: =ED39+ED43+ED52 -> 5176074.5 | EF53: =EF39+EF43+EF52 -> 5588741.2 | EH53: =EH39+EH43+EH52 -> 5737366.2 | EJ53: =EJ39+EJ43+EJ52 -> 5785574.5 | EL53: =EL39+EL43+EL52 -> 6088991.2 | EN53: =EN39+EN43+EN52 -> 6575991.2 | EP53: =EP39+EP43+EP52 -> 6423220.3 | ER53: =ER39+ER43+ER52 -> 6752637 | ET53: =ET39+ET43+ET52 -> 7162803.7 | EV53: =EV39+EV43+EV52 -> 6813553.7 | EX53: =EX39+EX43+EX52 -> 6845491.2
A55: Other Income
A56: Grant income | D56: =C56 -> 0 | F56: =E56 -> 0 | G56: =Budgets!E45 -> 0 | H56: =G56 -> 0 | I56: =Budgets!F45 -> 0 | J56: =I56 -> 0 | K56: =Budgets!G45 -> 0 | L56: =K56 -> 0 | M56: =Budgets!H45 -> 0 | N56: =M56 -> 0 | O56: =Budgets!I45 -> 0 | P56: =O56 -> 0 | Q56: =Budgets!G45 -> 0 | R56: =Q56 -> 0 | S56: =Budgets!J45 -> 0 | T56: =S56 -> 0 | U56: =Budgets!K45 -> 0 | V56: =U56 -> 0 | W56: =Budgets!M45 -> 0 | X56: =W56 -> 0 | Y56: =Budgets!O45 -> 0 | Z56: =Y56 -> 0 | AA56: =Budgets!Q45 -> 0 | AB56: =AA56 -> 0 | AC56: =Budgets!S45 -> 0 | AD56: =AC56 -> 0 | AE56: =Budgets!U45 -> 0 | AF56: =AE56 -> 0 | AG56: =Budgets!W45 -> 0 | AH56: =AG56 -> 0 | AI56: =Budgets!Y45 -> 0 | AJ56: =AI56 -> 0 | AK56: =Budgets!AA45 -> 0 | AL56: =AK56 -> 0 | AM56: =Budgets!AC45 -> 0 | AN56: =AM56 -> 0 | AO56: =Budgets!AE45 -> 0 | AP56: =AO56 -> 0 | AQ56: =Budgets!AG45 -> 0 | AR56: =AQ56 -> 0 | AS56: =Budgets!AI45 -> 0 | AT56: =AS56 -> 0 | AU56: =Budgets!AK45 -> 0 | AV56: =AU56 -> 0 | AW56: =Budgets!AM45 -> 0 | AX56: =AW56 -> 0 | AY56: =Budgets!AO45 -> 0 | AZ56: =AY56 -> 0 | BA56: =Budgets!AQ45 -> 0 | BB56: =BA56 -> 0 | BC56: =Budgets!AS45 -> 0 | BD56: =BC56 -> 0 | BE56: =Budgets!AU45 -> 0 | BF56: =BE56 -> 0 | BG56: =Budgets!AW45 -> 0 | BH56: =BG56 -> 0 | BI56: =Budgets!AY45 -> 0 | BJ56: =BI56 -> 0 | BK56: =Budgets!BA45 -> 0 | BL56: =BI56 -> 0 | BM56: =Budgets!BC45 -> 0 | BN56: =BM56 -> 0 | BO56: =Budgets!BE45 -> 0 | BP56: =BO56 -> 0 | BQ56: =Budgets!BG45 -> 0 | BR56: =BQ56 -> 0 | BS56: =Budgets!BG45 -> 0 | BT56: =BS56 -> 0 | BU56: =Budgets!BK45 -> 0 | BV56: =BU56 -> 0 | BW56: =Budgets!BM45 -> 0 | BX56: =BW56 -> 0 | BY56: =Budgets!CA45 -> 0 | BZ56: =BY56 -> 0 | CA56: =Budgets!AO43 -> 0 | CB56: =CA56 -> 0 | CC56: =Budgets!CF45 -> 0 | CD56: =CC56 -> 0 | CE56: =Budgets!CH45 -> 0 | CF56: =CE56 -> 0 | CG56: =Budgets!CK45 -> 0 | CH56: =CG56 -> 0 | CI56: =Budgets!CM45 -> 0 | CJ56: =CI56 -> 0 | CK56: =Budgets!CO45 -> 0 | CL56: =CK56 -> 0 | CM56: =Budgets!CQ45 -> 0 | CN56: =CM56 -> 0 | CO56: =Budgets!CS45 -> 0 | CP56: =CO56 -> 0 | CQ56: =Budgets!CU45 -> 0 | CR56: =CQ56 -> 0 | CS56: =Budgets!CW45 -> 0 | CT56: =CS56 -> 0 | CU56: =Budgets!CY45 -> 0 | CV56: =CU56 -> 0 | CW56: =Budgets!DA45 -> 0 | CX56: =CW56 -> 0 | CY56: =Budgets!DC45 -> 0 | CZ56: =CY56 -> 0 | DA56: =Budgets!DE45 -> 0 | DB56: =DA56 -> 0 | DC56: =Budgets!DG45 -> 0 | DD56: =DC56 -> 0 | DE56: =Budgets!DI45 -> 0 | DF56: =DE56 -> 0 | DG56: =Budgets!DK45 -> 0 | DH56: =DG56 -> 0 | DI56: =Budgets!DM45 -> 0 | DJ56: =DI56 -> 0 | DK56: =Budgets!DO45 -> 0 | DL56: =DK56 -> 0 | DM56: =Budgets!DQ45 -> 0 | DN56: =DM56 -> 0 | DO56: =Budgets!DS45 -> 0 | DP56: =DO56 -> 0 | DQ56: =Budgets!DU45 -> 0 | DR56: =DQ56 -> 0 | DS56: =Budgets!DW45 -> 0 | DT56: =DS56 -> 0 | DU56: =Budgets!DY45 -> 0 | DV56: =DU56 -> 0 | DW56: =Budgets!EA45 -> 0 | DX56: =DW56 -> 0 | DY56: =Budgets!EC45 -> 0 | DZ56: =DY56 -> 0 | EA56: =Budgets!EE45 -> 0 | EB56: =EA56 -> 0 | EC56: =Budgets!EG45 -> 0 | ED56: =EC56 -> 0 | EE56: =Budgets!EI45 -> 0 | EF56: =EE56 -> 0 | EG56: =Budgets!EK45 -> 0 | EH56: =EG56 -> 0 | EI56: =Budgets!EM45 -> 0 | EJ56: =EI56 -> 0 | EK56: =Budgets!EO45 -> 0 | EL56: =EK56 -> 0 | EM56: =Budgets!EQ45 -> 0 | EN56: =EM56 -> 0 | EO56: =Budgets!ES45 -> 0 | EP56: =EO56 -> 0 | EQ56: =Budgets!EU45 -> 0 | ER56: =EQ56 -> 0 | ES56: =Budgets!EW45 -> 0 | ET56: =ES56 -> 0 | EU56: =Budgets!EY45 -> 0 | EV56: =EU56 -> 0 | EW56: =Budgets!FA45 -> 0 | EX56: =EW56 -> 0
A57: Total Other income | D57: =SUM(D56) -> 0 | F57: =SUM(F56) -> 0 | H57: =SUM(H56) -> 0 | J57: =SUM(J56) -> 0 | L57: =K57 -> 0 | N57: =SUM(N56) -> 0 | P57: =SUM(P56) -> 0 | R57: =SUM(R56) -> 0 | T57: =SUM(T56) -> 0 | V57: =SUM(V56) -> 0 | X57: =SUM(X56) -> 0 | Z57: =SUM(Z56) -> 0 | AB57: =SUM(AB56) -> 0 | AD57: =SUM(AD56) -> 0 | AF57: =SUM(AF56) -> 0 | AH57: =SUM(AH56) -> 0 | AJ57: =SUM(AJ56) -> 0 | AL57: =SUM(AL56) -> 0 | AN57: =SUM(AN56) -> 0 | AP57: =SUM(AP56) -> 0 | AR57: =SUM(AR56) -> 0 | AT57: =SUM(AT56) -> 0 | AV57: =SUM(AV56) -> 0 | AX57: =SUM(AX56) -> 0 | AZ57: =SUM(AZ56) -> 0 | BB57: =SUM(AH56) -> 0 | BD57: =SUM(BD56) -> 0 | BF57: =SUM(BF56) -> 0 | BH57: =SUM(BH56) -> 0 | BJ57: =SUM(BJ56) -> 0 | BL57: =SUM(BL56) -> 0 | BN57: =SUM(BN56) -> 0 | BP57: =SUM(BP56) -> 0 | BR57: =SUM(BR56) -> 0 | BT57: =SUM(BT56) -> 0 | BV57: =SUM(BV56) -> 0 | BX57: =SUM(BX56) -> 0 | BZ57: =SUM(BZ56) -> 0 | CB57: =SUM(BO56) -> 0 | CD57: =SUM(CD56) -> 0 | CF57: =SUM(CF56) -> 0 | CH57: =SUM(CH56) -> 0 | CJ57: =SUM(CJ56) -> 0 | CL57: =SUM(CL56) -> 0 | CN57: =SUM(CN56) -> 0 | CP57: =SUM(CP56) -> 0 | CR57: =SUM(CR56) -> 0 | CT57: =SUM(CT56) -> 0 | CV57: =SUM(CV56) -> 0 | CX57: =SUM(CX56) -> 0 | CZ57: =SUM(CZ56) -> 0 | DB57: =SUM(DB56) -> 0 | DD57: =SUM(DD56) -> 0 | DF57: =SUM(DF56) -> 0 | DH57: =SUM(DH56) -> 0 | DJ57: =SUM(DJ56) -> 0 | DL57: =SUM(DL56) -> 0 | DN57: =SUM(DN56) -> 0 | DP57: =SUM(DP56) -> 0 | DR57: =SUM(DR56) -> 0 | DT57: =SUM(DT56) -> 0 | DV57: =SUM(DV56) -> 0 | DX57: =SUM(DX56) -> 0 | DZ57: =SUM(DZ56) -> 0 | EB57: =SUM(EB56) -> 0 | ED57: =SUM(ED56) -> 0 | EF57: =SUM(EF56) -> 0 | EH57: =SUM(EH56) -> 0 | EJ57: =SUM(EJ56) -> 0 | EL57: =SUM(EL56) -> 0 | EN57: =SUM(EN56) -> 0 | EP57: =SUM(EP56) -> 0 | ER57: =SUM(ER56) -> 0 | ET57: =SUM(ET56) -> 0 | EV57: =SUM(EV56) -> 0 | EX57: =SUM(EX56) -> 0
A59: Interest | D59: =C59 -> 0 | E59: =Budgets!D48 -> 33794.64 | F59: =E59 -> 33794.64 | G59: =Budgets!E48 -> 15669.72 | H59: =G59 -> 15669.72 | I59: =Budgets!F48 -> 0 | J59: =I59 -> 0 | K59: =Budgets!G48 -> 0 | L59: =K59 -> 0 | M59: =Budgets!H48 -> 0 | N59: =M59 -> 0 | O59: =Budgets!I48 -> 0 | P59: =O59 -> 0 | Q59: =Budgets!J48 -> 0 | R59: =Q59 -> 0 | S59: =Budgets!K48 -> 0 | T59: =S59 -> 0 | U59: =Budgets!L48 -> 0 | V59: =U59 -> 0 | W59: =Budgets!M48 -> 0 | X59: =W59 -> 0 | Y59: =Budgets!N48 -> 0 | Z59: =Y59 -> 0 | AA59: =Budgets!O48 -> 0 | AB59: =AA59 -> 0 | AC59: =Budgets!P48 -> 0 | AD59: =AC59 -> 0 | AE59: =Budgets!Q48 -> 0 | AF59: =AE59 -> 0 | AG59: =Budgets!R48 -> 0 | AH59: =AG59 -> 0 | AI59: =Budgets!S48 -> 0 | AJ59: =AI59 -> 0 | AK59: =Budgets!T48 -> 0 | AL59: =AK59 -> 0 | AM59: =Budgets!U48 -> 0 | AN59: =AM59 -> 0 | AO59: =Budgets!V48 -> 0 | AP59: =AO59 -> 0 | AQ59: =Budgets!W48 -> 0 | AR59: =AQ59 -> 0 | AS59: =Budgets!X48 -> 0 | AT59: =AS59 -> 0 | AU59: =Budgets!Y48 -> 0 | AV59: =AU59 -> 0 | AW59: =Budgets!Z48 -> 0 | AX59: =AW59 -> 0 | AY59: =Budgets!AA48 -> 0 | AZ59: =AY59 -> 0 | BA59: =Budgets!AB48 -> 0 | BB59: =BA59 -> 0 | BC59: =Budgets!AC48 -> 0 | BD59: =BC59 -> 0 | BE59: =Budgets!AD48 -> 0 | BF59: =BE59 -> 0 | BG59: =Budgets!AE48 -> 0 | BH59: =BG59 -> 0 | BI59: =Budgets!AF48 -> 0 | BJ59: =BI59 -> 0 | BK59: =Budgets!AG48 -> 0 | BL59: =BK59 -> 0 | BM59: =Budgets!AH48 -> 0 | BN59: =BM59 -> 0 | BO59: =Budgets!AI48 -> 0 | BP59: =BO59 -> 0 | BQ59: =Budgets!AJ48 -> 0 | BR59: =BQ59 -> 0 | BS59: =Budgets!AK48 -> 0 | BT59: =BS59 -> 0 | BU59: =Budgets!AL48 -> 0 | BV59: =BU59 -> 0 | BW59: =Budgets!AM48 -> 0 | BX59: =BW59 -> 0 | BY59: =Budgets!AN48 -> 0 | BZ59: =BY59 -> 0 | CA59: =Budgets!AO48 -> 0 | CB59: =CA59 -> 0 | CC59: =Budgets!AP48 -> 0 | CD59: =CC59 -> 0 | CE59: =Budgets!AQ48 -> 0 | CF59: =CE59 -> 0 | CG59: =Budgets!AR48 -> 0 | CH59: =CG59 -> 0 | CI59: =Budgets!AS48 -> 0 | CJ59: =CI59 -> 0 | CK59: =Budgets!AT48 -> 0 | CL59: =CK59 -> 0 | CM59: =Budgets!AU48 -> 0 | CN59: =CM59 -> 0 | CO59: =Budgets!AV48 -> 0 | CP59: =CO59 -> 0 | CQ59: =Budgets!AW48 -> 0 | CR59: =CQ59 -> 0 | CS59: =Budgets!AX48 -> 0 | CT59: =CS59 -> 0 | CU59: =Budgets!AY48 -> 0 | CV59: =CU59 -> 0 | CW59: =Budgets!AZ48 -> 0 | CX59: =CW59 -> 0 | CY59: =Budgets!BA48 -> 0 | CZ59: =CY59 -> 0 | DA59: =Budgets!BB48 -> 0 | DB59: =DA59 -> 0 | DC59: =Budgets!BC48 -> 0 | DD59: =DC59 -> 0 | DE59: =Budgets!BD48 -> 0 | DF59: =DE59 -> 0 | DG59: =Budgets!BE48 -> 0 | DH59: =DG59 -> 0 | DI59: =Budgets!BF48 -> 0 | DJ59: =DI59 -> 0 | DK59: =Budgets!BG48 -> 0 | DL59: =DK59 -> 0 | DM59: =Budgets!BH48 -> 0 | DN59: =DM59 -> 0 | DO59: =Budgets!BI48 -> 0 | DP59: =DO59 -> 0 | DQ59: =Budgets!BJ48 -> 0 | DR59: =DQ59 -> 0 | DS59: =Budgets!BK48 -> 0 | DT59: =DS59 -> 0 | DU59: =Budgets!BL48 -> 0 | DV59: =DU59 -> 0 | DW59: =Budgets!BM48 -> 0 | DX59: =DW59 -> 0 | DY59: =Budgets!BN48 -> 0 | DZ59: =DY59 -> 0 | EA59: =Budgets!BO48 -> 0 | EB59: =EA59 -> 0 | EC59: =Budgets!BP48 -> 0 | ED59: =EC59 -> 0 | EE59: =Budgets!BQ48 -> 0 | EF59: =EE59 -> 0 | EG59: =Budgets!BR48 -> 0 | EH59: =EG59 -> 0 | EI59: =Budgets!BS48 -> 0 | EJ59: =EI59 -> 0 | EK59: =Budgets!BT48 -> 0 | EL59: =EK59 -> 0 | EM59: =Budgets!BU48 -> 0 | EN59: =EM59 -> 0 | EO59: =Budgets!BV48 -> 0 | EP59: =EO59 -> 0 | EQ59: =Budgets!BW48 -> 0 | ER59: =EQ59 -> 0 | ES59: =Budgets!BX48 -> 0 | ET59: =ES59 -> 0 | EU59: =Budgets!BY48 -> 0 | EV59: =EU59 -> 0 | EW59: =Budgets!BZ48 -> 0 | EX59: =EW59 -> 0
A60: Depreciation | D60: =C60 -> 0 | E60: =Budgets!D49 -> -17451.72 | F60: =E60 -> -17451.72 | G60: =Budgets!E49 -> -2259.84 | H60: =G60 -> -2259.84 | I60: =Budgets!F49 -> 0 | J60: =I60 -> 0 | K60: =Budgets!G49 -> 0 | L60: =K60 -> 0 | M60: =Budgets!H49 -> 0 | N60: =M60 -> 0 | O60: =Budgets!I49 -> 0 | P60: =O60 -> 0 | Q60: =Budgets!J49 -> 0 | R60: =Q60 -> 0 | S60: =Budgets!K49 -> 0 | T60: =S60 -> 0 | U60: =Budgets!L49 -> 0 | V60: =U60 -> 0 | W60: =Budgets!M49 -> 0 | X60: =W60 -> 0 | Y60: =Budgets!N49 -> 0 | Z60: =Y60 -> 0 | AA60: =Budgets!O49 -> 0 | AB60: =AA60 -> 0 | AC60: =Budgets!P49 -> 0 | AD60: =AC60 -> 0 | AE60: =Budgets!Q49 -> 0 | AF60: =AE60 -> 0 | AG60: =Budgets!R49 -> 0 | AH60: =AG60 -> 0 | AI60: =Budgets!S49 -> 0 | AJ60: =AI60 -> 0 | AK60: =Budgets!T49 -> 0 | AL60: =AK60 -> 0 | AM60: =Budgets!U49 -> 0 | AN60: =AM60 -> 0 | AO60: =Budgets!V49 -> 0 | AP60: =AO60 -> 0 | AQ60: =Budgets!W49 -> 0 | AR60: =AQ60 -> 0 | AS60: =Budgets!X49 -> 0 | AT60: =AS60 -> 0 | AU60: =Budgets!Y49 -> 0 | AV60: =AU60 -> 0 | AW60: =Budgets!Z49 -> 0 | AX60: =AW60 -> 0 | AY60: =Budgets!AA49 -> 0 | AZ60: =AY60 -> 0 | BA60: =Budgets!AB49 -> 0 | BB60: =BA60 -> 0 | BC60: =Budgets!AC49 -> 0 | BD60: =BC60 -> 0 | BE60: =Budgets!AD49 -> 0 | BF60: =BE60 -> 0 | BG60: =Budgets!AE49 -> 0 | BH60: =BG60 -> 0 | BI60: =Budgets!AF49 -> 0 | BJ60: =BI60 -> 0 | BK60: =Budgets!AG49 -> 0 | BL60: =BK60 -> 0 | BM60: =Budgets!AH49 -> 0 | BN60: =BM60 -> 0 | BO60: =Budgets!AI49 -> 0 | BP60: =BO60 -> 0 | BQ60: =Budgets!AJ49 -> 0 | BR60: =BQ60 -> 0 | BS60: =Budgets!AK49 -> 0 | BT60: =BS60 -> 0 | BU60: =Budgets!AL49 -> 0 | BV60: =BU60 -> 0 | BW60: =Budgets!AM49 -> 0 | BX60: =BW60 -> 0 | BY60: =Budgets!AN49 -> 0 | BZ60: =BY60 -> 0 | CA60: =Budgets!AO49 -> 0 | CB60: =CA60 -> 0 | CC60: =Budgets!AP49 -> 0 | CD60: =CC60 -> 0 | CE60: =Budgets!AQ49 -> 0 | CF60: =CE60 -> 0 | CG60: =Budgets!AR49 -> 0 | CH60: =CG60 -> 0 | CI60: =Budgets!AS49 -> 0 | CJ60: =CI60 -> 0 | CK60: =Budgets!AT49 -> 0 | CL60: =CK60 -> 0 | CM60: =Budgets!AU49 -> 0 | CN60: =CM60 -> 0 | CO60: =Budgets!AV49 -> 0 | CP60: =CO60 -> 0 | CQ60: =Budgets!AW49 -> 0 | CR60: =CQ60 -> 0 | CS60: =Budgets!AX49 -> 0 | CT60: =CS60 -> 0 | CU60: =Budgets!AY49 -> 0 | CV60: =CU60 -> 0 | CW60: =Budgets!AZ49 -> 0 | CX60: =CW60 -> 0 | CY60: =Budgets!BA49 -> 0 | CZ60: =CY60 -> 0 | DA60: =Budgets!BB49 -> 0 | DB60: =DA60 -> 0 | DC60: =Budgets!BC49 -> 0 | DD60: =DC60 -> 0 | DE60: =Budgets!BD49 -> 0 | DF60: =DE60 -> 0 | DG60: =Budgets!BE49 -> 0 | DH60: =DG60 -> 0 | DI60: =Budgets!BF49 -> 0 | DJ60: =DI60 -> 0 | DK60: =Budgets!BG49 -> 0 | DL60: =DK60 -> 0 | DM60: =Budgets!BH49 -> 0 | DN60: =DM60 -> 0 | DO60: =Budgets!BI49 -> 0 | DP60: =DO60 -> 0 | DQ60: =Budgets!BJ49 -> 0 | DR60: =DQ60 -> 0 | DS60: =Budgets!BK49 -> 0 | DT60: =DS60 -> 0 | DU60: =Budgets!BL49 -> 0 | DV60: =DU60 -> 0 | DW60: =Budgets!BM49 -> 0 | DX60: =DW60 -> 0 | DY60: =Budgets!BN49 -> 0 | DZ60: =DY60 -> 0 | EA60: =Budgets!BO49 -> 0 | EB60: =EA60 -> 0 | EC60: =Budgets!BP49 -> 0 | ED60: =EC60 -> 0 | EE60: =Budgets!BQ49 -> 0 | EF60: =EE60 -> 0 | EG60: =Budgets!BR49 -> 0 | EH60: =EG60 -> 0 | EI60: =Budgets!BS49 -> 0 | EJ60: =EI60 -> 0 | EK60: =Budgets!BT49 -> 0 | EL60: =EK60 -> 0 | EM60: =Budgets!BU49 -> 0 | EN60: =EM60 -> 0 | EO60: =Budgets!BV49 -> 0 | EP60: =EO60 -> 0 | EQ60: =Budgets!BW49 -> 0 | ER60: =EQ60 -> 0 | ES60: =Budgets!BX49 -> 0 | ET60: =ES60 -> 0 | EU60: =Budgets!BY49 -> 0 | EV60: =EU60 -> 0 | EW60: =Budgets!BZ49 -> 0 | EX60: =EW60 -> 0
A61: Amortisaion | D61: =C61 -> 0 | E61: =Budgets!D50 -> 0 | F61: =E61 -> 0 | G61: =Budgets!E50 -> 0 | H61: =G61 -> 0 | I61: =-Budgets!F50 -> 0 | J61: =I61 -> 0 | K61: =-Budgets!G50 -> 0 | L61: =K61 -> 0 | M61: =-Budgets!H50 -> 0 | N61: =M61 -> 0 | O61: =-Budgets!I50 -> 0 | P61: =O61 -> 0 | Q61: =-Budgets!J50 -> 0 | R61: =Q61 -> 0 | S61: =-Budgets!K50 -> 0 | T61: =S61 -> 0 | U61: =-Budgets!L50 -> 0 | V61: =U61 -> 0 | W61: =-Budgets!M50 -> 0 | X61: =W61 -> 0 | Y61: =-Budgets!N50 -> 0 | Z61: =Y61 -> 0 | AA61: =-Budgets!R50 -> 0 | AB61: =AA61 -> 0 | AC61: =-Budgets!P50 -> 0 | AD61: =AC61 -> 0 | AE61: =-Budgets!Q50 -> 0 | AF61: =AE61 -> 0 | AG61: =-Budgets!R50 -> 0 | AH61: =AG61 -> 0 | AI61: =-Budgets!S50 -> 0 | AJ61: =AI61 -> 0 | AK61: =-Budgets!T50 -> 0 | AL61: =AK61 -> 0 | AM61: =-Budgets!U50 -> 0 | AN61: =AM61 -> 0 | AO61: =-Budgets!V50 -> 0 | AP61: =AO61 -> 0 | AQ61: =-Budgets!W50 -> 0 | AR61: =AQ61 -> 0 | AS61: =-Budgets!X50 -> 0 | AT61: =AS61 -> 0 | AU61: =-Budgets!Y50 -> 0 | AV61: =AU61 -> 0 | AW61: =-Budgets!Z50 -> 0 | AX61: =AW61 -> 0 | AY61: =-Budgets!AA50 -> 0 | AZ61: =AY61 -> 0 | BA61: =-Budgets!AB50 -> 0 | BB61: =BA61 -> 0 | BC61: =-Budgets!AC50 -> 0 | BD61: =BC61 -> 0 | BE61: =-Budgets!AD50 -> 0 | BF61: =BE61 -> 0 | BG61: =-Budgets!AE50 -> 0 | BH61: =BG61 -> 0 | BI61: =-Budgets!AF50 -> 0 | BJ61: =BI61 -> 0 | BK61: =-Budgets!AG50 -> 0 | BL61: =BI61 -> 0 | BM61: =-Budgets!AH50 -> 0 | BN61: =BM61 -> 0 | BO61: =-Budgets!AI50 -> 0 | BP61: =BO61 -> 0 | BQ61: =-Budgets!AJ50 -> 0 | BR61: =BQ61 -> 0 | BS61: =-Budgets!AK50 -> 0 | BT61: =BS61 -> 0 | BU61: =-Budgets!AL50 -> 0 | BV61: =BU61 -> 0 | BW61: =-Budgets!AM50 -> 0 | BX61: =BW61 -> 0 | BY61: =-Budgets!AN50 -> 0 | BZ61: =BY61 -> 0 | CA61: =-Budgets!AO50 -> 0 | CB61: =CA61 -> 0 | CC61: =-Budgets!AP50 -> 0 | CD61: =CC61 -> 0 | CE61: =-Budgets!AQ50 -> 0 | CF61: =CE61 -> 0 | CG61: =-Budgets!AR50 -> 0 | CH61: =CG61 -> 0 | CI61: =-Budgets!AS50 -> 0 | CJ61: =CI61 -> 0 | CK61: =-Budgets!AT50 -> 0 | CL61: =CK61 -> 0 | CM61: =-Budgets!AU50 -> 0 | CN61: =CM61 -> 0 | CO61: =-Budgets!AV50 -> 0 | CP61: =CO61 -> 0 | CQ61: =-Budgets!AW50 -> 0 | CR61: =CQ61 -> 0 | CS61: =-Budgets!AX50 -> 0 | CT61: =CS61 -> 0 | CU61: =-Budgets!AY50 -> 0 | CV61: =CU61 -> 0 | CW61: =-Budgets!AZ50 -> 0 | CX61: =CW61 -> 0 | CY61: =-Budgets!BA50 -> 0 | CZ61: =CY61 -> 0 | DA61: =-Budgets!BB50 -> 0 | DB61: =DA61 -> 0 | DC61: =-Budgets!BC50 -> 0 | DD61: =DC61 -> 0 | DE61: =-Budgets!BD50 -> 0 | DF61: =DE61 -> 0 | DG61: =-Budgets!BE50 -> 0 | DH61: =DG61 -> 0 | DI61: =-Budgets!BF50 -> 0 | DJ61: =DI61 -> 0 | DK61: =-Budgets!BG50 -> 0 | DL61: =DK61 -> 0 | DM61: =-Budgets!BH50 -> 0 | DN61: =DM61 -> 0 | DO61: =-Budgets!BI50 -> 0 | DP61: =DO61 -> 0 | DQ61: =-Budgets!BJ50 -> 0 | DR61: =DQ61 -> 0 | DS61: =-Budgets!BK50 -> 0 | DT61: =DS61 -> 0 | DU61: =-Budgets!BL50 -> 0 | DV61: =DU61 -> 0 | DW61: =-Budgets!BM50 -> 0 | DX61: =DW61 -> 0 | DY61: =-Budgets!BN50 -> 0 | DZ61: =DY61 -> 0 | EA61: =-Budgets!BO50 -> 0 | EB61: =EA61 -> 0 | EC61: =-Budgets!BP50 -> 0 | ED61: =EC61 -> 0 | EE61: =-Budgets!BQ50 -> 0 | EF61: =EE61 -> 0 | EG61: =-Budgets!BR50 -> 0 | EH61: =EG61 -> 0 | EI61: =-Budgets!BS50 -> 0 | EJ61: =EI61 -> 0 | EK61: =-Budgets!BT50 -> 0 | EL61: =EK61 -> 0 | EM61: =-Budgets!BU50 -> 0 | EN61: =EM61 -> 0 | EO61: =-Budgets!BV50 -> 0 | EP61: =EO61 -> 0 | EQ61: =-Budgets!BW50 -> 0 | ER61: =EQ61 -> 0 | ES61: =-Budgets!BX50 -> 0 | ET61: =ES61 -> 0 | EU61: =-Budgets!BY50 -> 0 | EV61: =EU61 -> 0 | EW61: =-Budgets!BZ50 -> 0 | EX61: =EW61 -> 0
A62: Operating Profit / (Loss) | D62: =SUM(D59:D61) -> 0 | F62: =SUM(F59:F61) -> 16342.92 | H62: =SUM(H59:H61) -> 13409.88 | J62: =SUM(J59:J61) -> 0 | L62: =SUM(L59:L61) -> 0 | N62: =SUM(N59:N61) -> 0 | P62: =SUM(P59:P61) -> 0 | R62: =SUM(R59:R61) -> 0 | T62: =SUM(T59:T61) -> 0 | V62: =SUM(V59:V61) -> 0 | X62: =SUM(X59:X61) -> 0 | Z62: =SUM(Z59:Z61) -> 0 | AB62: =SUM(AB59:AB61) -> 0 | AD62: =SUM(AD59:AD61) -> 0 | AF62: =SUM(AF59:AF61) -> 0 | AH62: =SUM(AH59:AH61) -> 0 | AJ62: =SUM(AJ59:AJ61) -> 0 | AL62: =SUM(AL59:AL61) -> 0 | AN62: =SUM(AN59:AN61) -> 0 | AP62: =SUM(AP59:AP61) -> 0 | AR62: =SUM(AR59:AR61) -> 0 | AT62: =SUM(AT59:AT61) -> 0 | AV62: =SUM(AV59:AV61) -> 0 | AX62: =SUM(AX59:AX61) -> 0 | AZ62: =SUM(AZ59:AZ61) -> 0 | BB62: =SUM(AH59:AH61) -> 0 | BD62: =SUM(BD59:BD61) -> 0 | BF62: =SUM(BF59:BF61) -> 0 | BH62: =SUM(BH59:BH61) -> 0 | BJ62: =SUM(BJ59:BJ61) -> 0 | BL62: =SUM(BL59:BL61) -> 0 | BN62: =SUM(BN59:BN61) -> 0 | BP62: =SUM(BP59:BP61) -> 0 | BR62: =SUM(BR59:BR61) -> 0 | BT62: =SUM(BT59:BT61) -> 0 | BV62: =SUM(BV59:BV61) -> 0 | BX62: =SUM(BX59:BX61) -> 0 | BZ62: =SUM(BZ59:BZ61) -> 0 | CB62: =SUM(BO59:BO61) -> 0 | CD62: =SUM(CD59:CD61) -> 0 | CF62: =SUM(CF59:CF61) -> 0 | CH62: =SUM(CH59:CH61) -> 0 | CJ62: =SUM(CJ59:CJ61) -> 0 | CL62: =SUM(CL59:CL61) -> 0 | CN62: =SUM(CN59:CN61) -> 0 | CP62: =SUM(CP59:CP61) -> 0 | CR62: =SUM(CR59:CR61) -> 0 | CT62: =SUM(CT59:CT61) -> 0 | CV62: =SUM(CV59:CV61) -> 0 | CX62: =SUM(CX59:CX61) -> 0 | CZ62: =SUM(CZ59:CZ61) -> 0 | DB62: =SUM(DB59:DB61) -> 0 | DD62: =SUM(DD59:DD61) -> 0 | DF62: =SUM(DF59:DF61) -> 0 | DH62: =SUM(DH59:DH61) -> 0 | DJ62: =SUM(DJ59:DJ61) -> 0 | DL62: =SUM(DL59:DL61) -> 0 | DN62: =SUM(DN59:DN61) -> 0 | DP62: =SUM(DP59:DP61) -> 0 | DR62: =SUM(DR59:DR61) -> 0 | DT62: =SUM(DT59:DT61) -> 0 | DV62: =SUM(DV59:DV61) -> 0 | DX62: =SUM(DX59:DX61) -> 0 | DZ62: =SUM(DZ59:DZ61) -> 0 | EB62: =SUM(EB59:EB61) -> 0 | ED62: =SUM(ED59:ED61) -> 0 | EF62: =SUM(EF59:EF61) -> 0 | EH62: =SUM(EH59:EH61) -> 0 | EJ62: =SUM(EJ59:EJ61) -> 0 | EL62: =SUM(EL59:EL61) -> 0 | EN62: =SUM(EN59:EN61) -> 0 | EP62: =SUM(EP59:EP61) -> 0 | ER62: =SUM(ER59:ER61) -> 0 | ET62: =SUM(ET59:ET61) -> 0 | EV62: =SUM(EV59:EV61) -> 0 | EX62: =SUM(EX59:EX61) -> 0
A63: Financing Costs | E63: =Budgets!D52 -> 0 | G63: =Budgets!E52 -> 0
A64: Tax (R&D credit -Cr) | D64: =C64 -> 0 | E64: =Budgets!D53 -> 0 | G64: =Budgets!E53 -> 0 | K64: =Budgets!G53 -> 0 | L64: =K64 -> 0 | M64: =Budgets!H53 -> 0 | N64: =M64 -> 0 | O64: =Budgets!I53 -> 436920 | P64: =O64 -> 436920 | Q64: =Budgets!J53 -> 0 | R64: =Q64 -> 0 | S64: =Budgets!O53 -> 0 | T64: =S64 -> 0 | AO64: =Budgets!V53 -> 330000 | BM64: =Budgets!AH53 -> 330000 | BN64: =BM64 -> 330000
A65: Corporation Tax | D65: =C65 -> 0 | E65: =Budgets!D54 -> 0 | G65: =Budgets!E54 -> 0 | I65: =-Budgets!F54 -> 0 | K65: =-Budgets!G54 -> 0
A67: Profit / (Loss) after Tax | D67: =D53+D57+D62+D65 -> 0 | E67: =SUM(E36:E66) -> -3201306.6 | F67: =F39+F43+F52+F62 -> -3201306.6 | G67: =SUM(G36:G66) -> -357279.07 | H67: =H39+H43+H52+H62 -> -357279.07 | I67: =SUM(I36:I66) -> -435792.42 | J67: =J39+J43+J52+J62 -> -435792.42 | K67: =SUM(K36:K66) -> -374122.46 | L67: =L39+L43+L52+L62+L64 -> -356491.05 | M67: =SUM(M36:M66) -> -372642.46 | N67: =N39+N43+N52+N62 -> -372642.46 | O67: =SUM(O36:O66) -> 69875.544 | P67: =P39+P43+P52+P62 -> -367044.46 | Q67: =SUM(Q36:Q66) -> -381176.75 | R67: =R39+R43+R52+R62 -> -381176.75 | S67: =SUM(S36:S66) -> -239482.76 | T67: =T39+T43+T52+T62 -> -239482.76 | U67: =SUM(U36:U66) -> -250788.54 | V67: =V39+V43+V52+V62 -> -250788.54 | W67: =SUM(W36:W66) -> -122756.54 | X67: =X39+X43+X52+X62 -> -122756.54 | Y67: =SUM(Y36:Y66) -> -104006.54 | Z67: =Z39+Z43+Z52+Z62 -> -104006.54 | AA67: =SUM(AA36:AA66) -> -181337.54 | AB67: =AB39+AB43+AB52+AB62 -> -181337.54 | AC67: =SUM(AC36:AC66) -> -121296.79 | AD67: =AD39+AD43+AD52+AD62 -> -121296.79 | AE67: =SUM(AE36:AE66) -> -139566.79 | AF67: =AF39+AF43+AF52+AF62 -> -139566.79 | AG67: =SUM(AG36:AG66) -> -119366.79 | AH67: =AH39+AH43+AH52+AH62 -> -119366.79 | AI67: =SUM(AI36:AI66) -> -306626.2 | AJ67: =AJ39+AJ43+AJ52+AJ62 -> -306626.2 | AK67: =SUM(AK36:AK66) -> -257325.7 | AL67: =AL39+AL43+AL52+AL62 -> -257325.7 | AM67: =SUM(AM36:AM66) -> -326501.2 | AN67: =AN39+AN43+AN52+AN62 -> -326501.2 | AO67: =SUM(AO36:AO66) -> 134538.53 | AP67: =AP39+AP43+AP52+AP62 -> -195461.47 | AQ67: =SUM(AQ36:AQ66) -> -293507.13 | AR67: =AR39+AR43+AR52+AR62 -> -293507.13 | AS67: =SUM(AS36:AS66) -> -333598.44 | AT67: =AT39+AT43+AT52+AT62 -> -333598.44 | AU67: =SUM(AU36:AU66) -> -259305.44 | AV67: =AV39+AV43+AV52+AV62 -> -259305.44 | AW67: =SUM(AW36:AW66) -> -142632.11 | AX67: =AX39+AX43+AX52+AX62 -> -142632.11 | AY67: =SUM(AY36:AY66) -> -216122.11 | AZ67: =AZ39+AZ43+AZ52+AZ62 -> -216122.11 | BA67: =SUM(BA36:BA66) -> -188881.69 | BB67: =AH39+AH43+AH52+AH62 -> -119366.79 | BC67: =SUM(BC36:BC66) -> -144846.69 | BD67: =BD39+BD43+BD52+BD62 -> -144846.69 | BE67: =SUM(BE36:BE66) -> -22173.357 | BF67: =BF39+BF43+BF52+BF62 -> -22173.357 | BG67: =SUM(BG36:BG66) -> -140246.06 | BH67: =BH39+BH43+BH52+BH62 -> -140246.06 | BI67: =SUM(BI36:BI66) -> -76311.062 | BJ67: =BJ39+BJ43+BJ52+BJ62 -> -76311.062 | BK67: =SUM(BK36:BK66) -> 26464.152 | BL67: =BL39+BL43+BL52+BL62 -> 26464.152 | BM67: =SUM(BM36:BM66) -> 326550.53 | BN67: =SUM(BN53:BN64) -> 326550.53 | BO67: =SUM(BO36:BO66) -> 145100.35 | BP67: =BP39+BP43+BP52+BP62 -> 145100.35 | BQ67: =SUM(BQ36:BQ66) -> 48240.61 | BR67: =BR39+BR43+BR52+BR62 -> 48240.61 | BS67: =SUM(BS36:BS66) -> 63609.008 | BT67: =BT39+BT43+BT52+BT62 -> 63609.008 | BU67: =SUM(BU36:BU66) -> 153421.51 | BV67: =BV39+BV43+BV52+BV62 -> 153421.51 | BW67: =SUM(BW36:BW66) -> 107171.51 | BX67: =BX39+BX43+BX52+BX62 -> 107171.51 | BY67: =SUM(BY36:BY66) -> 312192.34 | BZ67: =BZ39+BZ43+BZ52+BZ62 -> 312192.34 | CA67: =SUM(CA36:CA66) -> 612004.84 | CB67: =CB39+CB43+CB52+CB62 -> 612004.84 | CC67: =SUM(CC36:CC66) -> 398338.17 | CD67: =CD39+CD43+CD52+CD62 -> 398338.17 | CE67: =SUM(CE36:CE66) -> 458019.42 | CF67: =CF39+CF43+CF52+CF62 -> 458019.42 | CG67: =SUM(CG36:CG66) -> 723227.76 | CH67: =CH39+CH43+CH52+CH62 -> 723227.76 | CI67: =SUM(CI36:CI66) -> 643356.11 | CJ67: =CJ39+CJ43+CJ52+CJ62 -> 643356.11 | CK67: =SUM(CK36:CK66) -> 1052872.4 | CL67: =CL39+CL43+CL52+CL62 -> 1052872.4 | CM67: =SUM(CM36:CM66) -> 933497.38 | CN67: =CN39+CN43+CN52+CN62 -> 933497.38 | CO67: =SUM(CO36:CO66) -> 932976.55 | CP67: =CP39+CP43+CP52+CP62 -> 932976.55 | CQ67: =SUM(CQ36:CQ66) -> 1037292.4 | CR67: =CR39+CR43+CR52+CR62 -> 1037292.4 | CS67: =SUM(CS36:CS66) -> 1300292.4 | CT67: =CT39+CT43+CT52+CT62 -> 1300292.4 | CU67: =SUM(CU36:CU66) -> 1218896.6 | CV67: =CV39+CV43+CV52+CV62 -> 1218896.6 | CW67: =SUM(CW36:CW66) -> 1582521.6 | CX67: =CX39+CX43+CX52+CX62 -> 1582521.6 | CY67: =SUM(CY36:CY66) -> 1793417.4 | CZ67: =CZ39+CZ43+CZ52+CZ62 -> 1793417.4 | DA67: =SUM(DA36:DA66) -> 2083209.1 | DB67: =DB39+DB43+DB52+DB62 -> 2083209.1 | DC67: =SUM(DC36:DC66) -> 2318182.4 | DD67: =DD39+DD43+DD52+DD62 -> 2318182.4 | DE67: =SUM(DE36:DE66) -> 2326078.2 | DF67: =DF39+DF43+DF52+DF62 -> 2326078.2 | DG67: =SUM(DG36:DG66) -> 2470265.7 | DH67: =DH39+DH43+DH52+DH62 -> 2470265.7 | DI67: =SUM(DI36:DI66) -> 2742949.5 | DJ67: =DJ39+DJ43+DJ52+DJ62 -> 2742949.5 | DK67: =SUM(DK36:DK66) -> 2931157.8 | DL67: =DL39+DL43+DL52+DL62 -> 2931157.8 | DM67: =SUM(DM36:DM66) -> 3037720.3 | DN67: =DN39+DN43+DN52+DN62 -> 3037720.3 | DO67: =SUM(DO36:DO66) -> 3284262 | DP67: =DP39+DP43+DP52+DP62 -> 3284262 | DQ67: =SUM(DQ36:DQ66) -> 3642282.8 | DR67: =DR39+DR43+DR52+DR62 -> 3642282.8 | DS67: =SUM(DS36:DS66) -> 3819637 | DT67: =DT39+DT43+DT52+DT62 -> 3819637 | DU67: =SUM(DU36:DU66) -> 4240178.7 | DV67: =DV39+DV43+DV52+DV62 -> 4240178.7 | DW67: =SUM(DW36:DW66) -> 4574407.8 | DX67: =DX39+DX43+DX52+DX62 -> 4574407.8 | DY67: =SUM(DY36:DY66) -> 4873637 | DZ67: =DZ39+DZ43+DZ52+DZ62 -> 4873637 | EA67: =SUM(EA36:EA66) -> 4937199.5 | EB67: =EB39+EB43+EB52+EB62 -> 4937199.5 | EC67: =SUM(EC36:EC66) -> 5176074.5 | ED67: =ED39+ED43+ED52+ED62 -> 5176074.5 | EE67: =SUM(EE36:EE66) -> 5588741.2 | EF67: =EF39+EF43+EF52+EF62 -> 5588741.2 | EG67: =SUM(EG36:EG66) -> 5737366.2 | EH67: =EH39+EH43+EH52+EH62 -> 5737366.2 | EI67: =SUM(EI36:EI66) -> 5785574.5 | EJ67: =EJ39+EJ43+EJ52+EJ62 -> 5785574.5 | EK67: =SUM(EK36:EK66) -> 6088991.2 | EL67: =EL39+EL43+EL52+EL62 -> 6088991.2 | EM67: =SUM(EM36:EM66) -> 6575991.2 | EN67: =EN39+EN43+EN52+EN62 -> 6575991.2 | EO67: =SUM(EO36:EO66) -> 6423220.3 | EP67: =EP39+EP43+EP52+EP62 -> 6423220.3 | EQ67: =SUM(EQ36:EQ66) -> 6752637 | ER67: =ER39+ER43+ER52+ER62 -> 6752637 | ES67: =SUM(ES36:ES66) -> 7162803.7 | ET67: =ET39+ET43+ET52+ET62 -> 7162803.7 | EU67: =SUM(EU36:EU66) -> 6813553.7 | EV67: =EV39+EV43+EV52+EV62 -> 6813553.7 | EW67: =SUM(EW36:EW66) -> 6845491.2 | EX67: =EX39+EX43+EX52+EX62 -> 6845491.2
A70: Checi | E70: =E67-Budgets!D51 -> 0 | G70: =G67-Budgets!E56 -> 0 | I70: =I67-Budgets!F56 -> 0 | K70: =K67-Budgets!G56 -> 0 | M70: =M67-Budgets!H56 -> 0 | O70: =O67-Budgets!I56 -> 0 | Q70: =Q67-Budgets!J56 -> 0 | S70: =S67-Budgets!K56 -> 0 | U70: =U67-Budgets!L56 -> 0 | W70: =W67-Budgets!M56 -> 0 | Y70: =Y67-Budgets!N56 -> 0 | AA70: =AA67-Budgets!O56 -> 0 | AC70: =AC67-Budgets!P56 -> 0 | AE70: =AE67-Budgets!Q56 -> 0 | AG70: =AG67-Budgets!R56 -> 0 | AI70: =AI67-Budgets!S56 -> 0 | AK70: =AK67-Budgets!T56 -> 0 | AM70: =AM67-Budgets!U56 -> 0 | AO70: =AO67-Budgets!V56 -> 0 | AQ70: =AQ67-Budgets!W56 -> 0 | AS70: =AS67-Budgets!X56 -> 0 | AU70: =AU67-Budgets!Y56 -> 0 | AW70: =AW67-Budgets!Z56 -> 0 | AY70: =AY67-Budgets!AA56 -> 0 | BA70: =BA67-Budgets!AB56 -> 0 | BC70: =BC67-Budgets!AC56 -> 0 | BE70: =BE67-Budgets!AD56 -> 2.910383e-11 | BG70: =BG67-Budgets!AE56 -> 0 | BI70: =BI67-Budgets!AF56 -> 0 | BK70: =BK67-Budgets!AG56 -> -2.910383e-11 | BM70: =BM67-Budgets!AH56 -> 0 | BO70: =BO67-Budgets!AI56 -> 0 | BQ70: =BQ67-Budgets!AJ56 -> 0 | BS70: =BS67-Budgets!AK56 -> 0 | BU70: =BU67-Budgets!AL56 -> 0 | BW70: =BW67-Budgets!AM56 -> 0 | BY70: =BY67-Budgets!AN56 -> 0 | CA70: =CA67-Budgets!AO56 -> 0 | CC70: =CC67-Budgets!AP56 -> 0 | CE70: =CE67-Budgets!AQ56 -> 0 | CG70: =CG67-Budgets!AR56 -> 0 | CI70: =CI67-Budgets!AS56 -> 0 | CK70: =CK67-Budgets!AT56 -> 0 | CM70: =CM67-Budgets!AU56 -> 0 | CO70: =CO67-Budgets!AV56 -> 0 | CQ70: =CQ67-Budgets!AW56 -> 0 | CS70: =CS67-Budgets!AX56 -> 0 | CU70: =CU67-Budgets!AY56 -> 0 | CW70: =CW67-Budgets!AZ56 -> 0 | CY70: =CY67-Budgets!BA56 -> 0 | DA70: =DA67-Budgets!BB56 -> 0 | DC70: =DC67-Budgets!BC56 -> 0 | DE70: =DE67-Budgets!BD56 -> 0 | DG70: =DG67-Budgets!BE56 -> 0 | DI70: =DI67-Budgets!BF56 -> 0 | DK70: =DK67-Budgets!BG56 -> 0 | DM70: =DM67-Budgets!BH56 -> 0 | DO70: =DO67-Budgets!BI56 -> 0 | DQ70: =DQ67-Budgets!BJ56 -> 0 | DS70: =DS67-Budgets!BK56 -> 0 | DU70: =DU67-Budgets!BL56 -> 0 | DW70: =DW67-Budgets!BM56 -> 0 | DY70: =DY67-Budgets!BN56 -> 0 | EA70: =EA67-Budgets!BO56 -> 0 | EC70: =EC67-Budgets!BP56 -> 0 | EE70: =EE67-Budgets!BQ56 -> 0 | EG70: =EG67-Budgets!BR56 -> 0 | EI70: =EI67-Budgets!BS56 -> 0 | EK70: =EK67-Budgets!BT56 -> 0 | EM70: =EM67-Budgets!BU56 -> 0 | EO70: =EO67-Budgets!BV56 -> 0 | EQ70: =EQ67-Budgets!BW56 -> 0 | ES70: =ES67-Budgets!BX56 -> 0 | EU70: =EU67-Budgets!BY56 -> 0 | EW70: =EW67-Budgets!BZ56 -> 0

Sheet Primary Statements
A1: PROFIT AND LOSS ACCOUNT
B4: 2023 | C4: 2024 | D4: 2025 | E4: 2026 | F4: 2027
A5: Revenue
A6: DC Drive Business | B6: =SUM(Budgets!C6:L6) -> 938079.92 | C6: =SUM(Budgets!M6:X6) -> 2248921.4 | D6: =SUM(Budgets!Y6:AJ6) -> 6623187.5 | E6: =SUM(Budgets!AK6:AV6) -> 10912896 | F6: =SUM(Budgets!AW6:BH6) -> 13619125
A7: MC Drive Business | B7: =SUM(Budgets!C7:L7) -> 0 | C7: =SUM(Budgets!M7:X7) -> 62750 | D7: =SUM(Budgets!Y7:AJ7) -> 558750 | E7: =SUM(Budgets!AK7:AV7) -> 3246000 | F7: =SUM(Budgets!AW7:BH7) -> 9000270.8
A8: SaaS product | B8: =SUM(Budgets!C8:L8) -> 0 | C8: =SUM(Budgets!M8:X8)+SUM(Budgets!M9:X9) -> 0 | D8: =SUM(Budgets!Y8:AJ8)+SUM(Budgets!Y9:AJ9) -> 418187.5 | E8: =SUM(Budgets!AK8:AV8)+SUM(Budgets!AK9:AV9) -> 2918604.2 | F8: =SUM(Budgets!AW8:BH8)+SUM(Budgets!AW9:BH9) -> 10673646
A9: Total Revenue | B9: =SUM(B6:B8) -> 938079.92 | C9: =SUM(C6:C8) -> 2311671.4 | D9: =SUM(D6:D8) -> 7600125 | E9: =SUM(E6:E8) -> 17077500 | F9: =SUM(F6:F8) -> 33293042
A11: Cost of Sales
A12: Total Cost of Sales | B12: =SUM(Budgets!C26:L26) -> -130822.77 | C12: =SUM(Budgets!M26:X26) -> -196903.53 | D12: =SUM(Budgets!Y26:AJ26) -> -668743.43 | E12: =SUM(Budgets!AK26:AV26) -> -1432750 | F12: =SUM(Budgets!AW26:BH26) -> -2112666.7
A15: GROSS PROFIT | B15: =B9+B12 -> 807257.15 | C15: =C9+C12 -> 2114767.8 | D15: =D9+D12 -> 6931381.6 | E15: =E9+E12 -> 15644750 | F15: =F9+F12 -> 31180375
A17: Operating Expenses
A18: Sales & Marketing | B18: =SUM(Budgets!C32:L32) -> -1361035.9 | C18: =SUM(Budgets!M32:X32) -> -1444884.6 | D18: =SUM(Budgets!Y32:AJ32) -> -3476989.7 | E18: =SUM(Budgets!AK32:AV32) -> -4337661.6 | F18: =SUM(Budgets!AW32:BH32) -> -4482730.9
A19: Product development | B19: =SUM(Budgets!C34:L34) -> -2625519.5 | C19: =SUM(Budgets!M34:X34) -> -1339440.3 | D19: =SUM(Budgets!Y34:AJ34) -> -1606038.6 | E19: =SUM(Budgets!AK34:AV34) -> -1750956 | F19: =SUM(Budgets!AW34:BH34) -> -1763921
A20: G&A | B20: =SUM(Budgets!C36:L36) -> -1943549.7 | C20: =SUM(Budgets!M36:X36) -> -896000.19 | D20: =SUM(Budgets!Y36:AJ36) -> -1384754 | E20: =SUM(Budgets!AK36:AV36) -> -1895768.3 | F20: =SUM(Budgets!AW36:BH36) -> -2018955.3
A21: Product Support | B21: =SUM(Budgets!C38:L38) -> -886540.47 | C21: =SUM(Budgets!M38:X38) -> -935793.81 | D21: =SUM(Budgets!Y38:AJ38) -> -1437762.1 | E21: =SUM(Budgets!AK38:AV38) -> -1806239.7 | F21: =SUM(Budgets!AW38:BH38) -> -2090055.2
A22: Total Opex | B22: =SUM(B18:B21) -> -6816645.5 | C22: =SUM(C18:C21) -> -4616119 | D22: =SUM(D18:D21) -> -7905544.4 | E22: =SUM(E18:E21) -> -9790625.5 | F22: =SUM(F18:F21) -> -10355662
A23: EBITDA | B23: =B15+B22 -> -6009388.3 | C23: =C15+C22 -> -2501351.1 | D23: =D15+D22 -> -974162.88 | E23: =E15+E22 -> 5854124.5 | F23: =F15+F22 -> 20824713
A25: Interest | B25: =SUM(Budgets!C48:L48) -> 49464.36 | C25: =SUM(Budgets!M48:X48) -> 0 | D25: =SUM(Budgets!Y48:AJ48) -> 0 | E25: =SUM(Budgets!AK48:AV48) -> 0 | F25: =SUM(Budgets!AW48:BH48) -> 0
A26: Depreciation | B26: =SUM(Budgets!C49:L49) -> -19711.56 | C26: =SUM(Budgets!M49:X49) -> 0 | D26: =SUM(Budgets!Y49:AJ49) -> 0 | E26: =SUM(Budgets!AK49:AV49) -> 0 | F26: =SUM(Budgets!AW49:BH49) -> 0
A28: Operating Profit / (Loss) | B28: =SUM(B23:B26) -> -5979635.5 | C28: =SUM(C23:C26) -> -2501351.1 | D28: =SUM(D23:D26) -> -974162.88 | E28: =SUM(E23:E26) -> 5854124.5 | F28: =SUM(F23:F26) -> 20824713
A29: Financing Costs
A30: Tax (R&D credit -Cr) | B30: =-B19*0.11 -> 288807.14 | C30: =-C19*0.11 -> 147338.44 | D30: =-D19*0.11 -> 176664.25 | E30: =-E28*0.2 -> -1170824.9 | F30: =-F28*0.2 -> -4164942.5
A31: Profit / (Loss) after Tax | B31: =B28+B30 -> -5690828.4 | C31: =C28+C30 -> -2354012.7 | D31: =D28+D30 -> -797498.62 | E31: =E28+E30 -> 4683299.6 | F31: =F28+F30 -> 16659770

Sheet P&L
A1: SPRINT ELECTRIC LIMITED MANAGEMENT ACCOUNTS
A2: Year End 31 OCT
A3: Summary Profit and Loss November 2022
J5: Month | N5: Month | R5: Month | V5: Month | Z5: Month | AD5: Month | AH5: Month | AL5: Month | AP5: Month | AT5: Month | AX5: Year to Date
B6: 44866 | C6: 44866 | D6: 44866 | F6: =B6+31 -> 44897 | G6: =C6+31 -> 44897 | H6: =D6+31 -> 44897 | J6: =F6+31 -> 44928 | K6: =G6+31 -> 44928 | L6: =H6+31 -> 44928 | N6: =J6+31 -> 44959 | O6: =K6+31 -> 44959 | P6: =L6+31 -> 44959 | R6: =N6+31 -> 44990 | S6: =O6+31 -> 44990 | T6: =P6+31 -> 44990 | V6: =R6+31 -> 45021 | W6: =S6+31 -> 45021 | X6: =T6+31 -> 45021 | Z6: =V6+31 -> 45052 | AA6: =W6+31 -> 45052 | AB6: =X6+31 -> 45052 | AD6: =Z6+31 -> 45083 | AE6: =AA6+31 -> 45083 | AF6: =AB6+31 -> 45083 | AH6: =AD6+31 -> 45114 | AI6: =AE6+31 -> 45114 | AJ6: =AF6+31 -> 45114 | AL6: =AH6+31 -> 45145 | AM6: =AI6+31 -> 45145 | AN6: =AJ6+31 -> 45145 | AP6: =AL6+31 -> 45176 | AQ6: =AM6+31 -> 45176 | AR6: =AN6+31 -> 45176 | AT6: =AP6+31 -> 45207 | AU6: =AQ6+31 -> 45207 | AV6: =AR6+31 -> 45207 | AX6: 44927 | AY6: 44927 | AZ6: 44927
A7: Revenue | B7: Actual | C7: Budget | D7: Variance | F7: Actual | G7: Budget | H7: Variance | J7: Actual | K7: Budget | L7: Variance | N7: Actual | O7: Budget | P7: Variance | R7: Actual | S7: Budget | T7: Variance | V7: Actual | W7: Budget | X7: Variance | Z7: Actual | AA7: Budget | AB7: Variance | AD7: Actual | AE7: Budget | AF7: Variance | AH7: Actual | AI7: Reforecast | AJ7: Variance | AL7: Actual | AM7: Reforecast | AN7: Variance | AP7: Actual | AQ7: Reforecast | AR7: Variance | AT7: Actual | AU7: Reforecast | AV7: Variance | AX7: Actual | AY7: Budget | AZ7: Variance
A8: UK/Europe | C8: =Budgets!#REF! -> #REF! | D8: =C8-B8 -> #REF! | G8: =Budgets!#REF! -> #REF! | H8: =G8-F8 -> #REF! | J8: =SUM('Trial Balance'!$L54:$L63) -> 0 | K8: =Budgets!C6 -> 0 | L8: =K8-J8 -> 0 | O8: =Budgets!D6 -> 598158 | P8: =O8-N8 -> 598158 | S8: =Budgets!E6 -> 75913.92 | T8: =S8-R8 -> 75913.92 | W8: =Budgets!F6 -> 32708 | X8: =W8-V8 -> 32708 | AA8: =Budgets!G6 -> 8000 | AB8: =AA8-Z8 -> 8000 | AE8: =Budgets!H6 -> 8000 | AF8: =AE8-AD8 -> 8000 | AI8: =Budgets!I6 -> 34900 | AJ8: =AI8-AH8 -> 34900 | AM8: =Budgets!J6 -> 35500 | AN8: =AM8-AL8 -> 35500 | AQ8: =Budgets!K6 -> 74900 | AR8: =AQ8-AP8 -> 74900 | AU8: =Budgets!L6 -> 70000 | AV8: =AU8-AT8 -> 70000 | AX8: =B8+F8+J8 -> 0 | AY8: =C8+G8+K8 -> #REF! | AZ8: =AX8-AY8 -> #REF!
A9: USA | C9: =Budgets!#REF! -> #REF! | D9: =C9-B9 -> #REF! | G9: =Budgets!#REF! -> #REF! | H9: =G9-F9 -> #REF! | K9: =Budgets!C7 -> 0 | L9: =K9-J9 -> 0 | O9: =Budgets!D7 -> 0 | P9: =O9-N9 -> 0 | S9: =Budgets!E7 -> 0 | T9: =S9-R9 -> 0 | W9: =Budgets!F7 -> 0 | X9: =W9-V9 -> 0 | AA9: =Budgets!G7 -> 0 | AB9: =AA9-Z9 -> 0 | AE9: =Budgets!H7 -> 0 | AF9: =AE9-AD9 -> 0 | AI9: =Budgets!I7 -> 0 | AJ9: =AI9-AH9 -> 0 | AM9: =Budgets!J7 -> 0 | AN9: =AM9-AL9 -> 0 | AQ9: =Budgets!K7 -> 0 | AR9: =AQ9-AP9 -> 0 | AU9: =Budgets!L7 -> 0 | AV9: =AU9-AT9 -> 0
A10: RoW | C10: =Budgets!#REF! -> #REF! | D10: =C10-B10 -> #REF! | G10: =Budgets!#REF! -> #REF! | H10: =G10-F10 -> #REF! | K10: =Budgets!C8 -> 0 | L10: =K10-J10 -> 0 | O10: =Budgets!D8 -> 0 | P10: =O10-N10 -> 0 | S10: =Budgets!E8 -> 0 | T10: =S10-R10 -> 0 | W10: =Budgets!F8 -> 0 | X10: =W10-V10 -> 0 | AA10: =Budgets!G8 -> 0 | AB10: =AA10-Z10 -> 0 | AE10: =Budgets!H8 -> 0 | AF10: =AE10-AD10 -> 0 | AI10: =Budgets!I8 -> 0 | AJ10: =AI10-AH10 -> 0 | AM10: =Budgets!J8 -> 0 | AN10: =AM10-AL10 -> 0 | AQ10: =Budgets!K8 -> 0 | AR10: =AQ10-AP10 -> 0 | AU10: =Budgets!L8 -> 0 | AV10: =AU10-AT10 -> 0
A11: Total Revenue | B11: =SUM(B8:B10) -> 0 | C11: =SUM(C8:C10) -> #REF! | D11: =SUM(D8:D10) -> #REF! | F11: =SUM(F8:F10) -> 0 | G11: =SUM(G8:G10) -> #REF! | H11: =SUM(H8:H10) -> #REF! | J11: =SUM(J8:J10) -> 0 | K11: =SUM(K8:K10) -> 0 | L11: =SUM(L8:L10) -> 0 | N11: =SUM(N8:N10) -> 0 | O11: =SUM(O8:O10) -> 598158 | P11: =SUM(P8:P10) -> 598158 | R11: =SUM(R8:R10) -> 0 | S11: =SUM(S8:S10) -> 75913.92 | T11: =SUM(T8:T10) -> 75913.92 | V11: =SUM(V8:V10) -> 0 | W11: =SUM(W8:W10) -> 32708 | X11: =SUM(X8:X10) -> 32708 | Z11: =SUM(Z8:Z10) -> 0 | AA11: =SUM(AA8:AA10) -> 8000 | AB11: =SUM(AB8:AB10) -> 8000 | AD11: =SUM(AD8:AD10) -> 0 | AE11: =SUM(AE8:AE10) -> 8000 | AF11: =SUM(AF8:AF10) -> 8000 | AH11: =SUM(AH8:AH10) -> 0 | AI11: =SUM(AI8:AI10) -> 34900 | AJ11: =SUM(AJ8:AJ10) -> 34900 | AL11: =SUM(AL8:AL10) -> 0 | AM11: =SUM(AM8:AM10) -> 35500 | AN11: =SUM(AN8:AN10) -> 35500 | AP11: =SUM(AP8:AP10) -> 0 | AQ11: =SUM(AQ8:AQ10) -> 74900 | AR11: =SUM(AR8:AR10) -> 74900 | AT11: =SUM(AT8:AT10) -> 0 | AU11: =SUM(AU8:AU10) -> 70000 | AV11: =SUM(AV8:AV10) -> 70000 | AX11: =SUM(AX8:AX10) -> 0 | AY11: =SUM(AY8:AY10) -> #REF! | AZ11: =SUM(AZ8:AZ10) -> #REF!
A13: Cost of Sales
A14: Direct costs | B14: ='Direct Costs'!#REF! -> #REF! | C14: =Budgets!#REF! -> #REF! | D14: =C14-B14 -> #REF! | F14: ='Direct Costs'!C41 -> 0 | G14: =Budgets!E22 -> -11505.12 | H14: =G14-F14 -> -11505.12 | J14: =SUM('Trial Balance'!$L64:$L82)+'Trial Balance'!L88+'Trial Balance'!L94 -> 0 | K14: =Budgets!I22 -> -5000 | L14: =K14+J14 -> -5000 | N14: ='Direct Costs'!K41 -> 0 | O14: =Budgets!M22 -> 0 | P14: =O14-N14 -> 0 | R14: ='Direct Costs'!O41 -> 0 | S14: =Budgets!Q22 -> 0 | T14: =S14-R14 -> 0 | V14: ='Direct Costs'!S41 -> 0 | W14: =Budgets!U22 -> -10416.667 | X14: =W14-V14 -> -10416.667 | Z14: ='Direct Costs'!W41 -> 0 | AA14: =Budgets!Y22 -> -34166.667 | AB14: =AA14-Z14 -> -34166.667 | AD14: ='Direct Costs'!AA41 -> 0 | AE14: =Budgets!AC22 -> -38333.333 | AF14: =AE14-AD14 -> -38333.333 | AH14: ='Direct Costs'!AE41 -> 0 | AI14: =Budgets!AG22 -> -46666.667 | AJ14: =AI14-AH14 -> -46666.667 | AL14: ='Direct Costs'!AI41 -> 0 | AM14: =Budgets!AK22 -> -57083.333 | AN14: =AM14-AL14 -> -57083.333 | AP14: ='Direct Costs'!AM41 -> 0 | AQ14: =Budgets!AO22 -> -89166.667 | AR14: =AQ14-AP14 -> -89166.667 | AT14: ='Direct Costs'!AQ41 -> 0 | AU14: =Budgets!AS22 -> -117083.33 | AV14: =AU14-AT14 -> -117083.33 | AX14: =B14+F14+J14 -> #REF! | AY14: =C14+G14+K14 -> #REF! | AZ14: =AX14-AY14 -> #REF!
A15: Peregrine House (net position) | J15: =#REF! -> #REF! | L15: =K15+J15 -> #REF! | AX15: =B15+F15+J15 -> #REF! | AY15: =C15+G15+K15 -> 0 | AZ15: =AX15-AY15 -> #REF!
A16: Total Cost of Sales | B16: =SUM(B14) -> #REF! | C16: =SUM(C14) -> #REF! | D16: =SUM(D14) -> #REF! | F16: =SUM(F14) -> 0 | G16: =SUM(G14) -> -11505.12 | H16: =SUM(H14) -> -11505.12 | J16: =SUM(J14:J15) -> #REF! | K16: =SUM(K14:K15) -> -5000 | L16: =SUM(L14:L15) -> #REF! | N16: =SUM(N14) -> 0 | O16: =SUM(O14) -> 0 | P16: =SUM(P14) -> 0 | R16: =SUM(R14) -> 0 | S16: =SUM(S14) -> 0 | T16: =SUM(T14) -> 0 | V16: =SUM(V14) -> 0 | W16: =SUM(W14) -> -10416.667 | X16: =SUM(X14) -> -10416.667 | Z16: =SUM(Z14) -> 0 | AA16: =SUM(AA14) -> -34166.667 | AB16: =SUM(AB14) -> -34166.667 | AD16: =SUM(AD14) -> 0 | AE16: =SUM(AE14) -> -38333.333 | AF16: =SUM(AF14) -> -38333.333 | AH16: =SUM(AH14) -> 0 | AI16: =SUM(AI14) -> -46666.667 | AJ16: =SUM(AJ14) -> -46666.667 | AL16: =SUM(AL14) -> 0 | AM16: =SUM(AM14) -> -57083.333 | AN16: =SUM(AN14) -> -57083.333 | AP16: =SUM(AP14) -> 0 | AQ16: =SUM(AQ14) -> -89166.667 | AR16: =SUM(AR14) -> -89166.667 | AT16: =SUM(AT14) -> 0 | AU16: =AU14 -> -117083.33 | AV16: =SUM(AV14) -> -117083.33 | AX16: =SUM(AX14:AX15) -> #REF! | AY16: =SUM(AY14:AY15) -> #REF! | AZ16: =SUM(AZ14) -> #REF!
A18: GROSS PROFIT | B18: =B11-B16 -> #REF! | C18: =C11-C16 -> #REF! | D18: =D11-D16 -> #REF! | F18: =F11-F16 -> 0 | G18: =G11-G16 -> #REF! | H18: =H11-H16 -> #REF! | J18: =J11+J16 -> #REF! | K18: =K11+K16 -> -5000 | L18: =J18-K18 -> #REF! | N18: =N11-N16 -> 0 | O18: =O11-O16 -> 598158 | P18: =P11-P16 -> 598158 | R18: =R11-R16 -> 0 | S18: =S11-S16 -> 75913.92 | T18: =T11-T16 -> 75913.92 | V18: =V11-V16 -> 0 | W18: =W11-W16 -> 43124.667 | X18: =X11-X16 -> 43124.667 | Z18: =Z11-Z16 -> 0 | AA18: =AA11-AA16 -> 42166.667 | AB18: =AB11-AB16 -> 42166.667 | AD18: =AD11-AD16 -> 0 | AE18: =AE11-AE16 -> 46333.333 | AF18: =AF11-AF16 -> 46333.333 | AH18: =AH11-AH16 -> 0 | AI18: =AI11-AI16 -> 81566.667 | AJ18: =AJ11-AJ16 -> 81566.667 | AL18: =AL11-AL16 -> 0 | AM18: =AM11-AM16 -> 92583.333 | AN18: =AN11-AN16 -> 92583.333 | AP18: =AP11-AP16 -> 0 | AQ18: =AQ11-AQ16 -> 164066.67 | AR18: =AR11-AR16 -> 164066.67 | AT18: =AT11-AT16 -> 0 | AU18: =AU11-AU16 -> 187083.33 | AV18: =AV11-AV16 -> 187083.33 | AX18: =AX11+AX16 -> #REF! | AY18: =AY11+AY16 -> #REF! | AZ18: =AZ11+AZ16 -> #REF!
A20: Operating Expenses
A21: Sales & Marketing | C21: =Budgets!#REF! -> #REF! | D21: =-C21+B21 -> #REF! | G21: =Budgets!#REF! -> #REF! | H21: =-G21+F21 -> #REF! | J21: ='Sales and Marketing'!#REF! -> #REF! | K21: =Budgets!C32 -> 0 | L21: =-K21+J21 -> #REF! | O21: =Budgets!D32 -> -776274.95 | P21: =-O21+N21 -> 776274.95 | S21: =Budgets!E32 -> -67100.447 | T21: =-S21+R21 -> 67100.447 | W21: =Budgets!F32 -> -76601.778 | X21: =-W21+V21 -> 76601.778 | AA21: =Budgets!G32 -> -61428.447 | AB21: =-AA21+Z21 -> 61428.447 | AE21: =Budgets!H32 -> -61428.447 | AF21: =-AE21+AD21 -> 61428.447 | AI21: =Budgets!I32 -> -64656.447 | AJ21: =-AI21+AH21 -> 64656.447 | AM21: =Budgets!J32 -> -102348.45 | AN21: =-AM21+AL21 -> 102348.45 | AQ21: =Budgets!K32 -> -50128.447 | AR21: =-AQ21+AP21 -> 50128.447 | AU21: =Budgets!L32 -> -101068.45 | AV21: =-AU21+AT21 -> 101068.45 | AX21: =B21+F21+J21 -> #REF! | AY21: =C21+G21+K21 -> #REF! | AZ21: =-AY21+AX21 -> #REF!
A22: Product development | C22: =Budgets!#REF! -> #REF! | D22: =-C22+B22 -> #REF! | G22: =Budgets!#REF! -> #REF! | H22: =-G22+F22 -> #REF! | J22: =Engineering!#REF! -> #REF! | K22: =Budgets!C34 -> 0 | L22: =-K22+J22 -> #REF! | O22: =Budgets!D34 -> -1530642.8 | P22: =-O22+N22 -> 1530642.8 | S22: =Budgets!E34 -> -158085.68 | T22: =-S22+R22 -> 158085.68 | W22: =Budgets!F34 -> -158085.68 | X22: =-W22+V22 -> 158085.68 | AA22: =Budgets!G34 -> -145438.56 | AB22: =-AA22+Z22 -> 145438.56 | AE22: =Budgets!H34 -> -145438.56 | AF22: =-AE22+AD22 -> 145438.56 | AI22: =Budgets!I34 -> -145438.56 | AJ22: =-AI22+AH22 -> 145438.56 | AM22: =Budgets!J34 -> -130264.61 | AN22: =-AM22+AL22 -> 130264.61 | AQ22: =Budgets!K34 -> -118115.12 | AR22: =-AQ22+AP22 -> 118115.12 | AU22: =Budgets!L34 -> -94009.988 | AV22: =-AU22+AT22 -> 94009.988 | AX22: =B22+F22+J22 -> #REF! | AY22: =C22+G22+K22 -> #REF! | AZ22: =-AY22+AX22 -> #REF!
A23: G&A | C23: =Budgets!#REF! -> #REF! | D23: =-C23+B23 -> #REF! | G23: =Budgets!#REF! -> #REF! | H23: =-G23+F23 -> #REF! | J23: ='G&A'!#REF! -> #REF! | K23: =Budgets!C36 -> 0 | L23: =-K23+J23 -> #REF! | O23: =Budgets!D36 -> -1123747.5 | P23: =-O23+N23 -> 1123747.5 | S23: =Budgets!E36 -> -138087.51 | T23: =-S23+R23 -> 138087.51 | W23: =Budgets!F36 -> -152538.35 | X23: =-W23+V23 -> 152538.35 | AA23: =Budgets!G36 -> -101057.43 | AB23: =-AA23+Z23 -> 101057.43 | AE23: =Budgets!H36 -> -99077.43 | AF23: =-AE23+AD23 -> 99077.43 | AI23: =Budgets!I36 -> -101651.43 | AJ23: =-AI23+AH23 -> 101651.43 | AM23: =Budgets!J36 -> -108365.67 | AN23: =-AM23+AL23 -> 108365.67 | AQ23: =Budgets!K36 -> -65441.171 | AR23: =-AQ23+AP23 -> 65441.171 | AU23: =Budgets!L36 -> -53583.211 | AV23: =-AU23+AT23 -> 53583.211 | AX23: =B23+F23+J23 -> #REF! | AY23: =C23+G23+K23 -> #REF! | AZ23: =-AY23+AX23 -> #REF!
A24: Product Support | C24: =Budgets!#REF! -> #REF! | D24: =-C24+B24 -> #REF! | G24: =Budgets!#REF! -> #REF! | H24: =-G24+F24 -> #REF! | J24: ='Product Support'!H52 -> 0 | K24: =Budgets!C38 -> 0 | L24: =-K24+J24 -> 0 | O24: =Budgets!D38 -> -305518.66 | P24: =-O24+N24 -> 305518.66 | S24: =Budgets!E38 -> -71824.116 | T24: =-S24+R24 -> 71824.116 | W24: =Budgets!F38 -> -71824.116 | X24: =-W24+V24 -> 71824.116 | AA24: =Budgets!G38 -> -71824.116 | AB24: =-AA24+Z24 -> 71824.116 | AE24: =Budgets!H38 -> -71824.116 | AF24: =-AE24+AD24 -> 71824.116 | AI24: =Budgets!I38 -> -81824.116 | AJ24: =-AI24+AH24 -> 81824.116 | AM24: =Budgets!J38 -> -71824.116 | AN24: =-AM24+AL24 -> 71824.116 | AQ24: =Budgets!K38 -> -71824.116 | AR24: =-AQ24+AP24 -> 71824.116 | AU24: =Budgets!L38 -> -68252.991 | AV24: =-AU24+AT24 -> 68252.991 | AX24: =B24+F24+J24 -> 0 | AY24: =C24+G24+K24 -> #REF! | AZ24: =-AY24+AX24 -> #REF!
A25: Total Opex | B25: =SUM(B21:B23) -> 0 | C25: =SUM(C21:C23) -> #REF! | D25: =SUM(D21:D23) -> #REF! | F25: =SUM(F21:F23) -> 0 | G25: =SUM(G21:G23) -> #REF! | H25: =SUM(H21:H23) -> #REF! | J25: =SUM(J21:J23) -> #REF! | K25: =SUM(K21:K23) -> 0 | L25: =SUM(L21:L23) -> #REF! | N25: =SUM(N21:N23) -> 0 | O25: =SUM(O21:O23) -> -3430665.2 | P25: =SUM(P21:P23) -> 3430665.2 | R25: =SUM(R21:R23) -> 0 | S25: =SUM(S21:S23) -> -363273.63 | T25: =SUM(T21:T23) -> 363273.63 | V25: =SUM(V21:V23) -> 0 | W25: =SUM(W21:W23) -> -387225.8 | X25: =SUM(X21:X23) -> 387225.8 | Z25: =SUM(Z21:Z23) -> 0 | AA25: =SUM(AA21:AA23) -> -307924.43 | AB25: =SUM(AB21:AB23) -> 307924.43 | AD25: =SUM(AD21:AD23) -> 0 | AE25: =SUM(AE21:AE23) -> -305944.43 | AF25: =SUM(AF21:AF23) -> 305944.43 | AH25: =SUM(AH21:AH23) -> 0 | AI25: =SUM(AI21:AI23) -> -311746.43 | AJ25: =SUM(AJ21:AJ23) -> 311746.43 | AL25: =SUM(AL21:AL23) -> 0 | AM25: =SUM(AM21:AM23) -> -340978.73 | AN25: =SUM(AN21:AN23) -> 340978.73 | AP25: =SUM(AP21:AP23) -> 0 | AQ25: =SUM(AQ21:AQ23) -> -233684.74 | AR25: =SUM(AR21:AR23) -> 233684.74 | AT25: =SUM(AT21:AT23) -> 0 | AU25: =SUM(AU21:AU23) -> -248661.65 | AV25: =SUM(AV21:AV23) -> 248661.65 | AX25: =SUM(AX21:AX24) -> #REF! | AY25: =SUM(AY21:AY24) -> #REF! | AZ25: =SUM(AZ21:AZ23) -> #REF!
A26: EBITDA | B26: =B18-B25 -> #REF! | C26: =C18-C25 -> #REF! | D26: =D18-D25 -> #REF! | F26: =F18-F25 -> 0 | G26: =G18-G25 -> #REF! | H26: =H18-H25 -> #REF! | J26: =J25+J18 -> #REF! | K26: =K18+K25 -> -5000 | L26: =J26-K26 -> #REF! | N26: =N18-N25 -> 0 | O26: =O18-O25 -> 4028823.2 | P26: =P18-P25 -> -2832507.2 | R26: =R18-R25 -> 0 | S26: =S18-S25 -> 439187.55 | T26: =T18-T25 -> -287359.71 | V26: =V18-V25 -> 0 | W26: =W18-W25 -> 430350.47 | X26: =X18-X25 -> -344101.14 | Z26: =Z18-Z25 -> 0 | AA26: =AA18-AA25 -> 350091.1 | AB26: =AB18-AB25 -> -265757.77 | AD26: =AD18-AD25 -> 0 | AE26: =AE18-AE25 -> 352277.77 | AF26: =AF18-AF25 -> -259611.1 | AH26: =AH18-AH25 -> 0 | AI26: =AI18-AI25 -> 393313.1 | AJ26: =AJ18-AJ25 -> -230179.77 | AL26: =AL18-AL25 -> 0 | AM26: =AM18-AM25 -> 433562.06 | AN26: =AN18-AN25 -> -248395.4 | AP26: =AP18-AP25 -> 0 | AQ26: =AQ18-AQ25 -> 397751.4 | AR26: =AR18-AR25 -> -69618.069 | AT26: =AT18-AT25 -> 0 | AU26: =AU18-AU25 -> 435744.98 | AV26: =AV18-AV25 -> -61578.312 | AX26: =AX18+AX25 -> #REF! | AY26: =AY18+AY25 -> #REF! | AZ26: =AX26-AY26 -> #REF!
A28: Other Income / expenditure
A29: Miscellaneous Costs | D29: =C29-B29 -> 0 | H29: =G29-F29 -> 0 | L29: =K29-J29 -> 0 | O29: 0 | S29: =Budgets!#REF! -> #REF! | W29: 0 | AA29: 0 | AE29: 0 | AM29: 0 | AP29: 0 | AQ29: 0 | AR29: 0 | AU29: 0 | AV29: =AT29 -> 0 | AX29: ='Trial Balance'!L152+'Trial Balance'!L181 -> 0 | AY29: =C29+G29+K29 -> 0 | AZ29: =AX29-AY29 -> 0
A30: Total Other income / expenditure | B30: =SUM(B29) -> 0 | C30: =SUM(C29) -> 0 | D30: =SUM(D29) -> 0 | F30: =SUM(F29) -> 0 | G30: =SUM(G29) -> 0 | H30: =SUM(H29) -> 0 | J30: =SUM(J29) -> 0 | K30: =SUM(K29) -> 0 | L30: =SUM(L29) -> 0 | N30: =SUM(N29) -> 0 | O30: =SUM(O29) -> 0 | P30: =SUM(P29) -> 0 | R30: =SUM(R29) -> 0 | S30: =SUM(S29) -> #REF! | T30: =SUM(T29) -> 0 | V30: =SUM(V29) -> 0 | W30: =SUM(W29) -> 0 | X30: =SUM(X29) -> 0 | Z30: =SUM(Z29) -> 0 | AA30: =SUM(AA29) -> 0 | AB30: =SUM(AB29) -> 0 | AD30: =SUM(AD29) -> 0 | AE30: =SUM(AE29) -> 0 | AF30: =SUM(AF29) -> 0 | AH30: =SUM(AH29) -> 0 | AI30: =SUM(AI29) -> 0 | AJ30: =SUM(AJ29) -> 0 | AL30: =SUM(AL29) -> 0 | AM30: =SUM(AM29) -> 0 | AN30: =SUM(AN29) -> 0 | AP30: =SUM(AP29) -> 0 | AQ30: =SUM(AQ29) -> 0 | AR30: =SUM(AR29) -> 0 | AT30: =SUM(AT29) -> 0 | AU30: =SUM(AU29) -> 0 | AV30: =SUM(AV29) -> 0 | AX30: =SUM(AX29) -> 0 | AY30: =SUM(AY29) -> 0 | AZ30: =SUM(AZ29) -> 0
A32: Exceptional costs
A33: Interest | D33: =C33-B33 -> 0 | H33: =G33-F33 -> 0 | L33: =K33-J33 -> 0 | P33: =O33-N33 -> 0 | S33: =Budgets!E48 -> 15669.72 | T33: =S33-R33 -> 15669.72 | X33: =W33-V33 -> 0 | AB33: =AA33-Z33 -> 0 | AF33: =AE33-AD33 -> 0 | AJ33: =AI33-AH33 -> 0 | AN33: =AM33-AL33 -> 0 | AQ33: 0 | AR33: =AQ33-AP33 -> 0 | AV33: =AU33-AT33 -> 0 | AX33: ='Trial Balance'!L144 -> 0 | AY33: =C33+G33+K33 -> 0 | AZ33: =AX33-AY33 -> 0
A34: Depreciation | C34: =Budgets!#REF! -> #REF! | D34: =C34-B34 -> #REF! | G34: =Budgets!#REF! -> #REF! | H34: =G34-F34 -> #REF! | K34: =Budgets!C48 -> 0 | L34: =K34-J34 -> 0 | O34: =Budgets!D48 -> 33794.64 | P34: =O34-N34 -> 33794.64 | S34: =Budgets!E49 -> -2259.84 | T34: =S34-R34 -> -2259.84 | X34: =W34-V34 -> 0 | AB34: =AA34-Z34 -> 0 | AF34: =AE34-AD34 -> 0 | AJ34: =AI34-AH34 -> 0 | AN34: =AM34-AL34 -> 0 | AQ34: 0 | AR34: =AQ34-AP34 -> 0 | AV34: =AU34-AT34 -> 0 | AX34: ='Trial Balance'!L136+'Trial Balance'!L137+'Trial Balance'!L138 -> 0 | AY34: =C34+G34+K34 -> #REF! | AZ34: =AX34-AY34 -> #REF!
A35: Amortisaion | D35: =C35-B35 -> 0 | H35: =G35-F35 -> 0 | L35: =K35-J35 -> 0 | P35: =O35-N35 -> 0 | S35: =Budgets!E50 -> 0 | T35: =S35-R35 -> 0 | X35: =W35-V35 -> 0 | AB35: =AA35-Z35 -> 0 | AF35: =AE35-AD35 -> 0 | AJ35: =AI35-AH35 -> 0 | AN35: =AM35-AL35 -> 0 | AQ35: 0 | AR35: =AQ35-AP35 -> 0 | AV35: =AU35-AT35 -> 0 | AX35: =B35+F35+J35 -> 0 | AY35: =C35+G35+K35 -> 0 | AZ35: =AX35-AY35 -> 0
A36: Operating Profit / (Loss) | B36: =B26+B30-B33-B34-B35 -> #REF! | C36: =C26+C30-C33-C34-C35 -> #REF! | D36: =D26+D30-D33-D34-D35 -> #REF! | F36: =F26+F30-F33-F34-F35 -> 0 | G36: =G26+G30-G33-G34-G35 -> #REF! | H36: =H26+H30-H33-H34-H35 -> #REF! | J36: =J26+J30-J33-J34-J35 -> #REF! | K36: =K26+K30-K33-K34-K35 -> -5000 | L36: =L26+L30-L33-L34-L35 -> #REF! | N36: =N26+N30-N33-N34-N35 -> 0 | O36: =O26+O30-O33-O34-O35 -> 3995028.5 | P36: =P26+P30-P33-P34-P35 -> -2866301.8 | R36: =R26+R30-R33-R34-R35 -> 0 | S36: =S26+S30-S33-S34-S35 -> #REF! | T36: =T26+T30-T33-T34-T35 -> -300769.59 | V36: =V26+V30-V33-V34-V35 -> 0 | W36: =W26+W30-W33-W34-W35 -> 430350.47 | X36: =X26+X30-X33-X34-X35 -> -344101.14 | Z36: =Z26+Z30-Z33-Z34-Z35 -> 0 | AA36: =AA26+AA30-AA33-AA34-AA35 -> 350091.1 | AB36: =AB26+AB30-AB33-AB34-AB35 -> -265757.77 | AD36: =AD26+AD30-AD33-AD34-AD35 -> 0 | AE36: =AE26+AE30-AE33-AE34-AE35 -> 352277.77 | AF36: =AF26+AF30-AF33-AF34-AF35 -> -259611.1 | AH36: =AH26+AH30-AH33-AH34-AH35 -> 0 | AI36: =AI26+AI30-AI33-AI34-AI35 -> 393313.1 | AJ36: =AJ26+AJ30-AJ33-AJ34-AJ35 -> -230179.77 | AL36: =AL26+AL30-AL33-AL34-AL35 -> 0 | AM36: =AM26+AM30-AM33-AM34-AM35 -> 433562.06 | AN36: =AN26+AN30-AN33-AN34-AN35 -> -248395.4 | AP36: =AP26+AP30-AP33-AP34-AP35 -> 0 | AQ36: =AQ26+AQ30-AQ33-AQ34-AQ35 -> 397751.4 | AR36: =AR26+AR30-AR33-AR34-AR35 -> -69618.069 | AT36: =AT26+AT30-AT33-AT34-AT35 -> 0 | AU36: =AU26+AU30-AU33-AU34-AU35 -> 435744.98 | AV36: =AV26+AV30-AV33-AV34-AV35 -> -61578.312 | AX36: =AX26+SUM(AX30:AX35) -> #REF! | AY36: =AY26+SUM(AY30:AY35) -> #REF! | AZ36: =AX36-AY36 -> #REF!
A37: Financing Costs | S37: =Budgets!E47 -> 0 | W37: 0 | AA37: 0 | AE37: 0 | AI37: 0 | AM37: 0 | AQ37: 0 | AU37: 0
A38: Tax (R&D credit -Cr) | C38: 0 | G38: 0 | K38: 0 | O38: 0 | AV38: =AT38-AU38 -> 0 | AX38: ='Trial Balance'!L180 -> 0 | AY38: =SUM(Budgets!C53:J53) -> 436920 | AZ38: =AX38-AY38 -> -436920
A39: Profit / (Loss) after Tax | B39: =SUM(B36:B38) -> #REF! | C39: =SUM(C36:C38) -> #REF! | D39: =SUM(D36:D38) -> #REF! | F39: =SUM(F36:F38) -> 0 | G39: =SUM(G36:G38) -> #REF! | H39: =SUM(H36:H38) -> #REF! | J39: =SUM(J36:J38) -> #REF! | K39: =SUM(K36:K38) -> -5000 | L39: =SUM(L36:L38) -> #REF! | N39: =SUM(N36:N38) -> 0 | O39: =SUM(O36:O38) -> 3995028.5 | P39: =SUM(P36:P38) -> -2866301.8 | R39: =SUM(R36:R38) -> 0 | S39: =SUM(S36:S38) -> #REF! | T39: =SUM(T36:T38) -> -300769.59 | V39: =SUM(V36:V38) -> 0 | W39: =SUM(W36:W38) -> 430350.47 | X39: =SUM(X36:X38) -> -344101.14 | Z39: =SUM(Z36:Z38) -> 0 | AA39: =SUM(AA36:AA38) -> 350091.1 | AB39: =SUM(AB36:AB38) -> -265757.77 | AD39: =SUM(AD36:AD38) -> 0 | AE39: =SUM(AE36:AE38) -> 352277.77 | AF39: =SUM(AF36:AF38) -> -259611.1 | AH39: =SUM(AH36:AH38) -> 0 | AI39: =SUM(AI36:AI38) -> 393313.1 | AJ39: =SUM(AJ36:AJ38) -> -230179.77 | AL39: =SUM(AL36:AL38) -> 0 | AM39: =SUM(AM36:AM38) -> 433562.06 | AN39: =SUM(AN36:AN38) -> -248395.4 | AP39: =SUM(AP36:AP38) -> 0 | AQ39: =SUM(AQ36:AQ38) -> 397751.4 | AR39: =SUM(AR36:AR38) -> -69618.069 | AT39: =SUM(AT36:AT38) -> 0 | AU39: =SUM(AU36:AU38) -> 435744.98 | AV39: =SUM(AV36:AV38) -> -61578.312 | AX39: =AX36+AX38 -> #REF! | AY39: =AY36+AY38 -> #REF! | AZ39: =AZ36+AZ38 -> #REF!
A41: Cash | B41: 200422.14 | C41: 251509.95 | D41: =C41-B41 -> 51087.812 | F41: ='Balance Sheet'!G14 -> 2156488 | G41: 212909.99 | H41: 212909.99 | J41: 139341.32 | K41: 211663.73 | L41: 72322.414 | N41: 259016.67 | O41: 5086231.1 | P41: 4827214.4 | R41: 150666.21 | S41: =Budgets!G75 -> 525369.07 | T41: =R41-S41 -> -374702.85 | V41: 96578.008 | W41: 1597244.7 | X41: -1500666.7 | Z41: 96578.008 | AA41: 1597244.7 | AB41: -1500666.7 | AD41: 1537111.3 | AE41: 1365928.2 | AF41: 171183.15 | AH41: 1338397.8 | AI41: 1401100 | AJ41: -62702.227 | AL41: 1225061.8 | AM41: 1294003 | AN41: -68941.235 | AP41: ='Balance Sheet'!F14 -> 0 | AQ41: ='Balance Sheet'!G14 -> 2156488 | AR41: ='Balance Sheet'!H14 -> 0 | AX41: =AL41 -> 1225061.8 | AY41: 1156604 | AZ41: -62702.227
A42: Average Head Count
B45: 44197 | C45: 44197 | D45: 44197 | F45: 44228 | G45: 44228 | H45: 44228 | J45: 44256 | K45: 44256 | L45: 44256 | N45: 44287 | O45: 44287 | P45: 44287 | R45: 44317 | S45: 44317 | T45: 44317 | V45: 44348 | W45: 44348 | X45: 44348 | Z45: 44348 | AA45: 44348 | AB45: 44348 | AD45: 44409 | AE45: 44409 | AF45: 44409 | AH45: 44440 | AI45: 44440 | AJ45: 44440 | AL45: 44440 | AM45: 44440 | AN45: 44440 | AP45: 44440 | AQ45: 44440 | AR45: 44440 | AX45: 44440 | AY45: 44440 | AZ45: 44440
B46: Actual | C46: Budget | D46: Variance | F46: Actual | G46: Budget | H46: Variance | J46: Actual | K46: Budget | L46: Variance | N46: Actual | O46: Budget | P46: Variance | R46: Actual | S46: Budget | T46: Variance | V46: Actual | W46: Budget | X46: Variance | Z46: Actual | AA46: Budget | AB46: Variance | AD46: Actual | AE46: Budget | AF46: Variance | AH46: Actual | AI46: Reforecast | AJ46: Variance | AL46: Actual | AM46: Reforecast | AN46: Variance | AP46: Actual | AQ46: Reforecast | AR46: Variance | AX46: Actual | AY46: Budget | AZ46: Variance
A47: Capitalised Dev Costs
A48: Staff costs | D48: =C48-B48 -> 0 | F48: =Engineering!#REF!+Engineering!#REF! -> #REF! | G48: 47065.322 | H48: -5967.9007 | J48: =Engineering!#REF!+Engineering!#REF!+Engineering!#REF! -> #REF! | K48: 47065.322 | L48: -6088.6821 | N48: =Engineering!D36+Engineering!D39+Engineering!#REF! -> #REF! | O48: 51691.989 | P48: 1521.4265 | R48: =Engineering!E36+Engineering!E39+Engineering!#REF! -> #REF! | S48: =Budgets!#REF! -> #REF! | T48: =S48-R48 -> #REF! | V48: 41936.59 | W48: 56340.9 | X48: 14404.31 | Z48: 41936.59 | AA48: 56340.9 | AB48: 14404.31 | AD48: 94530.12 | AE48: 126195.3 | AF48: 31665.18 | AH48: 94530.12 | AI48: 174012.3 | AJ48: 31665.18 | AL48: 94530.12 | AM48: 174012.3 | AN48: 31665.18 | AP48: 94530.12 | AQ48: =[1]Budgets!P49+[1]Budgets!Q49 -> 0 | AR48: 31665.18 | AX48: =V48+R48+N48+J48+F48+B48+AD48 -> #REF! | AY48: =SUM(Budgets!#REF!) -> #REF! | AZ48: =AY48-AX48 -> #REF!
A49: Other | D49: =C49-B49 -> 0 | F49: =Engineering!#REF! -> #REF! | G49: 1500 | H49: 1472.86 | J49: =Engineering!#REF! -> #REF! | K49: 1500 | L49: -474.0943 | N49: =Engineering!D46 -> 0 | O49: 1500 | P49: 1500 | R49: =Engineering!E46 -> 0 | S49: =Budgets!#REF! -> #REF! | T49: =S49-R49 -> #REF! | V49: 4026.18 | W49: 1500 | X49: -2526.18 | Z49: 4026.18 | AA49: 1500 | AB49: -2526.18 | AD49: 0 | AE49: 4000 | AF49: 4000 | AH49: 0 | AI49: 4000 | AJ49: 4000 | AL49: 0 | AM49: 4000 | AN49: 4000 | AP49: 0 | AQ49: =[1]Budgets!P50+[1]Budgets!Q50 -> 0 | AR49: 4000 | AX49: =V49+R49+N49+J49+F49+B49+AD49 -> #REF! | AY49: =SUM(Budgets!#REF!) -> #REF! | AZ49: =AY49-AX49 -> #REF!
B50: =SUM(B48:B49) -> 0 | C50: =SUM(C48:C49) -> 0 | D50: =SUM(D48:D49) -> 0 | F50: =SUM(F48:F49) -> #REF! | G50: 48565.322 | H50: -4495.0407 | J50: 55128.098 | K50: 48565.322 | L50: -6562.7764 | N50: 50170.562 | O50: 53191.989 | P50: 3021.4265 | R50: 30849.151 | S50: =SUM(S48:S49) -> #REF! | T50: =SUM(T48:T49) -> #REF! | V50: 45962.77 | W50: 57840.9 | X50: 11878.13 | Z50: 45962.77 | AA50: 57840.9 | AB50: 11878.13 | AD50: 94530.12 | AE50: 130195.3 | AF50: 35665.18 | AH50: 94530.12 | AI50: 178012.3 | AJ50: 35665.18 | AL50: 94530.12 | AM50: 178012.3 | AN50: 35665.18 | AP50: 94530.12 | AQ50: =SUM(AQ48:AQ49) -> 0 | AR50: 35665.18 | AX50: =SUM(AX48:AX49) -> #REF! | AY50: =SUM(AZ48:AZ49) -> #REF! | AZ50: =SUM(AZ48:AZ49) -> #REF!
A55: Total P&L | B55: =B39 -> #REF! | N55: =N39 -> 0 | R55: =R39 -> 0 | V55: -39456.849 | AD55: -92999.199 | AH55: =SUM('Trial Balance'!K6:K75)-'P&L'!AH39-'P&L'!AD39-'P&L'!V39-'P&L'!R39-'P&L'!N39-'P&L'!J39-'P&L'!F39-'P&L'!B39 -> #REF! | AL55: =AX39-'P&L'!AL39-'P&L'!AH39-'P&L'!AD39-'P&L'!V39-'P&L'!R39-'P&L'!N39-'P&L'!J39-'P&L'!F39-'P&L'!B39 -> #REF!
AL56: =AL39-'Trial Balance'!M76 -> #VALUE!
A57: P&L check | B57: =SUM('Trial Balance'!K6:K43) -> 0 | N57: =-'Trial Balance'!M41 -> #VALUE! | R57: =-'Trial Balance'!M41 -> #VALUE! | V57: -39456.163 | AD57: -93302.286 | AL57: =AL56-AH35 -> #VALUE!
B59: =B55+B57 -> #REF! | C59: difference reported in Feb | N59: =N57-N55 -> #VALUE! | R59: =R55-R57 -> #VALUE! | V59: -0.68656207 | AD59: 303.08681

Sheet Cashflow
A1: FHL Cashflow
A2: Year End 31 Dec 2022
A3: Cashflow Forecast - Monthly
E4: 2023
D5: 44835 | E5: 44866 | F5: 44896 | G5: 44927 | H5: 44958 | I5: 44986 | J5: 45017 | K5: 45047 | L5: 45078 | M5: 45108 | N5: 45139 | O5: 45170 | P5: 45200
A6: Cash Flow from Operations
A7: Operating Profit/(Loss) | G7: =Budgets!C56 -> 0 | H7: =Budgets!D56 -> -3201306.6 | I7: =Budgets!E56 -> -357279.07 | J7: =Budgets!F56 -> -435792.42 | K7: =Budgets!G56 -> -374122.46 | L7: =Budgets!H56 -> -372642.46 | M7: =Budgets!I56 -> 69875.544 | N7: =Budgets!J56 -> -381176.75 | ... P7: =Budgets!L56 -> -250788.54
A8: add back Depreciation & Amortisation | G8: =Budgets!C49+Budgets!C50 -> 0 | H8: =Budgets!D49+Budgets!D50 -> -17451.72 | I8: =Budgets!E49+Budgets!E50 -> -2259.84 | J8: =Budgets!F49+Budgets!F50 -> 0 | K8: =Budgets!G49+Budgets!G50 -> 0 | L8: =Budgets!H49+Budgets!H50 -> 0 | M8: =Budgets!I49+Budgets!I50 -> 0 | N8: =Budgets!J49+Budgets!J50 -> 0 | ... P8: =Budgets!L49+Budgets!L50 -> 0
A9: add back interest | G9: =Budgets!C48 -> 0 | H9: =Budgets!D48 -> 33794.64 | I9: =Budgets!E48 -> 15669.72 | J9: =Budgets!F48 -> 0 | K9: =Budgets!G48 -> 0 | L9: =Budgets!H48 -> 0 | M9: =Budgets!I48 -> 0 | N9: =Budgets!J48 -> 0 | ... P9: =Budgets!L48 -> 0
A10: Dec/(inc) in Trade Debtors | G10: ='All In One'!C11 -> 0 | H10: ='All In One'!E11 -> 383396 | I10: ='All In One'!G11 -> -22120.92 | J10: ='All In One'!I11 -> 166042 | K10: ='All In One'!K11 -> 11536 | L10: ='All In One'!M11 -> -8000 | M10: ='All In One'!O11 -> -26900 | N10: ='All In One'!Q11 -> -27500 | O10: ='All In One'!S11 -> -40000 | P10: ='All In One'!U11 -> -34500
A11: Dec/(inc) in Other Debtors | G11: ='All In One'!C12 -> 0 | H11: ='All In One'!E12 -> -495861.96 | I11: ='All In One'!G12 -> 112786.08 | J11: ='All In One'!I12 -> 256861.68 | K11: ='All In One'!K12 -> 119814.2 | L11: ='All In One'!M12 -> -6400 | M11: ='All In One'!O12 -> -6400 | N11: ='All In One'!Q12 -> -6400 | O11: ='All In One'!S12 -> -6400 | P11: ='All In One'!U12 -> -28000
A12: Dec/(inc) in VAT debtor | G12: ='All In One'!C13 -> 0 | H12: ='All In One'!E13 -> -38857.632 | I12: ='All In One'!G13 -> -4983.2496 | J12: ='All In One'!I13 -> -4471.8673 | K12: ='All In One'!K13 -> 39538.882 | L12: ='All In One'!M13 -> -4302 | M12: ='All In One'!O13 -> -4764 | N12: ='All In One'!Q13 -> 9323.8673 | O12: ='All In One'!S13 -> -3964 | P12: ='All In One'!U13 -> -3062
A13: Inc/(Dec) in Trade Creditors | G13: ='All In One'!C16 -> 0 | H13: ='All In One'!E16 -> -265593.47 | I13: ='All In One'!G16 -> 33417.128 | J13: ='All In One'!I16 -> -6061.6829 | K13: ='All In One'!K16 -> -33404.445 | L13: ='All In One'!M16 -> 5304 | M13: ='All In One'!O16 -> 12396 | N13: ='All In One'!Q16 -> 37044 | O13: ='All In One'!S16 -> -50064 | P13: ='All In One'!U16 -> 74112
A14: Inc/(Dec) in Deferred income | G14: ='All In One'!C17 -> 0 | H14: ='All In One'!E17 -> 0 | I14: ='All In One'!G17 -> 0 | J14: ='All In One'!I17 -> 0 | K14: ='All In One'!K17 -> 0 | L14: ='All In One'!M17 -> 0 | M14: ='All In One'!O17 -> 0 | N14: ='All In One'!Q17 -> 0 | O14: ='All In One'!S17 -> 0 | P14: ='All In One'!U17 -> 0
A15: Inc/(Dec) in Other creditors | G15: ='All In One'!C18 -> 0 | H15: ='All In One'!E18 -> 372248.63 | I15: ='All In One'!G18 -> 4983.2496 | J15: ='All In One'!I18 -> 4471.8673 | K15: ='All In One'!K18 -> -339538.88 | L15: ='All In One'!M18 -> 104302 | M15: ='All In One'!O18 -> 104764 | N15: ='All In One'!Q18 -> 196676.13 | O15: ='All In One'!S18 -> 3964 | P15: ='All In One'!U18 -> 3062
A16: Net Cash Flow from Operations | D16: =SUM(D7:D15) -> 0 | G16: =SUM(G7:G15) -> 0 | H16: =SUM(H7:H15) -> -3229632.1 | I16: =SUM(I7:I15) -> -219786.9 | J16: =SUM(J7:J15) -> -18950.423 | K16: =SUM(K7:K15) -> -576176.7 | L16: =SUM(L7:L15) -> -281738.46 | M16: =SUM(M7:M15) -> 148971.54 | N16: =SUM(N7:N15) -> -172032.75 | ... P16: =SUM(P7:P15) -> -239176.54
A18: Cash flows from investing activities
A19: Purchase of Intangible assets | G19: =-Engineering!#REF! -> #REF! | H19: =-Engineering!D27 -> -1530642.8 | I19: =-Engineering!E27 -> -158085.68 | J19: =-Engineering!F27 -> -158085.68 | K19: =-Engineering!G27 -> -145438.56 | L19: =-Engineering!H27 -> -145438.56 | M19: =-Engineering!I27 -> -145438.56 | N19: =-Engineering!J27 -> -130264.61 | O19: =-Engineering!K27 -> -118115.12 | P19: =-Engineering!L27 -> -94009.988
A20: Purchase of Tangible assets | G20: =-#REF! -> #REF! | H20: =-#REF! -> #REF! | I20: =-#REF! -> #REF! | J20: =-#REF! -> #REF! | K20: =-#REF! -> #REF! | L20: =-#REF! -> #REF! | M20: =-#REF! -> #REF! | N20: =-#REF! -> #REF! | ... P20: =-#REF! -> #REF!
A21: Net Cash Flow from Investing | D21: =SUM(D19:D20) -> 0 | G21: =SUM(G19:G20) -> #REF! | H21: =SUM(H19:H20) -> #REF! | I21: =SUM(I19:I20) -> #REF! | J21: =SUM(J19:J20) -> #REF! | K21: =SUM(K19:K20) -> #REF! | L21: =SUM(L19:L20) -> #REF! | M21: =SUM(M19:M20) -> #REF! | N21: =SUM(N19:N20) -> #REF! | ... P21: =SUM(P19:P20) -> #REF!
A23: Cash flows from financing activities
A24: Issue of ordinary share capital | J24: 1000000
A25: New loans | G25: -857 | H25: -857 | I25: -857 | J25: -857 | K25: -857 | L25: -857 | M25: -857 | N25: -857 | O25: -857 | P25: -857
A26: Cost of fundraising | G26: -2500 | H26: -2500 | I26: -2500 | J26: -40000
A27: Repayment of borrowings
A28: Net Cash Flow from Financing | D28: =SUM(D24:D27) -> 0 | G28: =SUM(G24:G27) -> -3357 | H28: =SUM(H24:H27) -> -3357 | I28: =SUM(I24:I27) -> -3357 | J28: =SUM(J24:J27) -> 959143 | K28: =SUM(K24:K27) -> -857 | L28: =SUM(L24:L27) -> -857 | M28: =SUM(M24:M27) -> -857 | N28: =SUM(N24:N27) -> -857 | ... P28: =SUM(P24:P27) -> -857
A30: Net Cash Inflow/(Outflow) in period | D30: =D16+D21+D28 -> 0 | G30: =G16+G21+G28 -> #REF! | H30: =H16+H21+H28 -> #REF! | I30: =I16+I21+I28 -> #REF! | J30: =J16+J21+J28 -> #REF! | K30: =K16+K21+K28 -> #REF! | L30: =L16+L21+L28 -> #REF! | M30: =M16+M21+M28 -> #REF! | N30: =N16+N21+N28 -> #REF! | ... P30: =P16+P21+P28 -> #REF!
A31: Opening Cash Balance | G31: =F32 -> 721186 | H31: =G32 -> #REF! | I31: =H32 -> #REF! | J31: =I32 -> #REF! | K31: =J32 -> #REF! | L31: =K32 -> #REF! | M31: =L32 -> #REF! | N31: =M32 -> #REF! | ... P31: =O32 -> #REF!
A32: Closing Cash Balance | D32: =SUM(D30:D31) -> 0 | F32: 721186 | G32: =SUM(G30:G31) -> #REF! | H32: =SUM(H30:H31) -> #REF! | I32: =SUM(I30:I31) -> #REF! | J32: =SUM(J30:J31) -> #REF! | K32: =SUM(K30:K31) -> #REF! | L32: =SUM(L30:L31) -> #REF! | M32: =SUM(M30:M31) -> #REF! | N32: =SUM(N30:N31) -> #REF! | ... P32: =SUM(P30:P31) -> #REF!
D36: 2022
D37: Actual | E37: Actual | F37: Actual | G37: Actual | H37: Actual | I37: Actual | J37: Actual | K37: Actual | L37: Actual | M37: Actual | N37: Actual | O37: Actual
C38: 44166 | D38: 44866 | E38: 44896 | F38: 44927 | G38: 44958 | H38: 44986 | I38: 45017 | J38: 45047 | K38: 45078 | L38: 45108 | M38: 45139 | N38: 45170 | O38: 45200
A39: Cash Flow from Operations
A40: Operating Profit/(Loss)
A41: add back Depreciation & Amortisation
A42: add back interest
A43: Dec/(inc) in Trade Debtors
A44: Dec/(inc) in Other Debtors
A45: Dec/(inc) in VAT debtor
A46: Dec/(inc) in Prepayment
A47: Inc/(Dec) in Trade Creditors
A48: Inc/(Dec) in Accruals
A49: Inc/(Dec) in Deferred Income
A50: Inc/(Dec) in PAYE Creditors
... A52: Dec/(inc) in R&D Tax receivable
A53: Net Cash Flow from Operations | D53: =SUM(D40:D52) -> 0 | E53: =SUM(E40:E52) -> 0 | F53: =SUM(F40:F52) -> 0 | G53: =SUM(G40:G52) -> 0 | H53: =SUM(H40:H52) -> 0 | I53: =SUM(I40:I52) -> 0 | K53: =SUM(K40:K52) -> 0 | L53: =SUM(L40:L52) -> 0 | M53: =SUM(M40:M52) -> 0 | N53: =SUM(N40:N52) -> 0 | O53: =SUM(O40:O52) -> 0
A55: Cash flows from investing activities
A56: Purchase of Intangible assets
A57: Purchase of Tangible assets
A58: Net Cash Flow from Investing | D58: =SUM(D56:D57) -> 0 | E58: =SUM(E56:E57) -> 0 | F58: =SUM(F56:F57) -> 0 | G58: =SUM(G56:G57) -> 0 | H58: =SUM(H56:H57) -> 0 | I58: =SUM(I56:I57) -> 0 | K58: =SUM(K56:K57) -> 0 | L58: =SUM(L56:L57) -> 0 | M58: =SUM(M56:M57) -> 0 | N58: =SUM(N56:N57) -> 0 | O58: =SUM(O56:O57) -> 0
A60: Cash flows from financing activities
A61: Issue of ordinary share capital
A62: New loans
A64: Repayment of borrowings
A65: Net Cash Flow from Financing | D65: =SUM(D61:D64) -> 0 | E65: =SUM(E61:E64) -> 0 | F65: =SUM(F61:F64) -> 0 | G65: =SUM(G61:G64) -> 0 | H65: =SUM(H61:H64) -> 0 | I65: =SUM(I61:I64) -> 0 | K65: =SUM(K61:K64) -> 0 | L65: =SUM(L61:L64) -> 0 | M65: =SUM(M61:M64) -> 0 | N65: =SUM(N61:N64) -> 0 | O65: =SUM(O61:O64) -> 0
A67: Net Cash Inflow/(Outflow) in period
A68: Opening Cash Balance
A69: Closing Cash Balance | D69: =SUM(D67:D68) -> 0 | E69: =SUM(E67:E68) -> 0 | F69: =SUM(F67:F68) -> 0 | G69: =SUM(G67:G68) -> 0 | H69: =SUM(H67:H68) -> 0 | I69: =SUM(I67:I68) -> 0 | K69: =SUM(K67:K68) -> 0 | L69: =SUM(L67:L68) -> 0 | M69: =SUM(M67:M68) -> 0 | N69: =SUM(N67:N68) -> 0 | O69: =SUM(O67:O68) -> 0
A76: Budget
A78: Simple cashflow | D78: 44866 | E78: 44896 | F78: 44927 | G78: 44958 | H78: 44986 | I78: 45017 | J78: 45047 | K78: 45078 | L78: 45108 | M78: 45139 | N78: 45170 | O78: 45200
A79: Opening cash SEL | D79: 259236 | E79: =D85 -> #REF! | F79: =E85 -> #REF! | G79: =F85 -> #REF! | H79: =G85 -> #REF! | I79: =H85 -> #REF! | J79: =I85 -> #REF! | K79: =J85 -> #REF! | L79: =K85 -> #REF! | ... O79: =N85 -> #REF!
A81: Sales (+60 days) | D81: 250000 | E81: 250000 | F81: =Budgets!#REF! -> #REF! | G81: =Budgets!#REF! -> #REF! | H81: =Budgets!C6 -> 0 | I81: =Budgets!D6 -> 598158 | J81: =Budgets!E6 -> 75913.92 | K81: =Budgets!F6 -> 32708 | L81: =Budgets!G6 -> 8000 | M81: =Budgets!H6 -> 8000 | N81: =Budgets!I6 -> 34900 | O81: =Budgets!J6 -> 35500
A82: COGS (+30 days) | D82: =Budgets!#REF! -> #REF! | E82: =Budgets!#REF! -> #REF! | F82: =Budgets!C22 -> 0 | G82: =Budgets!D22 -> -79623.72 | H82: =Budgets!E22 -> -11505.12 | I82: =Budgets!F22 -> -9450.5004 | J82: =Budgets!G22 -> 0 | K82: =Budgets!H22 -> 0 | L82: =Budgets!I22 -> -5000 | M82: =Budgets!J22 -> 0 | ... O82: =Budgets!L22 -> 0
A83: Salaries and other costs (in month) | D83: =Budgets!#REF!+Budgets!#REF!+Budgets!#REF! -> #REF! | E83: =Budgets!#REF!+Budgets!#REF!+Budgets!#REF! -> #REF! | F83: =Budgets!C32+Budgets!C36+Budgets!C38 -> 0 | G83: =Budgets!D32+Budgets!D36+Budgets!D38 -> -2205541.1 | H83: =Budgets!E32+Budgets!E36+Budgets!E38 -> -277012.07 | I83: =Budgets!F32+Budgets!F36+Budgets!F38 -> -300964.24 | J83: =Budgets!G32+Budgets!G36+Budgets!G38 -> -234309.99 | K83: =Budgets!H32+Budgets!H36+Budgets!H38 -> -232329.99 | L83: =Budgets!I32+Budgets!I36+Budgets!I38 -> -248131.99 | M83: =Budgets!J32+Budgets!J36+Budgets!J38 -> -282538.23 | ... O83: =Budgets!L32+Budgets!L36+Budgets!L38 -> -222904.65
A85: Closing cash in SEL | D85: =SUM(D79:D83) -> #REF! | E85: =SUM(E79:E83) -> #REF! | F85: =SUM(F79:F83) -> #REF! | G85: =SUM(G79:G83) -> #REF! | H85: =SUM(H79:H83) -> #REF! | I85: =SUM(I79:I83) -> #REF! | J85: =SUM(J79:J83) -> #REF! | K85: =SUM(K79:K83) -> #REF! | ... O85: =SUM(O79:O83) -> #REF!
A87: Opening cash in SR | D87: 11824 | E87: =D91 -> #REF! | F87: =E91 -> #REF! | G87: =F91 -> #REF! | H87: =G91 -> #REF! | I87: =H91 -> #REF! | J87: =I91 -> #REF! | K87: =J91 -> #REF! | L87: =K91 -> #REF! | ... O87: =N91 -> #REF!
A88: Investment monies | F88: 1400000
